Workbook

Sheet Sprint Tracker
A1: Sprint List
A2: Objective : File ini digunakan oleh CI dan Deployment untuk mentracking List Sprint sepanjang tahun 2025
A3: User yang memiliki akses untuk edit adalah : Tim Deployment & CI
A4: Sprint 7, need tobe check by tim CI
O5: SPRINT 8
C6: CI Team | G6: CI Team | O6: 45907 | P6: 45920 | Q6: 45927 | R6: 45929 | S6: 45958 | V6: CI Team | W6: CI Team | X6: CI Team
A7: No | B7: Platform (Aplikasi) | C7: Dependency | D7: Background | E7: Objective | F7: Description | G7: Product Manager | H7: Requestor | I7: Chanel | J7: Expected Deployed | K7: Sprint | L7: Sprint Carry Over | M7: Story Point (if available) | N7: Update 08/28 | O7: Update 1 | P7: Update 2 | Q7: Update 3 | R7: Update 4 | S7: Update 5 | T7: Update 6 | U7: Update 7 | V7: PRD | W7: JIRA Ticket | X7: Picked Up
A8: 1 | B8: AMO | D8: QR code phase 2 (adding button to top up canvassing during pengiriman CITA di AMO offline) | E8: QR code phase 2 (adding button to top up canvassing during pengiriman CITA di AMO offline) | F8: QR code phase 2 (adding button to top up canvassing during pengiriman CITA di AMO offline) | G8: Marcha | H8: Duta | J8: 45870 | K8: Sprint 6 | O8: Done
A9: 2 | B9: AMO | D9: Canvassing = Product assortment / carousel untuk focused product | E9: Canvassing = Product assortment / carousel untuk focused product | F9: Canvassing = Product assortment / carousel untuk focused product follow B2B | G9: Marcha | H9: Duta | J9: 45870 | K9: Sprint 6 | O9: Done
A10: 3 | B10: AMO | D10: SKU reminder untuk focused product sebelum dilakukan payment | E10: SKU reminder untuk focused product sebelum dilakukan payment | F10: SKU reminder untuk focused product sebelum dilakukan payment (Re-offering) | G10: Marcha | H10: Duta | J10: 45870 | K10: Sprint 6 | O10: Done
A11: 4 | B11: AMO | D11: Mendapatkan progress achievement PG (Unique Call, Volume canvass & CITA) dari PBI Reporting AMO | E11: Mendapatkan progress achievement PG (Unique Call, Volume canvass & CITA) dari PBI Reporting AMO | F11: Mendapatkan progress achievement PG (Unique Call, Volume canvass & CITA) dari PBI Reporting AMO | G11: Marcha | H11: Duta | J11: 45870 | K11: Sprint 6 | O11: Done
A12: 5 | B12: AMO | D12: Add tab "Laporan" untuk menunjukan progress achievement PG (Unique Call, Volume canvass & CITA) | E12: Add tab "Laporan" untuk menunjukan progress achievement PG (Unique Call, Volume canvass & CITA) | F12: Add tab "Laporan" untuk menunjukan progress achievement PG (Unique Call, Volume canvass & CITA) | G12: Marcha | H12: Duta | J12: 45870 | K12: Sprint 6 | O12: Done
A13: 6 | B13: AYO Principal | D13: Elevate Automation | E13: Elevate - Data Entry | F13: Capability untuk user bisa melakukan WO atau guideline submission | G13: Ariph | H13: Nika | J13: 45930
A14: 7 | B14: AYO Principal | D14: Elevate Automation | E14: Elevate - Email generator | F14: Capability elevate untuk generate email ke zone sehubungan dengan WO/guideline yang diinputkan di Elevate | G14: Ariph | H14: Nika | J14: 45930 | K14: Sprint 8
A15: 8 | B15: AYO Principal | D15: Elevate Automation | E15: Elevate - Cycle calendar | F15: Capability untuk show dan filter WO atau guideline yang impact ke waktu week tertentu | G15: Ariph | H15: Nika | J15: 45930
A16: 9 | B16: Control Tower | D16: Seamless data upload | E16: CT Update Schedulling and rework data entry template | F16: Flexybility update data in CT by add feature schedule | G16: Ariph | H16: Sri P | J16: 45930 | K16: Sprint 7 | L16: Sprint 8 | N16: carry over to the next sprint
A17: 10 | B17: AMO | D17: Canvassing | E17: Fitur Scan QR pada mode Canvassing | F17: Edit text Kunjungan Non Downline menjadi "Mulai Kunjungan", direct page to fitur Scan QR dan akan ter-mapping ke customer registered HMS as map to RE | G17: Marcha | H17: Duta | J17: 45930 | K17: Sprint 7 | N17: covered in sprint 7
A18: 11 | B18: AMO plus | D18: Filter type outlet di maps | E18: Filter type outlet di maps | F18: Selecting toko yang tampil di peta pada AMO | G18: Maulana | H18: Duta | J18: 45930 | K18: Sprint 7
A19: 12 | B19: AMO Plus | D19: Search downline PG | E19: Search downline PG | F19: Fitur search downline salesman/mitra di AMO+ (seperti di AMO Existing) | G19: Maulana | H19: Duta | J19: 45930 | K19: Sprint 7
A20: 13 | B20: AMO Plus | D20: Remaining stock product PG | E20: Remaining stock product PG | F20: Info sisa stok yang dibawa PG di page transaksi | G20: Maulana | H20: Duta | J20: 45930 | K20: Sprint 7
A21: 14 | B21: AMO Plus | D21: Price product di page transaksi | E21: Price product di page transaksi | F21: Info price product / SKU di halaman transaksi | G21: Maulana | H21: Duta | J21: 45930 | K21: Sprint 7
A22: 15 | B22: AMO Plus | D22: Reconciliation report | E22: Reconciliation report | F22: Menggabungkan LPU dan BPPB pada AMO | G22: Maulana | H22: Duta | J22: 45930 | K22: Sprint 7
A23: 16 | B23: AYO Mitra Plus | D23: Manual assign by PG khususnya jika ada PG yg tidak masuk | E23: Manual assign by PG khususnya jika ada PG yg tidak masuk | F23: Manual assign by PG khususnya jika ada PG yg tidak masuk | G23: Maulana | H23: Sri P | J23: 45930 | K23: Sprint 7
A24: 17 | B24: AYO Mitra Plus | D24: Grouping order by PG di hari H-1 | E24: Grouping order by PG di hari H-1 | F24: Grouping order by PG di hari H | G24: Maulana | H24: Sri P | J24: 45930 | K24: Sprint 7
A25: 18 | B25: AYO Mitra Plus | D25: Mitra tetap dapat melakukan cluster, meskipun masih ada pesanan dalam pengiriman | E25: Mitra tetap dapat melakukan cluster, meskipun masih ada pesanan dalam pengiriman | F25: Mitra tetap dapat melakukan proses pesanan, ketika ada pesanan baru | G25: Maulana | H25: Sri P | J25: 45930 | K25: Sprint 7
A26: 19 | B26: AYO Mitra Plus | D26: Fixing miss cluster | E26: Fixing miss cluster | F26: Fixing miss cluster | G26: Maulana | H26: Sri P | J26: 45930 | K26: Sprint 7
A27: 20 | B27: AYO Mitra Plus | D27: Simply Initial load reccomendation | E27: Simply Initial load reccomendation | F27: Simply Initial load reccomendation | G27: Maulana | H27: Sri P | J27: 45930 | K27: Sprint 7
A28: 21 | B28: MyHero | D28: Hygiene document | E28: LPU | F28: Saat ini yang muncul ketika cetak LPU hanyalah tanggal cetak, bukan tanggal journeynya Add 1 field for tanggal journey | G28: Melissa Tio | H28: Nika | J28: 45930 | K28: Sprint 7
A29: 22 | B29: MyHero | D29: Multicategory document | E29: BPPB, Add load | F29: On top of kode barang, penambahan Prod name (masking) di BPPB untuk FMCG | G29: Melissa Tio | H29: Nika | J29: 45930 | K29: Sprint 7
A30: 23 | B30: MyHero | D30: Multicategory document | E30: BPPB, Add load | F30: Printed doc DN after jourgen dan input initial load by back end | G30: Melissa Tio | H30: Nika | J30: 45930 | K30: Sprint 7
A31: 24 | B31: CITA | D31: Detect distinct SKU and pack quantity inside paket produk | E31: Detect distinct SKU and pack quantity inside paket produk | F31: To be able to detect quantity of packs inside Paket Produk | G31: Nessia | H31: Sri/CI | J31: 45930 | K31: Sprint 7 | N31: covered in sprint 7
A32: 25 | B32: CITA | D32: Category Standardization | E32: Category Standardization | F32: To standardize category chip shown on CITA to refer to category on Product Principal instead of referring on "subfamily" column on produk supplier menu on Control Tower | G32: Nessia | H32: Sri/CI | J32: 45930 | K32: Sprint 7 | N32: covered in sprint 7
A33: 26 | B33: AYO Kasir | D33: Eliminate double transaction happened in AYO due unresponsive Payment gateway | E33: [CDE-25950] AYO Kasir - Limit transaction when FF spam selesaikan pesanan button more than 1x | G33: Marcha | H33: Ida/Adnan | J33: 45930 | K33: Sprint 7 | N33: deployed, 13 aug
A34: 27 | B34: AYO Kasir | D34: Integrate ORF request & process in AYO Kasir | E34: ORF | F34: ORF submission form & process in AYO Kasir to eliminate manual form & manual tracking | G34: Marcha | H34: Ida/Adnan | J34: 45930 | K34: Sprint 7 | N34: covered in sprint 7 ( tp butuh lintas sprint)
A35: 28 | B35: AYO Kasir | D35: Provide inventory data access to AYO Kasir Admin | E35: Stock Count & Stock Adjusment | F35: Laporan inventory harian per toko, per staff, per SKU untuk membantu daily stock take process | G35: Marcha | H35: Ida/Adnan | J35: 45930 | K35: Sprint 7 | N35: covered in sprint 7 ( tp butuh lintas sprint)
A36: 29 | B36: AYO Kasir | D36: Support perpindahan stock antar toko (pemerataan Limited stock & LOGD) | E36: Stock Transfer Store to Store | F36: Stock dapat dipindahkan antar toko (dan antar SLOC) melalui fitur stock movement (beserta history nya) yang dapat di tracking, termasuk dengan penyesuaian di SAP nya | G36: Marcha | H36: Ida/Adnan | J36: 45930 | K36: Sprint 7 | N36: covered in sprint 7 ( tp butuh lintas sprint)
A37: 30 | B37: AYO Kasir | D37: Support loyalty/miles program di IQOS Partne dan allow customization | E37: IP Miles, VAP, Delivery Partner Program | F37: IP memiliki beberapa loyalty toolbox option yang bisa dipilih oleh masing-masing mereka, menyesuaikan dengan kebutuhan bisnis | G37: Marcha | H37: Ida/Adnan | J37: 45930 | K37: Sprint 7 | N37: covered in sprint 7 ( tp butuh lintas sprint)
A38: 31 | B38: AYO Kasir | D38: Provide inventory management & tracking untuk AYO Kasir admin dalam memindahkan stock ke setiap staff | E38: Stock Transfer Admin to Staff | F38: AYO Kasir Admin memerlukan control terhadap inventory management & movement di setiap staff nya, termasuk visibility terkait stock on hand dan movement history yang bisa di track setiap saat untuk monitoring & stock audit | G38: Marcha | H38: Ida/Adnan | J38: 45930 | K38: Sprint 7 | N38: covered in sprint 7
A39: 32 | B39: AYO Kasir | D39: Provide codentify form box for each device purchased --> link device | E39: Device Codentify Input for every device purchased in same order id | F39: Setiap device yang terdapat di dalam suatu transaksi, memerlukan input informasi ke dalam system untuk codentify untuk setiap device. Saat ini, AYO Kasir hanya | G39: Marcha | H39: Ida/Adnan | J39: 45930 | K39: Sprint 7 | N39: covered in sprint 7
A40: 33 | B40: AYO Kasir | D40: Voucher enhancement | E40: Voucher enhancement | F40: Voucher Product Limitation Adjustment | G40: Marcha | H40: Ida/Adnan | J40: 45930 | K40: Sprint 7 | N40: covered in sprint 7
A41: 34 | B41: AYO Kasir | D41: Improve product demo experience for better trial & acceptance | E41: Taste Advisory | F41: Taste Advisory feature yang saat ini tersedia di Qoncierge untuk bisa di integrate ke AYO Kasir untuk seamless journey & data connection (konsumen & transaksi) | G41: Marcha | H41: Ida/Adnan | J41: 45930 | K41: Sprint 7 | N41: covered in sprint 7
A42: 35 | B42: AYO Kasir | D42: Enable AYO Kasir Web Version to be fully operated in IOS based device (All Pages) | E42: AYO Kasir responsive (phase 2) - Compatibility in mobile version (web) | F42: Enable AYO Kasir web to be accessed in mobile browser | H42: Ida/Adnan | J42: 45955 | K42: Sprint 8 (prio1)
A43: 36 | B43: AYO Kasir | D43: Enable AYO Kasir Web Version to be fully operated in IOS based device (Catalog Pages) | E43: AYO Kasir responsive (phase 3) - Compatibility in mobile version (catalog) | F43: Enable AYO Kasir web to be accessed in mobile browser | H43: Ida/Adnan | J43: 45955 | K43: Sprint 8 (prio1)
A44: 37 | B44: AYO Kasir | D44: Data Security - Global Requirement | E44: Pentest Finding: Show generic error message to omit info if phone number exists in database | F44: As a part of security finding, we need to create 1 login page for user to insert phone number and passcode, and show a generic error message to users. The deadline to fix the finding is in October 2025. | H44: Ida/CI | J44: 45955 | K44: Sprint 8 (prio1)
A45: 38 | B45: AYO Kasir | D45: Improve ORF accuracy by each touchpoint to ensure sufficient inventory management & security | E45: AYO Kasir - ORF Warehouse Replenishment - Jira (Phase 3) - PKM ORF | F45: AYO Kasir to be automatically provide ORF Qty recommendation for each touchpoints/coach based on Sales historical & current stock | G45: Sean | H45: Ida/Adnan | J45: 45955 | K45: Sprint 8 (prio1)
A46: 39 | B46: AYO Kasir | D46: Provide proper replacement service with proper process in terms of inventory & finance management, similar to DCE configuration | E46: phase 1: input replacement transaction phase 2: QURE in AYO Kasir | F46: Feature to enable SFP device replacement in AYO Kasir by inputting replacement transaction and having DCE API to check device eligibility & record the replacement. | H46: Ida/Adnan | J46: 45955 | K46: Sprint 8 (prio1)
A47: 40 | B47: AYO Kasir | D47: Offline mode AYO Kasir & data synchronization (to SAP & DCE) ability | E47: Allow AYO Kasir to go with offline mode during network limitation and allow data synchronization when back to online | F47: Feature to enable AYO Kasir to be used in offline mode. Usually applicable for events, where there's no signal | H47: Ida/Adnan | J47: 45955 | K47: Sprint 8 (prio1)
A48: 41 | B48: AYO Kasir | D48: Access Management differentiation for each role | E48: a. SDR to assign TL to selected touchpoint b. TL to login AYO Kasir for few touchpoint using 1 account c. TL to assign runner to selected touchpoint d. Runner to login AYO Kasir for few touchpoint using 1 account | F48: Feature for Team Leader and runner to access several booth/kiosk accounts | H48: Ida/Adnan | J48: 45955 | K48: Sprint 8 (prio1)
A49: 42 | B49: AYO Kasir | D49: AYO Principal - Payment gateway configuration for each customer type in AYO Principal | E49: Feature in AYO Principle to set accurate TID, MID and customer type for payment gatewaty configuration | F49: Feature in AYO Principle to set accurate TID, MID and customer type for payment gatewaty configuration | H49: Ida/Adnan | J49: 45955 | K49: Sprint 8 (prio1)
A50: 43 | B50: AYO Kasir | D50: Add shopping bag as sellable item, with proper configuration in finance & transaction record | E50: a. Enable shopping bag transaction to be recognized by SAP b. Enable stock count of shopping bag in AYO Kasir | F50: Shopping Bag IQOS akan menjadi sellable item dan menjadi berbayar. | H50: Ida/Adnan | J50: 45955 | K50: Sprint 8 (prio1)
A51: 44 | B51: AYO Kasir | D51: Aligning coin reward from new leads/member registration with DSD purchase history | E51: Automatic coin rewards for leads/member registration - SRC IQOS Point | F51: Currently, there is matching process between the amount of leads/member registration with DSD purchase by SRC/SRC IQOS Point. This will result in discrepency and potential for fraud. | H51: Jess/Ragib | J51: 45955 | K51: Sprint 8 (prio1)
A52: 45 | B52: AYO Kasir | D52: Store-to-store transfer movement between SAP & AYO Kasir relies on Material Code. But, currently, these movement can't be fully captured, creating a gap between stock movement in AYO Kasir vs SAP | E52: Replacing material code with barcode for store-to-store movement between AYO Kasir & SAP | F52: Material code will be replaced by barcode to communicate between SAP & AYO Kasir for store-to-store. | G52: Sean
A53: 46 | B53: AYO Kasir | D53: Every new product launch requires publishing description and barcode to both AYO Principal and SAP. However, the process depends on the global PMI team to push the master material code, creating delays before AYO Kasir can recognize the product. | E53: Enable SAP to send Master Material Code directly for new product launches, so AYO Kasir can recognize it through inbound / outbound | F53: The system will be enhanced so SAP automatically pushes Master Material Code along with product details (description, barcode) to AYO Kasir, reducing dependency on the global PMI team. | G53: Sean
A54: 47 | B54: AYO Kasir | D54: Codentify is a code used to activate warranty for IQOS devices, stored in the global DCE database (not directly accessible). Currently, a bot gathers codes nationally and activates them, but it often fails and cannot detect duplicate or invalid codes, leaving them stuck in a loop. | E54: Implement a codentify checking mechanism to validate codes upfront before activation. | F54: The system will check codentify codes against a validation logic before processing. If a code is already used or invalid, it will be rejected upfront, preventing duplicate or invalid activations.
A55: 48 | B55: AYO Kasir | D55: Touchpoints are inconsistently classified across regions. For example, a key account in Bandung can sell both SFP & Non-SFP products, but a similar key account in Jakarta cannot. This inconsistency creates confusion and inefficiency | E55: Standardize and differentiate touchpoint types to ensure consistent SFP vs Non-SFP capabilities. | F55: The system will classify and unify touchpoints based on capability, ensuring key accounts have consistent rights to sell SFP and/or Non-SFP products regardless of region. | G55: Sean/Jodis
A56: 49 | B56: AYO Kasir | D56: Currently, IQOS products (SFP) are mixed with other products (e.g., BONDS) in reporting dashboards, causing confusion and lack of clarity. PowerBI dashboards cannot differentiate between SFP and Non-SFP product performance. | E56: Separate SFP vs Non-SFP products for clearer reporting and tracking. | F56: The system will tag and differentiate SFP vs Non-SFP products as distinct entities, enabling PowerBI dashboards to generate separate, accurate reports for each product type. | G56: Sean/Jodis
A57: 50 | B57: DTE | C57: Principal | D57: Streamlining coin approval process to become more efficient | E57: Change Process Flow - Coins Approval | F57: Currently, when user conduct RFT or Transfer to Pojok Bayar the process is very lengthy. Through this initiative, we propose a way on how to ensure this process can be conducted in more efficient manner. Approval from related Departments have already been secured. | G57: Michael | H57: Hanif/Jess | J57: 45955 | K57: Sprint 8 (prio1)
A58: 51 | B58: PBI | D58: FMCG performance | E58: Add multiple SKU selection PNM in KSI panamas | F58: Add multiple SKU selection PNM in KSI panamas | H58: Nika | J58: 45955 | K58: Sprint 8 (prio1)
A59: 52 | B59: AYO Kasir | D59: Delimit AYO Kasir Stock at SRC IQOS Point to enable higher stock input | E59: Delimit AYO Kasir Stock - SFP | F59: SRC IQOS Point have limitation in adding product due to stock number restriction. This limitation needs to be removed. | H59: Jess/Ragib | J59: 45955 | K59: Sprint 8 (prio1)
A60: 53 | B60: AYO Kasir | D60: Provide "Order Cart" / "Order Draft" Feature before continue to payment | E60: Draft order and reload after doing other activities | F60: Memungkinkan Frontliners untuk menyimpan dulu draft order (seperti cart di e-commerce) sebelum melanjutkan ke payment/complete transaksi, sering digunakan pada saat traffic lagi ramai, >1 konsumen yang perlu dilayani dan diantara mereka masih mungkin untuk merubah item pembelanjaan | H60: Ida/Adnan | J60: 45955 | K60: Sprint 8 (prio2)
A61: 54 | B61: AYO Kasir | D61: Separate product stock for each inventory type (similar to DCE) | E61: Stock categories - sellable & non-sellable - Guided Trial - Replacement - Display Stock - Trade in | F61: Replicate DCE (CEGID & CeApp), dimana stock untuk product sellable dan non-sellable (product demo stock, display, broken device from replacement, trade in) tidak tercampur menjadi satu, memastikan proses disposal & return ke WH termasuk financial record nya bisa tepat & akurat | H61: Ida/Adnan | J61: 45955 | K61: Sprint 8 (prio2)
A62: 55 | B62: DTE | C62: Principal | D62: Add Visual Overlay Guide | E62: Visual Overlay Guides for In-App Camera | F62: Currently, there are no guidelines for users taking photos, which may result in pictures being taken under various conditions, not follow to the specified guidance. To improve the quality and reliability of photo submissions during DTE missions in the AYO Toko mobile app, we are introducing key enhancements that address both user experience and submission integrity. Visual Overlay Guides for In-App Camera Users often struggle to align their photos with brand-specific display requirements (e.g., Coca-Cola planogram, Aqua Danone layout, cigarette display standards). This leads to frequent submission errors, rework, and delays in mission validation. To address this, we will implement visual overlay guides directly on the in-app camera. These semi-transparent templates will help users align their camera shots with the expected visual standards, reducing human error and ensuring compliance with planogram expectations. This feature enhances clarity and guidance during submission, resulting in higher-quality, brand-compliant data capture. | G62: Michael | H62: Hanif/Jess | J62: 45955 | K62: Sprint 8 (prio2)
A63: 56 | B63: DTE | D63: To understand user behaviour and provide analytics in DTE platform in AYO Toko | E63: GA AYO Toko Tracking | F63: Implement Google Analytics for DTE features in Ayo Toko to understand user behavior. | G63: Michael | H63: Hanif/Jess | J63: 45955 | K63: Sprint 8 (prio2)
A64: 57 | B64: DTE | D64: Send reminder to budget owner if it's below a pre-defined threshold to ensure the sustainability of the program | E64: Trade Program Budget Reminder | F64: Send reminder to budget owner if it's below a pre-defined threshold. Reminder will be sent regularly until certain actions are taken (program expired, additional budget, manual close/delete) | G64: Michael | H64: Hanif/Jess | J64: 45955 | K64: Sprint 8 (prio2)
A65: 58 | B65: DTE | C65: Principal | D65: DTE Avatar Entry Point | E65: New entry point for Mission Performance and Mission Guidance video | F65: New entry point for Mission Performance and Mission Guidance video | G65: Michael | H65: Hanif/Jess | J65: 45955 | K65: Sprint 8 (prio2)
A66: 59 | B66: DTE | C66: Principal, CITA | D66: DTE CITA Missions | E66: Reactivate inactive CITA users and increase the pool size of active CITA users | F66: Introduce Missions on CITA | G66: Michael | K66: Sprint 8
A67: 60 | B67: DTE | D67: Recaptured Image Detection using Moire Pattern | E67: Detect and flag Moiré patterns in submitted images to identify potential manipulation and prevent fraudulent execution verification. | F67: Detect and flag Moiré patterns in submitted images to identify potential manipulation and prevent fraudulent execution verification. | G67: Andrew | H67: Ahmad/Jeffry | J67: 45955 | K67: Sprint 8 (prio2)
A68: 61 | B68: AMO Plus | D68: AYO Mitra Plus Hybrid Mode | E68: AYO Mitra Plus Hybrid Mode | F68: AMO Existing bisa digunakan dengan AYO Mitra yang baru | G68: Jimmy Hernomo / Yusron | H68: Sri P | J68: 45955 | K68: Sprint 8 (prio2)
A69: 62 | B69: AYO Mitra | D69: Cluster mapping | E69: Capability AYO Mitra Plus untuk export dan import hasil clutering agar memudahkan proses revisi cluster. (akan dihandle dari principal dan internal HMS bisa suggest cluster via principal) Untuk new customer akan ikut ditarik datanya dan ada flagging "new" (tersedia di mid aug) Jika PIC melakukan update Skenario : jika zone melakukan update panel di CT, maka data panel yang baru akan ikut ditarik | F69: Capability AYO Mitra Plus untuk export dan import hasil clutering agar memudahkan proses revisi cluster. Untuk new customer akan ikut ditarik datanya dan ada flagging "new". Skenario : jika zone melakukan update panel di CT, maka data panel yang baru akan ikut ditarik | H69: Sri P | J69: 45955 | K69: Sprint 8 (prio2)
A70: 63 | B70: AYO Mitra | D70: Cluster mapping | E70: - Jika ada update panel di CT, maka panel baru tersebut akan secara otomatis terassign ke PG di AYO Mitra. '- Panel baru akan diassignkan ke PG terdekat. Hasil clustering bisa dilihat CT (misal di Retailer Mapping ada PG ID nya), sehingga bisa dijadikan bahan review | F70: - Jika ada update panel CITA di CT, maka panel baru tersebut akan secara otomatis terassign ke PG di AYO Mitra. - panel baru akan diassignkan ke PG terdekat. Hasil clustering bisa dilihat CT (misal di Retailer Mapping ada PG ID nya), sehingga bisa dijadikan bahan review | H70: Sri P | J70: 45955 | K70: Sprint 8 (prio2)
A71: 64 | B71: Ayo Qoncierge Coach | D71: Test Advisory Revamp | E71: Create website builder for Taste Advisory Page | F71: Business can set up for catalog matrix & page design for Taste Advisory | G71: Wildan & Michel | H71: Mustika Nagari | K71: Sprint 8 (prio 0)
A72: 65 | B72: AYO Principal | D72: Duplication Number in Retailer Mapping | E72: Currently there are duplicated phone number between CT and iSMS | F72: to avoid possible bugs happening we need to ensure that CT has a unique phone number between each retailer. Still on discussion to fix this | G72: Ariph
A73: 66 | B73: AYO Principal | D73: Validation Retailer Mapping | E73: If user principal updating a duplicated value for phone number, it will rejected by the system. | F73: if user uploading duplicated phone number, then it will be rejected for that specific row, and shown to the user. | G73: Ariph
A74: 67 | B74: CITA | C74: Principal, OSEM, TSM, My Hero, AMO | D74: [CITA Loyalty] dormant users keep increasing despite the rapid increase of DAU from dijamin1klik. | E74: retain users and increase regular purchasers through loyalty program, learning from AYO DTE | G74: Jere, Michael | H74: CI/Commstrat | K74: Sprint 8
A75: 68 | B75: CITA | C75: Principal, OSEM, TSM | D75: [CITA Coachmark] no guidance exists on CITA to help users navigate important activities by themselves | E75: user can learn to operate the platform by themselves and reduce dependency to FF | F75: enable coachmark for every user, at the right time, tailored for each user type-- dormant, regular, etc. In the context of D1K, the coachmark is adaptive. By adaptivemeans the coachmark is tailored based on FF’s stock recommendations.​ | G75: Jere | H75: CI | K75: Sprint 8
A76: 69 | B76: CITA | C76: Principal, DTE, MyHero | D76: [Instant CN Rewards] Currently, CN Rewards are only applied to Direct Selling activities, and the reward distribution is not immediate—it can only be redeemed during the next visit by the salesman, which typically occurs every two weeks. | E76: Enabling instant reward distribution to digital platform | F76: Instant CN Rewards, we would like to allocate a portion of the coins to CITA, allowing users to redeem digital vouchers or use them to offset the total order value when purchasing through CITA | G76: Jere | H76: Trade Team | K76: Sprint 8
A77: 70 | B77: CITA | C77: Principal, OSEM, TSM | D77: [CITA PN Integration to OSEM&TSM] Currently, CITA relies on manual audience selection for sending push notifications, which results in significant administrative effort and static targeting. | E77: To improve efficiency and relevance when sending push notification to users | F77: Push Notification Integration with TSM and OSEM This integration will enable trigger- and condition-based notifications, as well as dynamic audience segmentation. As a result, notifications will reach the right users at the right time, while also reducing manual workload for our admins. | G77: Jere | H77: CI/Deployment | K77: Sprint 8
A78: 71 | B78: MyAyo Web | C78: AYO Toko | D78: Metahuman for PD Support at SRC | E78: SRC Customer have an access for product knowledge, especially for IQOS BONDS | F78: Metahuman support by Global Vendor Synthesia. Consumer can access through QR scanning after registration at SRC as Leads | G78: Wildan | K78: Sprint 8 (prio 0)
A79: 72 | B79: SSR | D79: LAS/LANU Registration for KA (IDM) | E79: Facilitate LAS LANU for self registration & Device Link | F79: Website that LAS/LANU can access for registration process & device link | G79: Wildan | H79: Ivan Orlando | K79: September (IT Region)
A80: 73 | B80: Principal SFP | C80: AYO Toko, My Hero, iSMS, SAP | D80: Customer registration for IQOS Partner (Phase I) | E80: Create seamless system integration for IQOS Partner Registration | F80: Create seamless system integration for IQOS Partner Registration, & initial support invoice automatitation | G80: Wildan | H80: Mustika Nagari | K80: Sprint 8 (prio 0)
A81: 74 | B81: Ayo Qoncierge Coach | C81: Tania | D81: Tania for SFP | E81: Interactive AI to support frontliner incentive | F81: Tanai will giving information & recommendation of the frontliner achievement status | G81: Wildan | K81: Sprint 8 (prio 0)
A82: 75 | B82: AYO Principal | D82: CMS For Tania | E82: To create CMS for Tania in AYO Principal | F82: for this phase it will be simple editor and add edit delete content in AYO Principal. | G82: Ariph | H82: Arum | K82: Sprint 7 (Sept) | L82: Sprint 8
A83: 76 | B83: AYO PRINCIPAL | D83: Database Push Notification | E83: Improve logging database for push notification CITA on ayo_master | F83: Enhancement include: 1) Adding pnrl_id column 2) Remove execution_count 3) Make every PN execution recorded as 1 row (not updated). https://wiki.app.pconnect.biz/x/t4BzTg https://jira.app.pconnect.biz/browse/CDE-27312 | G83: Livi / Jere | H83: Livi | J83: 45955 | K83: Sprint 8 (prio2)
A84: 77 | B84: AYO PRINCIPAL | D84: Create New Service for SMS Request to Infobip | E84: Prevent SMS request queueing system in the future to be challenging | F84: Create new service dedicated for SMS request to Infobip https://jira.app.pconnect.biz/browse/CDE-27686 | G84: Livi | H84: Diana/Zhafran/Livi | J84: 45955 | K84: Sprint 8 (prio1)
A85: 78 | B85: AYO PRINCIPAL | D85: MITA x OSEM, New Audience Paneling for MITA | E85: Improve current way to generate panel MITA to be more seamless and flexible. Currently relying heavily on pipeline & logic from IT DATA. | F85: Enhancement include: 1) Adding new golden records related to MITA 2) Create new S3 AYO for Wiz to consume the panel 3) Create new MITA Config menu on AYO PRINCIPAL (select audience osem, retrieve phone number, export to S3 AYO, split by panel category, config logic for salesman last visit, etc) https://wiki.app.pconnect.biz/x/0AK0Sg | G85: Livi / Zhafran | H85: Shinta/Livi | J85: 45955 | K85: Sprint 8 (prio1)
A86: 79 | B86: My Hero Backend - CDM Payment Gateway | D86: Cater Business Plan to Go with TA for PANAMAS PRE-ORDER Cash Collection | E86: Exclude Receipt PANAMAS PRE-ORDER Data Ingestion to Payment Gateway Flow | F86: Exclude booking_code "TARE...." from receipt data ingestion payment gateway (my hero ipad setoran page, my hero backend CDM menu, including receipt report, settlement report, disbursement report, etc) | G86: Livi / Melissa Tio | H86: Rangga | J86: 45955 | K86: Sprint 8 (prio1)
A87: 80 | B87: My Hero Backend - TA Cash Collection | D87: Create New Menu for TA Cash Collection | E87: Facilitate CPO / HO to identify how much amount of delivered order is collected by cash vs QRIS | F87: There will be a new menu on MHBE dedicated for TA Cash Collection, contain table with columns: Area, Salespoint, TA Code, TA Name, Total SO, Delivery Date, Total Delivered Amount, Uang Tunai, E-Payment [CDE-27276] TA Delivery Report | G87: Livi / Melissa Tio | H87: Bu Vivi (Commercial) / Mas Pram | J87: 45955 | K87: Sprint 8 (prio1)
A88: 81 | B88: My Hero Backend - TA Cash Collection | D88: Create New Menu for TA Delivery Status Report | E88: Facilitate CPO / HO to identify how many orders has been delivered or cancelled from TA (TMS app) | F88: There will be a new menu on MHBE dedicated for TA Cash Collection, contain table with columns: TA Journey Code, TA Name, SO Order Date, Delivery Date, Status, Invoice Amount, Invoice Code, Invoice Legal Number, Territory Code, Customer Code, Customer Name, FF Name, Entity [CDE-27347] Delivery Status (Report) | G88: Livi / Melissa Tio | H88: Bu Vivi (Commercial) / Mas Pram | J88: 45955 | K88: Sprint 8 (prio1)
A89: 82 | B89: AMO Plus | D89: Sometimes PG completing delivery more than 6 p.m. when admin has gone home so they cannot help PG to carry over incomplete order to next day | E89: To avoid incomplete order to auto-cancelled when admin has finished their shift | F89: Carry over pengiriman CITA yang belum bisa diantarkan ke besok hari dari AMO PG | G89: Jimmy H./ M. Yusron
A90: 83 | B90: AMO Existing & Plus | D90: Needed to help prepare the product D-1 prior to delivery | E90: To effectively categorized packaged product by the PG name | F90: Invoice pada transaksi selain memunculkan nama PG, juga no HP PG | G90: Jimmy H./ M. Yusron
A91: 84 | B91: AMO Plus | D91: To avoid calculation error when the visit is retrieved via PBI (or any other reporting mechanism) | E91: To avoid calculation error when the visit is retrieved via PBI (or any other reporting mechanism) | F91: Update visit status when Selesaikan Pesanan (currently in DWH visit status is 0, even the delivery has been completed) | G91: Jimmy H./ M. Yusron
A92: 85 | B92: AMO Plus | D92: Adanya kemungkinan duplikasi atau double counting pada Data PG Performance Tracker | E92: Fixing the calculation of Data PG Performance Tracker | F92: Calculation PG Performance Tracker yang dikirimkan melalui reverse ETL diharapkan bisa disummary tiap periode performance sehingga perlu enhancement juga dari sisi AMO | G92: Jimmy H./ M. Yusron | H92: Jimmy H.
A93: 86 | B93: AMO Existing & AMO Plus | D93: The logic can cause processing inefficiency and high server load in a long run | E93: More effective process (if still needed) | F93: Change the logic from actively query-ing the data from data order table and whitelisting table in database upon completion of delivery order to using flagging on file download. | G93: Jimmy H./ M. Yusron
A94: 87 | B94: AMO Plus | D94: To monitor PG activity and calculate a more accurate SLA | E94: To monitor PG activity and calculate a more accurate SLA | F94: Upon completion of CITA Delivery Order it is required to record the Longitude and Latitude | G94: Jimmy H./ M. Yusron
A95: 88 | B95: AYO Toko | D95: Home Page Revamp | E95: More engaging content in homepage will be led to more active user | F95: -Publish new configuration at anytime without deployment -Section menu can be arranged in principal -Tile menu can be arrange & hide from principal | G95: M. Yusron | J95: 45955 | K95: Sprint 8
A96: 89 | B96: AYO Toko | D96: Belanja Page Revamp | E96: Tidier and attaractive Belanja poge will attract to more good experience in Belanja | F96: -Collect all history order in one page -Merged cart page and checkout page into 1 pasge only | G96: M. Yusron | J96: 45955 | K96: Sprint 8
A97: 90 | B97: AYO Toko | D97: Non Login experience | E97: Dummy homepage with B2B & DTE menu end to end | F97: -Create real order that will be proceed when retailer log-in/registered -Answer real DTE mission with all type of question detail | G97: M. Yusron | J97: 45955 | K97: Sprint 8
A98: 91 | B98: AYO Toko | D98: Pinang Raya performa - Bank Raya -Pojok Modal | E98: SRC Partnership X Bank Raya | F98: -connection to Pojok Modal AYO Toko with pinang performan bank raya -Configure panel in principal -user can apply for a loan at Bank Raya | G98: M. Yusron | H98: Dhea Rizka | J98: 45955 | K98: Sprint 8
A99: 92 | B99: AYO Toko | D99: Shopping Bag - AYO Toko SFP | E99: The sale of SFP shopping bags provides PMI with additional income categorized as other revenue | F99: -Create a new 'Others' category in AYO Toko -Partners can purchase SFP shopping bags directly through the platform | G99: M. Yusron | H99: Reza Aryo | J99: 45955 | K99: Sprint 8
A100: 93 | B100: AYO Toko | D100: Use Metahuman in AYO Toko for lead generation and to enhance user engagement | E100: Display a QR code in AYO Toko to support lead generation and strengthen SRC’s business operations by enabling seamless and accurate knowledge transfer | F100: -Display a QR code and link on Ayo Toko to show the Metahuman video experience -Enable video metahuman from both retailer and consumer devices to ensure broader engagement | G100: M. Yusron | H100: Wildan | J100: 45955 | K100: Sprint 8
...

Sheet Sprint 8  with Prio
A1: Sprint List | H1: AYO Toko | J1: (3) | K1: DTE | L1: 12
A2: Objective : File ini digunakan oleh CI dan Deployment untuk mentracking List Sprint sepanjang tahun 2025 | H2: MyHero | I2: =66 -> 66 | J2: (1) | K2: AYO Kasir | L2: 97
A3: User yang memiliki akses untuk edit adalah : Tim Deployment & CI | J3: (2) | K3: CITA | L3: 50 | M3: 10 | N3: allocate to AYO Kasir
A4: Sprint 7, need tobe check by tim CI | K4: AYO Mitra
K5: AMO | L5: 107 | O5: SPRINT 8
C6: CI Team | G6: CI Team | L6: assume 1 sprint = 10 mandays | O6: 45904 | P6: 45920 | Q6: 45927 | R6: 45929 | S6: 45958
A7: No | B7: Platform (Aplikasi) | C7: Dependency | D7: Background | E7: Objective | F7: Description | G7: Product Manager | H7: Requestor | I7: Chanel | J7: Expected Deployed | K7: Sprint | L7: Rank Prio | M7: Sprint Carry Over | N7: Update 0 8/28 | O7: Update 1 | P7: Update 2 | Q7: Update 3 | R7: Update 4 | S7: Update 5 | T7: Update 6 | U7: Update 7 | V7: JIRA | W7: Mandays
A8: 1 | B8: AMO | D8: QR code phase 2 (adding button to top up canvassing during pengiriman CITA di AMO offline) | E8: QR code phase 2 (adding button to top up canvassing during pengiriman CITA di AMO offline) | F8: QR code phase 2 (adding button to top up canvassing during pengiriman CITA di AMO offline) | G8: Marcha | H8: Duta | J8: 45870 | K8: Sprint 6 | O8: Done
A9: 2 | B9: AMO | D9: Canvassing = Product assortment / carousel untuk focused product | E9: Canvassing = Product assortment / carousel untuk focused product | F9: Canvassing = Product assortment / carousel untuk focused product follow B2B | G9: Marcha | H9: Duta | J9: 45870 | K9: Sprint 6 | O9: Done
A10: 3 | B10: AMO | D10: SKU reminder untuk focused product sebelum dilakukan payment | E10: SKU reminder untuk focused product sebelum dilakukan payment | F10: SKU reminder untuk focused product sebelum dilakukan payment (Re-offering) | G10: Marcha | H10: Duta | J10: 45870 | K10: Sprint 6 | O10: Done
A11: 4 | B11: AMO | D11: Mendapatkan progress achievement PG (Unique Call, Volume canvass & CITA) dari PBI Reporting AMO | E11: Mendapatkan progress achievement PG (Unique Call, Volume canvass & CITA) dari PBI Reporting AMO | F11: Mendapatkan progress achievement PG (Unique Call, Volume canvass & CITA) dari PBI Reporting AMO | G11: Marcha | H11: Duta | J11: 45870 | K11: Sprint 6 | O11: Done
A12: 5 | B12: AMO | D12: Add tab "Laporan" untuk menunjukan progress achievement PG (Unique Call, Volume canvass & CITA) | E12: Add tab "Laporan" untuk menunjukan progress achievement PG (Unique Call, Volume canvass & CITA) | F12: Add tab "Laporan" untuk menunjukan progress achievement PG (Unique Call, Volume canvass & CITA) | G12: Marcha | H12: Duta | J12: 45870 | K12: Sprint 6 | O12: Done
A13: 6 | B13: AYO Principal | D13: Elevate Automation | E13: Elevate - Data Entry | F13: Capability untuk user bisa melakukan WO atau guideline submission | G13: Nessia | H13: Nika | J13: 45930 | K13: Sprint 7
A14: 7 | B14: AYO Principal | D14: Elevate Automation | E14: Elevate - Email generator | F14: Capability elevate untuk generate email ke zone sehubungan dengan WO/guideline yang diinputkan di Elevate | G14: Nessia | H14: Nika | J14: 45930 | K14: Sprint 7
A15: 8 | B15: AYO Principal | D15: Elevate Automation | E15: Elevate - Cycle calendar | F15: Capability untuk show dan filter WO atau guideline yang impact ke waktu week tertentu | G15: Nessia | H15: Nika | J15: 45930 | K15: Sprint 7
A16: 9 | B16: Control Tower | D16: Seamless data upload | E16: CT Update Schedulling and rework data entry template | F16: Flexybility update data in CT by add feature schedule | G16: Nessia | H16: Sri P | J16: 45930 | K16: Sprint 7 | M16: Sprint 8 | N16: carry over to the next sprint
A17: 10 | B17: AMO | D17: Canvassing | E17: Fitur Scan QR pada mode Canvassing | F17: Edit text Kunjungan Non Downline menjadi "Mulai Kunjungan", direct page to fitur Scan QR dan akan ter-mapping ke customer registered HMS as map to RE | G17: Marcha | H17: Duta | J17: 45930 | K17: Sprint 7 | N17: covered in sprint 7
A18: 11 | B18: AMO plus | D18: Filter type outlet di maps | E18: Filter type outlet di maps | F18: Selecting toko yang tampil di peta pada AMO | G18: Maulana | H18: Duta | J18: 45930 | K18: Sprint 7
A19: 12 | B19: AMO Plus | D19: Search downline PG | E19: Search downline PG | F19: Fitur search downline salesman/mitra di AMO+ (seperti di AMO Existing) | G19: Maulana | H19: Duta | J19: 45930 | K19: Sprint 7 | N19: covered in sprint 7
A20: 13 | B20: AMO Plus | D20: Remaining stock product PG | E20: Remaining stock product PG | F20: Info sisa stok yang dibawa PG di page transaksi | G20: Maulana | H20: Duta | J20: 45930 | K20: Sprint 7 | N20: covered in sprint 7
A21: 14 | B21: AMO Plus | D21: Price product di page transaksi | E21: Price product di page transaksi | F21: Info price product / SKU di halaman transaksi | G21: Maulana | H21: Duta | J21: 45930 | K21: Sprint 7 | N21: covered in sprint 7
A22: 15 | B22: AMO Plus | D22: Reconciliation report | E22: Reconciliation report | F22: Menggabungkan LPU dan BPPB pada AMO | G22: Maulana | H22: Duta | J22: 45930 | K22: Sprint 7 | N22: covered in sprint 7
A23: 16 | B23: AYO Mitra Plus | D23: Manual assign by PG khususnya jika ada PG yg tidak masuk | E23: Manual assign by PG khususnya jika ada PG yg tidak masuk | F23: Manual assign by PG khususnya jika ada PG yg tidak masuk | G23: Maulana | H23: Sri P | J23: 45930 | K23: Sprint 7 | N23: covered in sprint 7
A24: 17 | B24: AYO Mitra Plus | D24: Grouping order by PG di hari H-1 | E24: Grouping order by PG di hari H-1 | F24: Grouping order by PG di hari H | G24: Maulana | H24: Sri P | J24: 45930 | K24: Sprint 7 | N24: covered in sprint 7
A25: 18 | B25: AYO Mitra Plus | D25: Mitra tetap dapat melakukan cluster, meskipun masih ada pesanan dalam pengiriman | E25: Mitra tetap dapat melakukan cluster, meskipun masih ada pesanan dalam pengiriman | F25: Mitra tetap dapat melakukan proses pesanan, ketika ada pesanan baru | G25: Maulana | H25: Sri P | J25: 45930 | K25: Sprint 7 | N25: covered in sprint 7
A26: 19 | B26: AYO Mitra Plus | D26: Fixing miss cluster | E26: Fixing miss cluster | F26: Fixing miss cluster | G26: Maulana | H26: Sri P | J26: 45930 | K26: Sprint 7 | N26: covered in sprint 7
A27: 20 | B27: AYO Mitra Plus | D27: Simply Initial load reccomendation | E27: Simply Initial load reccomendation | F27: Simply Initial load reccomendation | G27: Maulana | H27: Sri P | J27: 45930 | K27: Sprint 7 | N27: covered in sprint 7
A28: 21 | B28: MyHero | D28: Hygiene document | E28: LPU | F28: Saat ini yang muncul ketika cetak LPU hanyalah tanggal cetak, bukan tanggal journeynya Add 1 field for tanggal journey | G28: Hadi Pram | H28: Nika | J28: 45930 | K28: Sprint 7
A29: 22 | B29: MyHero | D29: Multicategory document | E29: BPPB, Add load | F29: On top of kode barang, penambahan Prod name (masking) di BPPB untuk FMCG | G29: Hadi Pram | H29: Nika | J29: 45930 | K29: Sprint 7
A30: 23 | B30: MyHero | D30: Multicategory document | E30: BPPB, Add load | F30: Printed doc DN after jourgen dan input initial load by back end | G30: Hadi Pram | H30: Nika | J30: 45930 | K30: Sprint 7
A31: 24 | B31: CITA | D31: Detect distinct SKU and pack quantity inside paket produk | E31: Detect distinct SKU and pack quantity inside paket produk | F31: To be able to detect quantity of packs inside Paket Produk | G31: Nessia | H31: Sri/CI | J31: 45930 | K31: Sprint 7 | N31: covered in sprint 7
A32: 25 | B32: CITA | D32: Category Standardization | E32: Category Standardization | F32: To standardize category chip shown on CITA to refer to category on Product Principal instead of referring on "subfamily" column on produk supplier menu on Control Tower | G32: Nessia | H32: Sri/CI | J32: 45930 | K32: Sprint 7 | N32: covered in sprint 7
A33: 26 | B33: AYO Kasir | D33: Eliminate double transaction happened in AYO due unresponsive Payment gateway | E33: [CDE-25950] AYO Kasir - Limit transaction when FF spam selesaikan pesanan button more than 1x | G33: Marcha | H33: Ida/Adnan | J33: 45930 | K33: Sprint 7 | N33: deployed, 13 aug
A34: 27 | B34: AYO Kasir | D34: Integrate ORF request & process in AYO Kasir | E34: ORF | F34: ORF submission form & process in AYO Kasir to eliminate manual form & manual tracking | G34: Marcha | H34: Ida/Adnan | J34: 45930 | K34: Sprint 7 | N34: covered in sprint 7 ( tp butuh lintas sprint)
A35: 28 | B35: AYO Kasir | D35: Provide inventory data access to AYO Kasir Admin | E35: Stock Count & Stock Adjusment | F35: Laporan inventory harian per toko, per staff, per SKU untuk membantu daily stock take process | G35: Marcha | H35: Ida/Adnan | J35: 45930 | K35: Sprint 7 | N35: covered in sprint 7 ( tp butuh lintas sprint)
A36: 29 | B36: AYO Kasir | D36: Support perpindahan stock antar toko (pemerataan Limited stock & LOGD) | E36: Stock Transfer Store to Store | F36: Stock dapat dipindahkan antar toko (dan antar SLOC) melalui fitur stock movement (beserta history nya) yang dapat di tracking, termasuk dengan penyesuaian di SAP nya | G36: Marcha | H36: Ida/Adnan | J36: 45930 | K36: Sprint 7 | N36: covered in sprint 7 ( tp butuh lintas sprint)
A37: 30 | B37: AYO Kasir | D37: Support loyalty/miles program di IQOS Partne dan allow customization | E37: IP Miles, VAP, Delivery Partner Program | F37: IP memiliki beberapa loyalty toolbox option yang bisa dipilih oleh masing-masing mereka, menyesuaikan dengan kebutuhan bisnis | G37: Marcha | H37: Ida/Adnan | J37: 45930 | K37: Sprint 7 | N37: covered in sprint 7 ( tp butuh lintas sprint)
A38: 31 | B38: AYO Kasir | D38: Provide inventory management & tracking untuk AYO Kasir admin dalam memindahkan stock ke setiap staff | E38: Stock Transfer Admin to Staff | F38: AYO Kasir Admin memerlukan control terhadap inventory management & movement di setiap staff nya, termasuk visibility terkait stock on hand dan movement history yang bisa di track setiap saat untuk monitoring & stock audit | G38: Marcha | H38: Ida/Adnan | J38: 45930 | K38: Sprint 7 | N38: covered in sprint 7
A39: 32 | B39: AYO Kasir | D39: Provide codentify form box for each device purchased --> link device | E39: Device Codentify Input for every device purchased in same order id | F39: Setiap device yang terdapat di dalam suatu transaksi, memerlukan input informasi ke dalam system untuk codentify untuk setiap device. Saat ini, AYO Kasir hanya | G39: Marcha | H39: Ida/Adnan | J39: 45930 | K39: Sprint 7 | N39: covered in sprint 7
A40: 33 | B40: AYO Kasir | D40: Voucher enhancement | E40: Voucher enhancement | F40: Voucher Product Limitation Adjustment | G40: Marcha | H40: Ida/Adnan | J40: 45930 | K40: Sprint 7 | N40: covered in sprint 7
A41: 34 | B41: AYO Kasir | D41: Improve product demo experience for better trial & acceptance | E41: Taste Advisory | F41: Taste Advisory feature yang saat ini tersedia di Qoncierge untuk bisa di integrate ke AYO Kasir untuk seamless journey & data connection (konsumen & transaksi) | G41: Marcha | H41: Ida/Adnan | J41: 45930 | K41: Sprint 7 | N41: covered in sprint 7
A42: 35 | B42: AYO Kasir | D42: Enable AYO Kasir Web Version to be fully operated in IOS based device (All Pages) | E42: AYO Kasir responsive (phase 2) - Compatibility in mobile version (web) | F42: Enable AYO Kasir web to be accessed in mobile browser | H42: Ida/Adnan | J42: 45955 | K42: Sprint 8 (prio1)
A43: 36 | B43: AYO Kasir | D43: Enable AYO Kasir Web Version to be fully operated in IOS based device (Catalog Pages) | E43: AYO Kasir responsive (phase 3) - Compatibility in mobile version (catalog) | F43: Enable AYO Kasir web to be accessed in mobile browser | H43: Ida/Adnan | J43: 45955 | K43: Sprint 8 (prio1)
A44: 37 | B44: AYO Kasir | D44: Data Security - Global Requirement | E44: Pentest Finding: Show generic error message to omit info if phone number exists in database | F44: As a part of security finding, we need to create 1 login page for user to insert phone number and passcode, and show a generic error message to users. The deadline to fix the finding is in October 2025. | H44: Ida/CI | J44: 45955 | K44: Sprint 8 (prio1)
A45: 38 | B45: AYO Kasir | D45: Improve ORF accuracy by each touchpoint to ensure sufficient inventory management & security | E45: AYO Kasir - ORF Warehouse Replenishment - Jira (Phase 3) - PKM ORF | F45: AYO Kasir to be automatically provide ORF Qty recommendation for each touchpoints/coach based on Sales historical & current stock | H45: Ida/Adnan | J45: 45955 | K45: Sprint 8 (prio1)
A46: 39 | B46: AYO Kasir | D46: Provide proper replacement service with proper process in terms of inventory & finance management, similar to DCE configuration | E46: phase 1: input replacement transaction phase 2: QURE in AYO Kasir | F46: Feature to enable SFP device replacement in AYO Kasir by inputting replacement transaction and having DCE API to check device eligibility & record the replacement. | H46: Ida/Adnan | J46: 45955 | K46: Sprint 8 (prio1)
A47: 40 | B47: AYO Kasir | D47: Offline mode AYO Kasir & data synchronization (to SAP & DCE) ability | E47: Allow AYO Kasir to go with offline mode during network limitation and allow data synchronization when back to online | F47: Feature to enable AYO Kasir to be used in offline mode. Usually applicable for events, where there's no signal | H47: Ida/Adnan | J47: 45955 | K47: Sprint 8 (prio1)
A48: 41 | B48: AYO Kasir | D48: Access Management differentiation for each role | E48: a. SDR to assign TL to selected touchpoint b. TL to login AYO Kasir for few touchpoint using 1 account c. TL to assign runner to selected touchpoint d. Runner to login AYO Kasir for few touchpoint using 1 account | F48: Feature for Team Leader and runner to access several booth/kiosk accounts | H48: Ida/Adnan | J48: 45955 | K48: Sprint 8 (prio1)
A49: 42 | B49: AYO Kasir | D49: AYO Principal - Payment gateway configuration for each customer type in AYO Principal | E49: Feature in AYO Principle to set accurate TID, MID and customer type for payment gatewaty configuration | F49: Feature in AYO Principle to set accurate TID, MID and customer type for payment gatewaty configuration | H49: Ida/Adnan | J49: 45955 | K49: Sprint 8 (prio1)
A50: 43 | B50: AYO Kasir | D50: Add shopping bag as sellable item, with proper configuration in finance & transaction record | E50: a. Enable shopping bag transaction to be recognized by SAP b. Enable stock count of shopping bag in AYO Kasir | F50: Shopping Bag IQOS akan menjadi sellable item dan menjadi berbayar. | H50: Ida/Adnan | J50: 45955 | K50: Sprint 8 (prio1)
A51: 44 | B51: AYO Kasir | D51: Aligning coin reward from new leads/member registration with DSD purchase history | E51: Automatic coin rewards for leads/member registration - SRC IQOS Point | F51: Currently, there is matching process between the amount of leads/member registration with DSD purchase by SRC/SRC IQOS Point. This will result in discrepency and potential for fraud. | H51: Jess/Ragib | J51: 45955 | K51: Sprint 8 (prio1)
A52: 45 | B52: DTE | D52: Streamlining coin approval process to become more efficient | E52: Change Process Flow - Coins Approval | F52: Currently, when user conduct RFT or Transfer to Pojok Bayar the process is very lengthy. Through this initiative, we propose a way on how to ensure this process can be conducted in more efficient manner. Approval from related Departments have already been secured. | H52: Hanif/Jess | J52: 45955 | K52: Sprint 8 (prio1) | L52: 1
A53: 46 | B53: PBI | D53: FMCG performance | E53: Add multiple SKU selection PNM in KSI panamas | F53: Add multiple SKU selection PNM in KSI panamas | H53: Nika | J53: 45955 | K53: Sprint 8 (prio1) | L53: 1
A54: 47 | B54: AYO Kasir | D54: Delimit AYO Kasir Stock at SRC IQOS Point to enable higher stock input | E54: Delimit AYO Kasir Stock - SFP | F54: SRC IQOS Point have limitation in adding product due to stock number restriction. This limitation needs to be removed. | H54: Jess/Ragib | J54: 45955 | K54: Sprint 8 (prio1)
A55: 48 | B55: AYO Kasir | D55: Provide "Order Cart" / "Order Draft" Feature before continue to payment | E55: Draft order and reload after doing other activities | F55: Memungkinkan Frontliners untuk menyimpan dulu draft order (seperti cart di e-commerce) sebelum melanjutkan ke payment/complete transaksi, sering digunakan pada saat traffic lagi ramai, >1 konsumen yang perlu dilayani dan diantara mereka masih mungkin untuk merubah item pembelanjaan | H55: Ida/Adnan | J55: 45955 | K55: Sprint 8 (prio2)
A56: 49 | B56: AYO Kasir | D56: Separate product stock for each inventory type (similar to DCE) | E56: Stock categories - sellable & non-sellable - Guided Trial - Replacement - Display Stock - Trade in | F56: Replicate DCE (CEGID & CeApp), dimana stock untuk product sellable dan non-sellable (product demo stock, display, broken device from replacement, trade in) tidak tercampur menjadi satu, memastikan proses disposal & return ke WH termasuk financial record nya bisa tepat & akurat | H56: Ida/Adnan | J56: 45955 | K56: Sprint 8 (prio2)
A57: 50 | B57: DTE | D57: Add Visual Overlay Guide | E57: Visual Overlay Guides for In-App Camera | F57: Currently, there are no guidelines for users taking photos, which may result in pictures being taken under various conditions, not follow to the specified guidance. To improve the quality and reliability of photo submissions during DTE missions in the AYO Toko mobile app, we are introducing key enhancements that address both user experience and submission integrity. Visual Overlay Guides for In-App Camera Users often struggle to align their photos with brand-specific display requirements (e.g., Coca-Cola planogram, Aqua Danone layout, cigarette display standards). This leads to frequent submission errors, rework, and delays in mission validation. To address this, we will implement visual overlay guides directly on the in-app camera. These semi-transparent templates will help users align their camera shots with the expected visual standards, reducing human error and ensuring compliance with planogram expectations. This feature enhances clarity and guidance during submission, resulting in higher-quality, brand-compliant data capture. | H57: Hanif/Jess | J57: 45955 | K57: Sprint 8 (prio2) | L57: 5
A58: 51 | B58: DTE | D58: To understand user behaviour and provide analytics in DTE platform in AYO Toko | E58: GA AYO Toko Tracking | F58: Implement Google Analytics for DTE features in Ayo Toko to understand user behavior. | H58: Hanif/Jess | J58: 45955 | K58: Sprint 8 (prio2) | L58: 3
A59: 52 | B59: DTE | D59: Send reminder to budget owner if it's below a pre-defined threshold to ensure the sustainability of the program | E59: Trade Program Budget Reminder | F59: Send reminder to budget owner if it's below a pre-defined threshold. Reminder will be sent regularly until certain actions are taken (program expired, additional budget, manual close/delete) | H59: Hanif/Jess | J59: 45955 | K59: Sprint 8 (prio2) | L59: 6
A60: 53 | B60: DTE | C60: Principal, CITA | D60: DTE CITA Missions | E60: Reactivate inactive CITA users and increase the pool size of active CITA users | F60: Introduce Missions on CITA | G60: Michael | K60: Sprint 9 | L60: 4
A61: 54 | B61: DTE | D61: DTE Avatar Entry Point | E61: New entry point for Mission Performance and Mission Guidance video | F61: New entry point for Mission Performance and Mission Guidance video | H61: Hanif/Jess | J61: 45955 | K61: Sprint 8 (prio2) | L61: 2
A62: 55 | B62: DTE | D62: Recaptured Image Detection using Moire Pattern | E62: Detect and flag Moiré patterns in submitted images to identify potential manipulation and prevent fraudulent execution verification. | F62: Detect and flag Moiré patterns in submitted images to identify potential manipulation and prevent fraudulent execution verification. | H62: Ahmad/Jeffry | J62: 45955 | K62: Sprint 8 (prio2) | L62: Deprio | O62: Sprint 9
A63: 56 | B63: AMO Plus | D63: AYO Mitra Plus Hybrid Mode | E63: AYO Mitra Plus Hybrid Mode | F63: AMO Existing bisa digunakan dengan AYO Mitra yang baru | H63: Sri P | J63: 45955 | K63: Sprint 8 (prio2) | L63: 1
A64: 57 | B64: AYO Mitra | D64: Cluster mapping | E64: Capability AYO Mitra Plus untuk export dan import hasil clutering agar memudahkan proses revisi cluster. (akan dihandle dari principal dan internal HMS bisa suggest cluster via principal) Untuk new customer akan ikut ditarik datanya dan ada flagging "new" (tersedia di mid aug) Jika PIC melakukan update Skenario : jika zone melakukan update panel di CT, maka data panel yang baru akan ikut ditarik | F64: Capability AYO Mitra Plus untuk export dan import hasil clutering agar memudahkan proses revisi cluster. Untuk new customer akan ikut ditarik datanya dan ada flagging "new". Skenario : jika zone melakukan update panel di CT, maka data panel yang baru akan ikut ditarik | H64: Sri P | J64: 45955 | K64: Sprint 8 (prio2) | L64: 2
A65: 58 | B65: AYO Mitra | D65: Cluster mapping | E65: - Jika ada update panel di CT, maka panel baru tersebut akan secara otomatis terassign ke PG di AYO Mitra. '- Panel baru akan diassignkan ke PG terdekat. Hasil clustering bisa dilihat CT (misal di Retailer Mapping ada PG ID nya), sehingga bisa dijadikan bahan review | F65: - Jika ada update panel CITA di CT, maka panel baru tersebut akan secara otomatis terassign ke PG di AYO Mitra. - panel baru akan diassignkan ke PG terdekat. Hasil clustering bisa dilihat CT (misal di Retailer Mapping ada PG ID nya), sehingga bisa dijadikan bahan review | H65: Sri P | J65: 45955 | K65: Sprint 8 (prio2) | L65: 3
A66: 59 | B66: Ayo Qoncierge Coach | D66: Test Advisory Revamp | E66: Create website builder for Taste Advisory Page | F66: Business can set up for catalog matrix & page design for Taste Advisory | G66: Wildan & Michel | H66: Mustika Nagari | K66: Sprint 8 | L66: 1
A67: 60 | B67: AYO Principal | D67: Duplication Number in Retailer Mapping | E67: Currently there are duplicated phone number between CT and iSMS | F67: to avoid possible bugs happening we need to ensure that CT has a unique phone number between each retailer. Still on discussion to fix this | G67: Ariph | K67: Sprint 8 | L67: 7
A68: 61 | B68: AYO Principal | D68: Validation Retailer Mapping | E68: If user principal updating a duplicated value for phone number, it will rejected by the system. | F68: if user uploading duplicated phone number, then it will be rejected for that specific row, and shown to the user. | G68: Ariph | K68: Sprint 8 | L68: Deprio | O68: Sprint 9
A69: 62 | B69: CITA | C69: Principal, OSEM, TSM, My Hero, AMO | D69: [CITA Loyalty] dormant users keep increasing despite the rapid increase of DAU from dijamin1klik. | E69: retain users and increase regular purchasers through loyalty program, learning from AYO DTE | G69: Jere, Michael | H69: CI/Commstrat | K69: Sprint 8 | L69: 3 | N69: v
A70: 63 | B70: CITA | C70: Principal, OSEM, TSM | D70: [CITA Coachmark] no guidance exists on CITA to help users navigate important activities by themselves | E70: user can learn to operate the platform by themselves and reduce dependency to FF | F70: enable coachmark for every user, at the right time, tailored for each user type-- dormant, regular, etc. In the context of D1K, the coachmark is adaptive. By adaptivemeans the coachmark is tailored based on FF’s stock recommendations.​ | G70: Jere | H70: CI | K70: Sprint 8 | L70: 2 | N70: v
A71: 64 | B71: CITA | C71: Principal, DTE, MyHero | D71: [Instant CN Rewards] Currently, CN Rewards are only applied to Direct Selling activities, and the reward distribution is not immediate—it can only be redeemed during the next visit by the salesman, which typically occurs every two weeks. | E71: Enabling instant reward distribution to digital platform | F71: Instant CN Rewards, we would like to allocate a portion of the coins to CITA, allowing users to redeem digital vouchers or use them to offset the total order value when purchasing through CITA | G71: Jere | H71: Trade Team | K71: Sprint 8 | L71: 1 | N71: v
A72: 65 | B72: CITA | C72: Principal, OSEM, TSM | D72: [CITA PN Integration to OSEM&TSM] Currently, CITA relies on manual audience selection for sending push notifications, which results in significant administrative effort and static targeting. | E72: To improve efficiency and relevance when sending push notification to users | F72: Push Notification Integration with TSM and OSEM This integration will enable trigger- and condition-based notifications, as well as dynamic audience segmentation. As a result, notifications will reach the right users at the right time, while also reducing manual workload for our admins. | G72: Jere | H72: CI/Deployment | K72: Sprint 8 | L72: 4
A73: 66 | B73: MyAyo Web | C73: AYO Toko | D73: Metahuman for PD Support at SRC | E73: SRC Customer have an access for product knowledge, especially for IQOS BONDS | F73: Metahuman support by Global Vendor Synthesia. Consumer can access through QR scanning after registration at SRC as Leads | G73: Wildan | K73: Sprint 8 | L73: 1
A74: 67 | B74: SSR | D74: LAS/LANU Registration for KA (IDM) | E74: Facilitate LAS LANU for self registration & Device Link | F74: Website that LAS/LANU can access for registration process & device link | G74: Wildan | H74: Ivan Orlando | K74: Sprint 8 | L74: 1
A75: 68 | B75: Principal SFP | C75: AYO Toko, My Hero, iSMS, SAP | D75: Customer registration for IQOS Partner (Phase I) | E75: Create seamless system integration for IQOS Partner Registration | F75: Create seamless system integration for IQOS Partner Registration, & initial support invoice automatitation | G75: Wildan | H75: Mustika Nagari | K75: Sprint 8 | L75: 1
A76: 69 | B76: Ayo Qoncierge Coach | C76: Tania | D76: Tania for SFP | E76: Interactive AI to support frontliner incentive | F76: Tanai will giving information & recommendation of the frontliner achievement status | G76: Wildan | K76: Sprint 8 | L76: 2
A77: 70 | B77: AYO Principal | D77: CMS For Tania | E77: To create CMS for Tania in AYO Principal | F77: for this phase it will be simple editor and add edit delete content in AYO Principal. | G77: Ariph | H77: Arum | K77: Sprint 8 | L77: 13 | M77: Sprint7 | N77: v
A78: 71 | B78: AYO PRINCIPAL | D78: Database Push Notification | E78: Improve logging database for push notification CITA on ayo_master | F78: Enhancement include: 1) Adding pnrl_id column 2) Remove execution_count 3) Make every PN execution recorded as 1 row (not updated). https://wiki.app.pconnect.biz/x/t4BzTg https://jira.app.pconnect.biz/browse/CDE-27312 | G78: Livi / Jere | H78: Livi | J78: 45955 | K78: Sprint 8 | L78: 10
A79: 72 | B79: AYO PRINCIPAL | D79: Create New Service for SMS Request to Infobip | E79: Prevent SMS request queueing system in the future to be challenging | F79: Create new service dedicated for SMS request to Infobip https://jira.app.pconnect.biz/browse/CDE-27686 | G79: Livi | H79: Diana/Zhafran/Livi | J79: 45955 | K79: Sprint 8 | L79: 8
A80: 73 | B80: AYO PRINCIPAL | D80: MITA x OSEM, New Audience Paneling for MITA | E80: Improve current way to generate panel MITA to be more seamless and flexible. Currently relying heavily on pipeline & logic from IT DATA. | F80: Enhancement include: 1) Adding new golden records related to MITA 2) Create new S3 AYO for Wiz to consume the panel 3) Create new MITA Config menu on AYO PRINCIPAL (select audience osem, retrieve phone number, export to S3 AYO, split by panel category, config logic for salesman last visit, etc) https://wiki.app.pconnect.biz/x/0AK0Sg | G80: Livi / Zhafran | H80: Shinta/Livi | J80: 45955 | K80: Sprint 8 | L80: 9
A81: 74 | B81: My Hero Backend - CDM Payment Gateway | D81: Cater Business Plan to Go with TA for PANAMAS PRE-ORDER Cash Collection | E81: Exclude Receipt PANAMAS PRE-ORDER Data Ingestion to Payment Gateway Flow | F81: Exclude booking_code "TARE...." from receipt data ingestion payment gateway (my hero ipad setoran page, my hero backend CDM menu, including receipt report, settlement report, disbursement report, etc) | G81: Livi / Melissa Tio | H81: Rangga | J81: 45955 | K81: Sprint 8 | L81: 2
A82: 75 | B82: My Hero Backend - TA Cash Collection | D82: Create New Menu for TA Cash Collection | E82: Facilitate CPO / HO to identify how much amount of delivered order is collected by cash vs QRIS | F82: There will be a new menu on MHBE dedicated for TA Cash Collection, contain table with columns: Area, Salespoint, TA Code, TA Name, Total SO, Delivery Date, Total Delivered Amount, Uang Tunai, E-Payment [CDE-27276] TA Delivery Report | G82: Livi / Melissa Tio | H82: Bu Vivi (Commercial) / Mas Pram | J82: 45955 | K82: Sprint 8 | L82: 3
A83: 76 | B83: My Hero Backend - TA Cash Collection | D83: Create New Menu for TA Delivery Status Report | E83: Facilitate CPO / HO to identify how many orders has been delivered or cancelled from TA (TMS app) | F83: There will be a new menu on MHBE dedicated for TA Cash Collection, contain table with columns: TA Journey Code, TA Name, SO Order Date, Delivery Date, Status, Invoice Amount, Invoice Code, Invoice Legal Number, Territory Code, Customer Code, Customer Name, FF Name, Entity [CDE-27347] Delivery Status (Report) | G83: Livi / Melissa Tio | H83: Bu Vivi (Commercial) / Mas Pram | J83: 45955 | K83: Sprint 8 | L83: 19
A84: 77 | B84: AMO Plus | D84: Sometimes PG completing delivery more than 6 p.m. when admin has gone home so they cannot help PG to carry over incomplete order to next day | E84: To avoid incomplete order to auto-cancelled when admin has finished their shift | F84: Carry over pengiriman CITA yang belum bisa diantarkan ke besok hari dari AMO PG | G84: Jimmy H./ M. Yusron | K84: Sprint 8 | L84: 4
A85: 78 | B85: AMO Existing & Plus | D85: Needed to help prepare the product D-1 prior to delivery | E85: To effectively categorized packaged product by the PG name | F85: Invoice pada transaksi selain memunculkan nama PG, juga no HP PG | G85: Jimmy H./ M. Yusron | K85: Sprint 8 | L85: 10
A86: 79 | B86: AMO Plus | D86: To avoid calculation error when the visit is retrieved via PBI (or any other reporting mechanism) | E86: To avoid calculation error when the visit is retrieved via PBI (or any other reporting mechanism) | F86: Update visit status when Selesaikan Pesanan (currently in DWH visit status is 0, even the delivery has been completed) | G86: Jimmy H./ M. Yusron | K86: Sprint 8 | L86: 11
A87: 80 | B87: AMO Plus | D87: Adanya kemungkinan duplikasi atau double counting pada Data PG Performance Tracker | E87: Fixing the calculation of Data PG Performance Tracker | F87: Calculation PG Performance Tracker yang dikirimkan melalui reverse ETL diharapkan bisa disummary tiap periode performance sehingga perlu enhancement juga dari sisi AMO | G87: Jimmy H./ M. Yusron | H87: Jimmy H. | K87: Sprint 8 | L87: 9
A88: 81 | B88: AMO Existing & AMO Plus | D88: The logic can cause processing inefficiency and high server load in a long run | E88: More effective process (if still needed) | F88: Change the logic from actively query-ing the data from data order table and whitelisting table in database upon completion of delivery order to using flagging on file download. | G88: Jimmy H./ M. Yusron | K88: Sprint 8 | L88: 7
A89: 82 | B89: AMO Plus | D89: To monitor PG activity and calculate a more accurate SLA | E89: To monitor PG activity and calculate a more accurate SLA | F89: Upon completion of CITA Delivery Order it is required to record the Longitude and Latitude | G89: Jimmy H./ M. Yusron | K89: Sprint 8 | L89: 6
A90: 83 | B90: AYO Toko | D90: Home Page Revamp | E90: More engaging content in homepage will be led to more active user | F90: -Publish new configuration at anytime without deployment -Section menu can be arranged in principal -Tile menu can be arrange & hide from principal | G90: M. Yusron | J90: 45955 | K90: Sprint 8 | L90: 5
A91: 84 | B91: AYO Toko | D91: Belanja Page Revamp | E91: Tidier and attaractive Belanja poge will attract to more good experience in Belanja | F91: -Collect all history order in one page -Merged cart page and checkout page into 1 pasge only | G91: M. Yusron | J91: 45955 | K91: Sprint 8 | L91: 6
A92: 85 | B92: AYO Toko | D92: Non Login experience | E92: Dummy homepage with B2B & DTE menu end to end | F92: -Create real order that will be proceed when retailer log-in/registered -Answer real DTE mission with all type of question detail | G92: M. Yusron | J92: 45955 | K92: Sprint 8 | L92: 1
A93: 86 | B93: AYO Toko | D93: Pinang Raya performa - Bank Raya -Pojok Modal | E93: SRC Partnership X Bank Raya | F93: -connection to Pojok Modal AYO Toko with pinang performan bank raya -Configure panel in principal -user can apply for a loan at Bank Raya | G93: M. Yusron | H93: Dhea Rizka | J93: 45955 | K93: Sprint 8 | L93: 4
A94: 87 | B94: AYO Toko | D94: Shopping Bag - AYO Toko SFP | E94: The sale of SFP shopping bags provides PMI with additional income categorized as other revenue | F94: -Create a new 'Others' category in AYO Toko -Partners can purchase SFP shopping bags directly through the platform | G94: M. Yusron | H94: Reza Aryo | J94: 45955 | K94: Sprint 8 | L94: 3
A95: 88 | B95: AYO Toko | D95: Use Metahuman in AYO Toko for lead generation and to enhance user engagement | E95: Display a QR code in AYO Toko to support lead generation and strengthen SRC’s business operations by enabling seamless and accurate knowledge transfer | F95: -Display a QR code and link on Ayo Toko to show the Metahuman video experience -Enable video metahuman from both retailer and consumer devices to ensure broader engagement | G95: M. Yusron | H95: Wildan | J95: 45955 | K95: Sprint 8 | L95: 2
A96: 89 | B96: OSEM | D96: OSEM x TSM x Push Notification CITA | E96: To be able to connect with PN CITA to create digital journey Through TSM | F96: - New Event trigger in TSM UI - Connecting TSM with PN CITA Table | G96: Zhafran | J96: 45955 | K96: Sprint 8 | L96: 1
A97: 90 | B97: OSEM | D97: NEW TSM LOOP Flow Control | E97: To be able to loop the journey of TSM | F97: - Flow control logic that adds New UI in TSM journey | G97: Zhafran | J97: 45955 | K97: Sprint 8 | L97: 2
A98: 91 | B98: OSEM | D98: OSEM x TSM x Coachmark CITA | G98: Zhafran | J98: 45955 | K98: Sprint 8 | L98: 3
A99: 92 | B99: OSEM | D99: TSM UI Enhancement - Button "Batal" Flow Control | F99: flow control - wait by activity button "Batal" | G99: Zhafran | J99: 45955 | K99: Sprint 8 | L99: 4
A100: 93 | B100: AYO Mitra Plus | D100: CT data is frequently updated. When a new downline is added under a WS (Wholesaler), the WS is required to manually assign the new downline to a cluster. However, if the WS has previously adjusted the cluster using Gemini, any new update may reset those adjustments. To address this, the auto-clustering feature ensures that any new downline is automatically assigned to the nearest cluster. This helps maintain consistent cluster segmentation and reduces the need for repeated manual adjustments | E100: auto cluster untuk downline baru pada Mitra yang sudah memiliki cluster | F100: Auto Cluster | G100: Varhan/Junaidi | H100: Project Area (Bandung 2 & Jogja) | J100: 45955 | K100: Sprint 8 | L100: 5
...

Sheet Sprint 8 with Prio (unlocked)
A1: Sprint List | I1: AYO Toko | K1: (3) | L1: DTE | M1: 12
A2: Objective : File ini digunakan oleh CI dan Deployment untuk mentracking List Sprint sepanjang tahun 2025 | I2: MyHero | J2: =66 -> 66 | K2: (1) | L2: AYO Kasir | M2: 97
A3: User yang memiliki akses untuk edit adalah : Tim Deployment & CI | K3: (2) | L3: CITA | M3: 50 | N3: 10 | O3: allocate to AYO Kasir
A4: Sprint 7, need tobe check by tim CI | L4: AYO Mitra
L5: AMO | M5: 107 | P5: SPRINT 8
C6: CI Team | G6: CI Team | M6: assume 1 sprint = 10 mandays | P6: 45904 | Q6: 45920 | R6: 45927 | S6: 45929 | T6: 45958
A7: No | B7: Platform (Aplikasi) | C7: Dependency | D7: Background | E7: Objective | F7: Description | G7: Product Manager | H7: ITPD | I7: Requestor | J7: Chanel | K7: Expected Deployed | L7: Sprint | M7: Rank Prio | N7: Sprint Carry Over | O7: Update from 1st backlog | P7: Update 1 | Q7: Update 2 | R7: Update 3 | S7: Update 4 | T7: Update 5 | U7: Update 6 | V7: Update 7 | W7: PRD | X7: JIRA | Y7: Mandays
A8: 1 | B8: AMO | D8: QR code phase 2 (adding button to top up canvassing during pengiriman CITA di AMO offline) | E8: QR code phase 2 (adding button to top up canvassing during pengiriman CITA di AMO offline) | F8: QR code phase 2 (adding button to top up canvassing during pengiriman CITA di AMO offline) | G8: Marcha | I8: Duta | K8: 45870 | L8: Sprint 6 | P8: Done
A9: 2 | B9: AMO | D9: Canvassing = Product assortment / carousel untuk focused product | E9: Canvassing = Product assortment / carousel untuk focused product | F9: Canvassing = Product assortment / carousel untuk focused product follow B2B | G9: Marcha | I9: Duta | K9: 45870 | L9: Sprint 6 | P9: Done
A10: 3 | B10: AMO | D10: SKU reminder untuk focused product sebelum dilakukan payment | E10: SKU reminder untuk focused product sebelum dilakukan payment | F10: SKU reminder untuk focused product sebelum dilakukan payment (Re-offering) | G10: Marcha | I10: Duta | K10: 45870 | L10: Sprint 6 | P10: Done
A11: 4 | B11: AMO | D11: Mendapatkan progress achievement PG (Unique Call, Volume canvass & CITA) dari PBI Reporting AMO | E11: Mendapatkan progress achievement PG (Unique Call, Volume canvass & CITA) dari PBI Reporting AMO | F11: Mendapatkan progress achievement PG (Unique Call, Volume canvass & CITA) dari PBI Reporting AMO | G11: Marcha | I11: Duta | K11: 45870 | L11: Sprint 6 | P11: Done
A12: 5 | B12: AMO | D12: Add tab "Laporan" untuk menunjukan progress achievement PG (Unique Call, Volume canvass & CITA) | E12: Add tab "Laporan" untuk menunjukan progress achievement PG (Unique Call, Volume canvass & CITA) | F12: Add tab "Laporan" untuk menunjukan progress achievement PG (Unique Call, Volume canvass & CITA) | G12: Marcha | I12: Duta | K12: 45870 | L12: Sprint 6 | P12: Done
A13: 6 | B13: AMO | D13: Canvassing | E13: Fitur Scan QR pada mode Canvassing | F13: Edit text Kunjungan Non Downline menjadi "Mulai Kunjungan", direct page to fitur Scan QR dan akan ter-mapping ke customer registered HMS as map to RE | G13: Marcha | I13: Duta | K13: 45930 | L13: Sprint 7 | O13: covered in sprint 7
A14: 7 | B14: AMO Existing & AMO Plus | D14: The logic can cause processing inefficiency and high server load in a long run | E14: More effective process (if still needed) | F14: Change the logic from actively query-ing the data from data order table and whitelisting table in database upon completion of delivery order to using flagging on file download. | G14: Jimmy H./ M. Yusron | L14: Sprint 8 | M14: 7
A15: 8 | B15: AMO Existing & Plus | D15: Needed to help prepare the product D-1 prior to delivery | E15: To effectively categorized packaged product by the PG name | F15: Invoice pada transaksi selain memunculkan nama PG, juga no HP PG | G15: Jimmy H./ M. Yusron | L15: Sprint 8 | M15: 10
A16: 9 | B16: AMO plus | D16: Filter type outlet di maps | E16: Filter type outlet di maps | F16: Selecting toko yang tampil di peta pada AMO | G16: Maulana | I16: Duta | K16: 45930 | L16: Sprint 7
A17: 10 | B17: AMO Plus | D17: Search downline PG | E17: Search downline PG | F17: Fitur search downline salesman/mitra di AMO+ (seperti di AMO Existing) | G17: Maulana | I17: Duta | K17: 45930 | L17: Sprint 7 | O17: covered in sprint 7
A18: 11 | B18: AMO Plus | D18: Remaining stock product PG | E18: Remaining stock product PG | F18: Info sisa stok yang dibawa PG di page transaksi | G18: Maulana | I18: Duta | K18: 45930 | L18: Sprint 7 | O18: covered in sprint 7
A19: 12 | B19: AMO Plus | D19: Price product di page transaksi | E19: Price product di page transaksi | F19: Info price product / SKU di halaman transaksi | G19: Maulana | I19: Duta | K19: 45930 | L19: Sprint 7 | O19: covered in sprint 7
A20: 13 | B20: AMO Plus | D20: Reconciliation report | E20: Reconciliation report | F20: Menggabungkan LPU dan BPPB pada AMO | G20: Maulana | I20: Duta | K20: 45930 | L20: Sprint 7 | O20: covered in sprint 7
A21: 14 | B21: AMO Plus | D21: AYO Mitra Plus Hybrid Mode | E21: AYO Mitra Plus Hybrid Mode | F21: AMO Existing bisa digunakan dengan AYO Mitra yang baru | I21: Sri P | K21: 45955 | L21: Sprint 8 (prio2) | M21: 1
A22: 15 | B22: AMO Plus | D22: Sometimes PG completing delivery more than 6 p.m. when admin has gone home so they cannot help PG to carry over incomplete order to next day | E22: To avoid incomplete order to auto-cancelled when admin has finished their shift | F22: Carry over pengiriman CITA yang belum bisa diantarkan ke besok hari dari AMO PG | G22: Jimmy H./ M. Yusron | L22: Sprint 8 | M22: 4
A23: 16 | B23: AMO Plus | D23: To avoid calculation error when the visit is retrieved via PBI (or any other reporting mechanism) | E23: To avoid calculation error when the visit is retrieved via PBI (or any other reporting mechanism) | F23: Update visit status when Selesaikan Pesanan (currently in DWH visit status is 0, even the delivery has been completed) | G23: Jimmy H./ M. Yusron | L23: Sprint 8 | M23: 11
A24: 17 | B24: AMO Plus | D24: Adanya kemungkinan duplikasi atau double counting pada Data PG Performance Tracker | E24: Fixing the calculation of Data PG Performance Tracker | F24: Calculation PG Performance Tracker yang dikirimkan melalui reverse ETL diharapkan bisa disummary tiap periode performance sehingga perlu enhancement juga dari sisi AMO | G24: Jimmy H./ M. Yusron | I24: Jimmy H. | L24: Sprint 8 | M24: 9
A25: 18 | B25: AMO Plus | D25: To monitor PG activity and calculate a more accurate SLA | E25: To monitor PG activity and calculate a more accurate SLA | F25: Upon completion of CITA Delivery Order it is required to record the Longitude and Latitude | G25: Jimmy H./ M. Yusron | L25: Sprint 8 | M25: 6
A26: 19 | B26: AMO Plus & AYO Mitra Plus | D26: Heavy queries in AMO: When AMO (AYO Mitra Order / AMO Plus for Pasgar Sinergi) opens BPPB and/or processes CITA orders, the app runs heavy queries to recompute initial stock recommendation and then another query to check stock. This is inefficient and prone to service spikes at higher concurrency. Stok/BPPB checks should only reference the post-“Proses” snapshot table (initial load result), not re-calculate on each screen/process. | E26: Improve Query BPPB & Stock Checking when processing CITA Order | F26: - Eliminate heavy queries in AMO for BPPB and CITA processing - Guarantee stock deduction for all CITA orders that enter BPPB even if the SKU is not listed by the Mitra - Align BPPB across AYO Mitra & AMO (single source of truth). - AMO Plus operates smoothly for ≥5,000 Pasgar concurrently, with ≥35 CITA store orders per Pasgar per day | G26: Varhan/Jun/Jimmy | I26: Varhan | K26: 45930 | L26: Sprint 7 | M26: 13 | Q26: Sprint 7 --> ongoing development | X26: https://jira.app.pconnect.biz/browse/CDE-26740
A27: 20 | B27: AYO Kasir | D27: Eliminate double transaction happened in AYO due unresponsive Payment gateway | E27: [CDE-25950] AYO Kasir - Limit transaction when FF spam selesaikan pesanan button more than 1x | G27: Marcha | I27: Ida/Adnan | K27: 45930 | L27: Sprint 7 | O27: deployed, 13 aug
A28: 21 | B28: AYO Kasir | D28: Integrate ORF request & process in AYO Kasir | E28: ORF | F28: ORF submission form & process in AYO Kasir to eliminate manual form & manual tracking | G28: Marcha | I28: Ida/Adnan | K28: 45930 | L28: Sprint 7 | O28: covered in sprint 7 ( tp butuh lintas sprint)
A29: 22 | B29: AYO Kasir | D29: Provide inventory data access to AYO Kasir Admin | E29: Stock Count & Stock Adjusment | F29: Laporan inventory harian per toko, per staff, per SKU untuk membantu daily stock take process | G29: Marcha | I29: Ida/Adnan | K29: 45930 | L29: Sprint 7 | O29: covered in sprint 7 ( tp butuh lintas sprint)
A30: 23 | B30: AYO Kasir | D30: Support perpindahan stock antar toko (pemerataan Limited stock & LOGD) | E30: Stock Transfer Store to Store | F30: Stock dapat dipindahkan antar toko (dan antar SLOC) melalui fitur stock movement (beserta history nya) yang dapat di tracking, termasuk dengan penyesuaian di SAP nya | G30: Marcha | I30: Ida/Adnan | K30: 45930 | L30: Sprint 7 | O30: covered in sprint 7 ( tp butuh lintas sprint)
A31: 24 | B31: AYO Kasir | D31: Support loyalty/miles program di IQOS Partne dan allow customization | E31: IP Miles, VAP, Delivery Partner Program | F31: IP memiliki beberapa loyalty toolbox option yang bisa dipilih oleh masing-masing mereka, menyesuaikan dengan kebutuhan bisnis | G31: Marcha | I31: Ida/Adnan | K31: 45930 | L31: Sprint 7 | O31: covered in sprint 7 ( tp butuh lintas sprint)
A32: 25 | B32: AYO Kasir | D32: Provide inventory management & tracking untuk AYO Kasir admin dalam memindahkan stock ke setiap staff | E32: Stock Transfer Admin to Staff | F32: AYO Kasir Admin memerlukan control terhadap inventory management & movement di setiap staff nya, termasuk visibility terkait stock on hand dan movement history yang bisa di track setiap saat untuk monitoring & stock audit | G32: Marcha | I32: Ida/Adnan | K32: 45930 | L32: Sprint 7 | O32: covered in sprint 7
A33: 26 | B33: AYO Kasir | D33: Provide codentify form box for each device purchased --> link device | E33: Device Codentify Input for every device purchased in same order id | F33: Setiap device yang terdapat di dalam suatu transaksi, memerlukan input informasi ke dalam system untuk codentify untuk setiap device. Saat ini, AYO Kasir hanya | G33: Marcha | I33: Ida/Adnan | K33: 45930 | L33: Sprint 7 | O33: covered in sprint 7
A34: 27 | B34: AYO Kasir | D34: Voucher enhancement | E34: Voucher enhancement | F34: Voucher Product Limitation Adjustment | G34: Marcha | I34: Ida/Adnan | K34: 45930 | L34: Sprint 7 | O34: covered in sprint 7
A35: 28 | B35: AYO Kasir | D35: Improve product demo experience for better trial & acceptance | E35: Taste Advisory | F35: Taste Advisory feature yang saat ini tersedia di Qoncierge untuk bisa di integrate ke AYO Kasir untuk seamless journey & data connection (konsumen & transaksi) | G35: Marcha | I35: Ida/Adnan | K35: 45930 | L35: Sprint 7 | O35: covered in sprint 7
A36: 29 | B36: AYO Kasir | D36: Enable AYO Kasir Web Version to be fully operated in IOS based device (All Pages) | E36: AYO Kasir responsive (phase 2) - Compatibility in mobile version (web) | F36: Enable AYO Kasir web to be accessed in mobile browser | I36: Ida/Adnan | K36: 45955 | L36: Sprint 8 (prio1)
A37: 30 | B37: AYO Kasir | D37: Enable AYO Kasir Web Version to be fully operated in IOS based device (Catalog Pages) | E37: AYO Kasir responsive (phase 3) - Compatibility in mobile version (catalog) | F37: Enable AYO Kasir web to be accessed in mobile browser | I37: Ida/Adnan | K37: 45955 | L37: Sprint 8 (prio1)
A38: 31 | B38: AYO Kasir | D38: Data Security - Global Requirement | E38: Pentest Finding: Show generic error message to omit info if phone number exists in database | F38: As a part of security finding, we need to create 1 login page for user to insert phone number and passcode, and show a generic error message to users. The deadline to fix the finding is in October 2025. | I38: Ida/CI | K38: 45955 | L38: Sprint 8 (prio1)
A39: 32 | B39: AYO Kasir | D39: Improve ORF accuracy by each touchpoint to ensure sufficient inventory management & security | E39: AYO Kasir - ORF Warehouse Replenishment - Jira (Phase 3) - PKM ORF | F39: AYO Kasir to be automatically provide ORF Qty recommendation for each touchpoints/coach based on Sales historical & current stock | I39: Ida/Adnan | K39: 45955 | L39: Sprint 8 (prio1)
A40: 33 | B40: AYO Kasir | D40: Provide proper replacement service with proper process in terms of inventory & finance management, similar to DCE configuration | E40: phase 1: input replacement transaction phase 2: QURE in AYO Kasir | F40: Feature to enable SFP device replacement in AYO Kasir by inputting replacement transaction and having DCE API to check device eligibility & record the replacement. | I40: Ida/Adnan | K40: 45955 | L40: Sprint 8 (prio1)
A41: 34 | B41: AYO Kasir | D41: Offline mode AYO Kasir & data synchronization (to SAP & DCE) ability | E41: Allow AYO Kasir to go with offline mode during network limitation and allow data synchronization when back to online | F41: Feature to enable AYO Kasir to be used in offline mode. Usually applicable for events, where there's no signal | I41: Ida/Adnan | K41: 45955 | L41: Sprint 8 (prio1)
A42: 35 | B42: AYO Kasir | D42: Access Management differentiation for each role | E42: a. SDR to assign TL to selected touchpoint b. TL to login AYO Kasir for few touchpoint using 1 account c. TL to assign runner to selected touchpoint d. Runner to login AYO Kasir for few touchpoint using 1 account | F42: Feature for Team Leader and runner to access several booth/kiosk accounts | I42: Ida/Adnan | K42: 45955 | L42: Sprint 8 (prio1)
A43: 36 | B43: AYO Kasir | D43: Add shopping bag as sellable item, with proper configuration in finance & transaction record | E43: a. Enable shopping bag transaction to be recognized by SAP b. Enable stock count of shopping bag in AYO Kasir | F43: Shopping Bag IQOS akan menjadi sellable item dan menjadi berbayar. | I43: Ida/Adnan | K43: 45955 | L43: Sprint 8 (prio1)
A44: 37 | B44: AYO Kasir | D44: Aligning coin reward from new leads/member registration with DSD purchase history | E44: Automatic coin rewards for leads/member registration - SRC IQOS Point | F44: Currently, there is matching process between the amount of leads/member registration with DSD purchase by SRC/SRC IQOS Point. This will result in discrepency and potential for fraud. | I44: Jess/Ragib | K44: 45955 | L44: Sprint 8 (prio1)
A45: 38 | B45: AYO Kasir | D45: Delimit AYO Kasir Stock at SRC IQOS Point to enable higher stock input | E45: Delimit AYO Kasir Stock - SFP | F45: SRC IQOS Point have limitation in adding product due to stock number restriction. This limitation needs to be removed. | I45: Jess/Ragib | K45: 45955 | L45: Sprint 8 (prio1)
A46: 39 | B46: AYO Kasir | D46: Provide "Order Cart" / "Order Draft" Feature before continue to payment | E46: Draft order and reload after doing other activities | F46: Memungkinkan Frontliners untuk menyimpan dulu draft order (seperti cart di e-commerce) sebelum melanjutkan ke payment/complete transaksi, sering digunakan pada saat traffic lagi ramai, >1 konsumen yang perlu dilayani dan diantara mereka masih mungkin untuk merubah item pembelanjaan | I46: Ida/Adnan | K46: 45955 | L46: Sprint 8 (prio2)
A47: 40 | B47: AYO Kasir | D47: Separate product stock for each inventory type (similar to DCE) | E47: Stock categories - sellable & non-sellable - Guided Trial - Replacement - Display Stock - Trade in | F47: Replicate DCE (CEGID & CeApp), dimana stock untuk product sellable dan non-sellable (product demo stock, display, broken device from replacement, trade in) tidak tercampur menjadi satu, memastikan proses disposal & return ke WH termasuk financial record nya bisa tepat & akurat | I47: Ida/Adnan | K47: 45955 | L47: Sprint 8 (prio2)
A48: 41 | B48: AYO Kasir | D48: Store-to-store transfer movement between SAP & AYO Kasir relies on Material Code. But, currently, these movement can't be fully captured, creating a gap between stock movement in AYO Kasir vs SAP | E48: Replacing material code with barcode for store-to-store movement between AYO Kasir & SAP | F48: Material code will be replaced by barcode to communicate between SAP & AYO Kasir for store-to-store. | G48: Sean
A49: 42 | B49: AYO Kasir | D49: AYO Principal - Payment gateway configuration for each customer type in AYO Principal | E49: Feature in AYO Principle to set accurate TID, MID and customer type for payment gatewaty configuration | F49: Feature in AYO Principle to set accurate TID, MID and customer type for payment gatewaty configuration | I49: Ida/Adnan | K49: 45955 | L49: Sprint 8 (prio1)
A50: 43 | B50: AYO Kasir | D50: Every new product launch requires publishing description and barcode to both AYO Principal and SAP. However, the process depends on the global PMI team to push the master material code, creating delays before AYO Kasir can recognize the product. | E50: Enable SAP to send Master Material Code directly for new product launches, so AYO Kasir can recognize it through inbound / outbound | F50: The system will be enhanced so SAP automatically pushes Master Material Code along with product details (description, barcode) to AYO Kasir, reducing dependency on the global PMI team. | G50: Sean
A51: 44 | B51: AYO Kasir | D51: Codentify is a code used to activate warranty for IQOS devices, stored in the global DCE database (not directly accessible). Currently, a bot gathers codes nationally and activates them, but it often fails and cannot detect duplicate or invalid codes, leaving them stuck in a loop. | E51: Implement a codentify checking mechanism to validate codes upfront before activation. | F51: The system will check codentify codes against a validation logic before processing. If a code is already used or invalid, it will be rejected upfront, preventing duplicate or invalid activations.
A52: 45 | B52: AYO Kasir | D52: Touchpoints are inconsistently classified across regions. For example, a key account in Bandung can sell both SFP & Non-SFP products, but a similar key account in Jakarta cannot. This inconsistency creates confusion and inefficiency | E52: Standardize and differentiate touchpoint types to ensure consistent SFP vs Non-SFP capabilities. | F52: The system will classify and unify touchpoints based on capability, ensuring key accounts have consistent rights to sell SFP and/or Non-SFP products regardless of region. | G52: Sean/Jodis
A53: 46 | B53: AYO Kasir | D53: Currently, IQOS products (SFP) are mixed with other products (e.g., BONDS) in reporting dashboards, causing confusion and lack of clarity. PowerBI dashboards cannot differentiate between SFP and Non-SFP product performance. | E53: Separate SFP vs Non-SFP products for clearer reporting and tracking. | F53: The system will tag and differentiate SFP vs Non-SFP products as distinct entities, enabling PowerBI dashboards to generate separate, accurate reports for each product type. | G53: Sean/Jodis
A54: 47 | B54: AYO Kasir | D54: Every new product launch requires publishing description and barcode to both AYO Principal and SAP. However, the process depends on the global PMI team to push the master material code, creating delays before AYO Kasir can recognize the product. | F54: [PRD] AYO Kasir - Material Master Configuration for NPL in SAP - Commercial Digital Ecosystem - Confluence | W54: [PRD] AYO Kasir - Material Master Configuration for NPL in SAP - Commercial Digital Ecosystem - Confluence | X54: [CDE-29946] AYO Kasir - Material Master Configuration for NPL in SAP - Jira
A55: 48 | B55: AYO Kasir | D55: Currently, there're several cancellations of outbound / inbound doc which requires a backend deletion due to no capability in AYO Kasir to cancel it. The deletion via backend needs CHT which takes quite a long way to process and run. If the outbound is not cancelled, it'll be prone to be submitted by user and leads to stock discrepancy. | F55: [PRD] Stock Replenishment with SAP Integration - Commercial Digital Ecosystem - Confluence | W55: [PRD] Stock Replenishment with SAP Integration - Commercial Digital Ecosystem - Confluence | X55: [CDE-29748] AYO Kasir - Cancel inbound / outbound docs and reflect it in SAP - Jira
A56: 49 | B56: AYO Kasir | D56: Export xlsx for replenishment inbound & outbound doc | F56: [PRD] Stock Replenishment with SAP Integration - Commercial Digital Ecosystem - Confluence | W56: [PRD] Stock Replenishment with SAP Integration - Commercial Digital Ecosystem - Confluence | X56: https://jira.app.pconnect.biz/browse/CDE-29750
A57: 50 | B57: AYO Kasir | D57: Enhance downline management: bulk upload | F57: PRD CDE-19423 Downline Management (Transfer Stock: Admin to Staff) - Commercial Digital Ecosystem - Confluence | W57: PRD CDE-19423 Downline Management (Transfer Stock: Admin to Staff) - Commercial Digital Ecosystem - Confluence | X57: [CDE-29945] AYO Kasir - Bulk upload for "Transfer Stock Admin to Staff" feature - Jira
A58: 51 | B58: AYO Kasir | D58: Enhance downline management: show staffs' stock in export Produk file | F58: PRD CDE-19423 Downline Management (Transfer Stock: Admin to Staff) - Commercial Digital Ecosystem - Confluence | W58: PRD CDE-19423 Downline Management (Transfer Stock: Admin to Staff) - Commercial Digital Ecosystem - Confluence | X58: [CDE-29944] AYO Kasir - Show staffs' stock by exporting file in Produk menu - Jira
A59: 52 | B59: AYO Mitra | D59: Cluster mapping | E59: Capability AYO Mitra Plus untuk export dan import hasil clutering agar memudahkan proses revisi cluster. (akan dihandle dari principal dan internal HMS bisa suggest cluster via principal) Untuk new customer akan ikut ditarik datanya dan ada flagging "new" (tersedia di mid aug) Jika PIC melakukan update Skenario : jika zone melakukan update panel di CT, maka data panel yang baru akan ikut ditarik | F59: Capability AYO Mitra Plus untuk export dan import hasil clutering agar memudahkan proses revisi cluster. Untuk new customer akan ikut ditarik datanya dan ada flagging "new". Skenario : jika zone melakukan update panel di CT, maka data panel yang baru akan ikut ditarik | I59: Sri P | K59: 45955 | L59: Sprint 8 (prio2) | M59: 2
A60: 53 | B60: AYO Mitra | D60: Cluster mapping | E60: - Jika ada update panel di CT, maka panel baru tersebut akan secara otomatis terassign ke PG di AYO Mitra. '- Panel baru akan diassignkan ke PG terdekat. Hasil clustering bisa dilihat CT (misal di Retailer Mapping ada PG ID nya), sehingga bisa dijadikan bahan review | F60: - Jika ada update panel CITA di CT, maka panel baru tersebut akan secara otomatis terassign ke PG di AYO Mitra. - panel baru akan diassignkan ke PG terdekat. Hasil clustering bisa dilihat CT (misal di Retailer Mapping ada PG ID nya), sehingga bisa dijadikan bahan review | I60: Sri P | K60: 45955 | L60: Sprint 8 (prio2) | M60: 3
A61: 54 | B61: AYO Mitra | C61: CITA | D61: provice information when retailer redeem loyalty from CITA/MITA. | E61: memudahkan controling / reinbursment adminstratitve AYO Mitra | F61: adding information "pesan malalui" and update filter | G61: Junaidi | I61: CI/Commstrat | L61: Sprint 8 | M61: 12
A62: 55 | B62: AYO Mitra Existing & Plus | D62: To create better user journey to adopt Digital from CITA and then AYO Toko, DTE team are creating Loyalty point mechanism where retailer can use for payment to their order in CITA. | E62: To enable point redemption in CITA and the subsequent delivery using AYO Mitra and AMO. | F62: Specific for AMO and AMO Plus, there will be order from CITA with detailed of SKU, Qty, and nominal Payment per SKU, plus point redemption / utilization. Upon Delivery: 1. When retailer reduce the number of purchase until below the number of point redeemed, then number of point redeemed must be set the same as the purchase. This must be informed back to CITA and AYO Mitra. 2. When retailer add the number of purchase, the number of point redeemed will be the same and cannot be increased though retailer still have some loyalty points left in CITA. | G62: Jimmy H./ M. Yusron | I62: Mike & Jere | K62: 45958 | L62: Sprint 8 | M62: 8
A63: 56 | B63: AYO Mitra PH | D63: Existing setup mechanism takes too much time on Mitra since it needs to be inputed via UI | E63: Upgrade setup mechanism of Rider Routing by using Excel upload | F63: https://jira.app.pconnect.biz/browse/CDE-24667 | G63: Robert | I63: Commercial PH | L63: Sprint 8 | O63: PO has been created by PMFTC (Capex)
A64: 57 | B64: AYO Mitra PH | D64: Current inventory management feature rarely used because WS does not have inventory data for longtail SKU | E64: To allow WS apply inventory management to SKUs that are fast-moving | F64: https://jira.app.pconnect.biz/browse/CDE-23348 | G64: Robert | I64: Commercial PH | L64: Sprint 8 | O64: PO has been created by PMFTC (Capex)
A65: 58 | B65: AYO Mitra PH | E65: To solve existing Bug found during regression on Deep migration | F65: https://jira.app.pconnect.biz/browse/CDE-29024 | G65: Robert | I65: Commercial PH | L65: Sprint 8 | O65: Opex - BAU
A66: 59 | B66: AYO Mitra PH | D66: >40% product on databank & Mitra's product does not have pictures | E66: To enable bulk upload of pictures on Principal to be used on AYO Mitra | F66: https://jira.app.pconnect.biz/browse/CDE-25303 | G66: Robert | I66: Commercial PH | L66: Sprint 9
A67: 60 | B67: AYO Mitra Plus | D67: Manual assign by PG khususnya jika ada PG yg tidak masuk | E67: Manual assign by PG khususnya jika ada PG yg tidak masuk | F67: Manual assign by PG khususnya jika ada PG yg tidak masuk | G67: Maulana | I67: Sri P | K67: 45930 | L67: Sprint 7 | O67: covered in sprint 7
A68: 61 | B68: AYO Mitra Plus | D68: Grouping order by PG di hari H-1 | E68: Grouping order by PG di hari H-1 | F68: Grouping order by PG di hari H | G68: Maulana | I68: Sri P | K68: 45930 | L68: Sprint 7 | O68: covered in sprint 7
A69: 62 | B69: AYO Mitra Plus | D69: Mitra tetap dapat melakukan cluster, meskipun masih ada pesanan dalam pengiriman | E69: Mitra tetap dapat melakukan cluster, meskipun masih ada pesanan dalam pengiriman | F69: Mitra tetap dapat melakukan proses pesanan, ketika ada pesanan baru | G69: Maulana | I69: Sri P | K69: 45930 | L69: Sprint 7 | O69: covered in sprint 7
A70: 63 | B70: AYO Mitra Plus | D70: Fixing miss cluster | E70: Fixing miss cluster | F70: Fixing miss cluster | G70: Maulana | I70: Sri P | K70: 45930 | L70: Sprint 7 | O70: covered in sprint 7
A71: 64 | B71: AYO Mitra Plus | D71: Simply Initial load reccomendation | E71: Simply Initial load reccomendation | F71: Simply Initial load reccomendation | G71: Maulana | I71: Sri P | K71: 45930 | L71: Sprint 7 | O71: covered in sprint 7
A72: 65 | B72: AYO Mitra Plus | D72: CT data is frequently updated. When a new downline is added under a WS (Wholesaler), the WS is required to manually assign the new downline to a cluster. However, if the WS has previously adjusted the cluster using Gemini, any new update may reset those adjustments. To address this, the auto-clustering feature ensures that any new downline is automatically assigned to the nearest cluster. This helps maintain consistent cluster segmentation and reduces the need for repeated manual adjustments | E72: auto cluster untuk downline baru pada Mitra yang sudah memiliki cluster | F72: Auto Cluster | G72: Varhan/Junaidi | I72: Project Area (Bandung 2 & Jogja) | K72: 45955 | L72: Sprint 8 | M72: 5 | X72: https://jira.app.pconnect.biz/browse/CDE-26737
A73: 66 | B73: AYO Mitra Plus | D73: Today, AYO Mitra uses conditions that (on average) rely on updated_at and created_at in table orders_cita when users click “Proses” or when fetching data in Pengaturan Pesanan Hari Ini for whitelisted Instant Delivery / Pasgar Synergy. As a side effect, orders placed on Thursday but configured to ship/deliver on Saturday may fail to appear in AYO Mitra on Saturday, because the logic expects an Friday updated_at value to be in-range. This also interacts poorly with “tunda ke esok hari”, which does not update delivery_date and shipping_date, increasing query complexity and causing visibility inconsistencies | E73: Pengaturan Pesanan Hari ini & "Proses" logic enhancement | F73: - Make “today” visibility deterministic by delivery/ship date - Normalize deferral (“tunda ke esok hari”) - Unify date logic across clients & endpoints | G73: Varhan/Jun | I73: Varhan | K73: 45955 | L73: Sprint 8 | M73: 14 | X73: https://jira.app.pconnect.biz/browse/CDE-26738
A74: 67 | B74: AYO Mitra Plus | D74: Currently, editing qty on initial load page for each brand need 3 steps, click icon edit, fill in the qty, and click save. | E74: reducing step for creating initial load for pasgar | F74: This enhancement will make user only need to fill the qty wihtout clicking edit and save button, and make user can move to another column by clicking tab on the keyboard that will make editing initial load faster (replacing ticket 93 & 98 --> duplicate) | G74: Varhan | I74: Varhan | K74: 45955 | L74: Sprint 8 | M74: 5 | X74: https://jira.app.pconnect.biz/browse/CDE-29902
A75: 68 | B75: AYO Principal | D75: Elevate Automation | E75: Elevate - Data Entry | F75: Capability untuk user bisa melakukan WO atau guideline submission | G75: Nessia | I75: Nika | K75: 45930 | L75: Sprint 7
A76: 69 | B76: AYO Principal | D76: Elevate Automation | E76: Elevate - Email generator | F76: Capability elevate untuk generate email ke zone sehubungan dengan WO/guideline yang diinputkan di Elevate | G76: Nessia | I76: Nika | K76: 45930 | L76: Sprint 7
A77: 70 | B77: AYO Principal | D77: Elevate Automation | E77: Elevate - Cycle calendar | F77: Capability untuk show dan filter WO atau guideline yang impact ke waktu week tertentu | G77: Nessia | I77: Nika | K77: 45930 | L77: Sprint 7
A78: 71 | B78: AYO Principal | D78: CMS For Tania | E78: To create CMS for Tania in AYO Principal | F78: for this phase it will be simple editor and add edit delete content in AYO Principal. | G78: Ariph | I78: Arum | L78: Sprint 8 | M78: 13 | N78: Sprint7 | O78: v
A79: 72 | B79: AYO PRINCIPAL | D79: Database Push Notification | E79: Improve logging database for push notification CITA on ayo_master | F79: Enhancement include: 1) Adding pnrl_id column 2) Remove execution_count 3) Make every PN execution recorded as 1 row (not updated). https://wiki.app.pconnect.biz/x/t4BzTg https://jira.app.pconnect.biz/browse/CDE-27312 | G79: Livi / Jere | I79: Livi | K79: 45955 | L79: Sprint 8 | M79: 10 | W79: https://wiki.app.pconnect.biz/x/t4BzTg | X79: https://jira.app.pconnect.biz/browse/CDE-27312
A80: 73 | B80: AYO PRINCIPAL | D80: Create New Service for SMS Request to Infobip | E80: Prevent SMS request queueing system in the future to be challenging | F80: Create new service dedicated for SMS request to Infobip https://jira.app.pconnect.biz/browse/CDE-27686 | G80: Livi | I80: Diana/Zhafran/Livi | K80: 45955 | L80: Sprint 8 | M80: 8 | W80: https://wiki.app.pconnect.biz/pages/viewpage.action?spaceKey=CDE&title=Phase+3.2+-+SMS+Blast | X80: https://jira.app.pconnect.biz/browse/CDE-27312
A81: 74 | B81: AYO PRINCIPAL | D81: MITA x OSEM, New Audience Paneling for MITA | E81: Improve current way to generate panel MITA to be more seamless and flexible. Currently relying heavily on pipeline & logic from IT DATA. | F81: Enhancement include: 1) Adding new golden records related to MITA 2) Create new S3 AYO for Wiz to consume the panel 3) Create new MITA Config menu on AYO PRINCIPAL (select audience osem, retrieve phone number, export to S3 AYO, split by panel category, config logic for salesman last visit, etc) https://wiki.app.pconnect.biz/x/0AK0Sg | G81: Livi / Zhafran | I81: Shinta/Livi | K81: 45955 | L81: Sprint 8 | M81: 9 | O81: Sprint 9
A82: 75 | B82: AYO Principal | D82: This feature allows area users to propose cluster recommendations for AYO Mitra Plus. It is integrated with GEMINI and includes an option to import clusters based on the Field Force (FF) route plan, ensuring alignment with operational execution on the ground. | E82: Recommendation Cluster for AYO Mitra Plus | F82: Recommendation Cluster | G82: Varhan (AYO Principal), Junaidi (AYO Mitra | I82: Deployment & RTM | K82: 45962 | L82: Sprint 8 | M82: 1 | X82: https://jira.app.pconnect.biz/projects/CDE/issues/CDE-24537?filter=allissues
A83: 76 | B83: AYO Principal | D83: Currently, image banners or product package visuals must be uploaded to Yellow, and the link must be manually copied and pasted into AYO. This process will be improved by enabling direct uploads via the principal, with the files stored and accessible directly within AYO. | E83: Image Uploader for CITA | F83: Image Uploader | G83: Varhan | I83: Jere | K83: 45955 | L83: Sprint 8 | M83: 12 | X83: https://jira.app.pconnect.biz/browse/CDE-27416
A84: 77 | B84: AYO Principal | D84: A new feature will enable users to set FAQs directly within CITA, including the ability to link relevant coachmarks to each FAQ. This integration will help guide users more effectively by providing contextual assistance aligned with frequently asked questions | E84: FAQ for CITA | F84: FAQ for CITA | G84: Varhan | I84: Jere | K84: 45955 | L84: Sprint 8 | M84: 11 | X84: https://jira.app.pconnect.biz/browse/CDE-29323
A85: 78 | B85: AYO Principal | D85: Enable Admin to Seamlessly Whitelist MITA Inbound | E85: MITA configurator in principal | F85: This feature enables area-level users to configure the following settings within MITA: '- Whitelist Management: Set and manage whitelisted users or entities at the area level. - Copywriting Configurator: Customize and manage copywriting content as needed. - Call Delay Settings: Adjust call delay parameters to suit operational needs. - Weekend Availability: Define whether specific features or operations are available during weekends. | G85: Ariph | I85: Livi/Nessia | L85: Sprint 8 | M85: 6 | X85: https://jira.app.pconnect.biz/browse/CDE-30278
A86: 79 | B86: AYO Principal | D86: Search in Dropdown | E86: Make dropdown simpler by adding search feature in dropdown single / multiple selection - Control Tower - Field Force - Data Management | F86: Currently in every dropdown in AYO Principal, user currently has a pain point when accessing it. If there is a lot of list in that dropdown, user will need to go through the list to select the item. | G86: Ariph | I86: Ariph | L86: Sprint 8 | M86: 5
A87: 80 | B87: AYO Principal | D87: Currently have a pain point to select dropdown when there is a lot of list | E87: To fasten up user experience when selecting filter in ayo principal | F87: https://jira.app.pconnect.biz/browse/CDE-29361 | G87: Ariph | I87: Ariph | L87: Sprint 9
A88: 81 | B88: AYO Principal | D88: Gemini improvement After user uploading the file in gemini, user need to cross check the data. User experiencing pain point when they need to change pinpoint location. They need to define long lat manually | E88: To simplify and ease user experience, we would like to make drag and drop so user can change the pinpoint easily | G88: Ariph | I88: Ariph | L88: Sprint 9
A89: 82 | B89: AYO Principal | D89: We would like to track user behaviour when accessing AYO Principal | G89: Ariph | I89: Ariph | L89: Sprint 9
A90: 83 | B90: AYO Principal | D90: Duplication Number in Retailer Mapping | E90: Currently there are duplicated phone number between CT and iSMS | F90: to avoid possible bugs happening we need to ensure that CT has a unique phone number between each retailer. Still on discussion to fix this | G90: Ariph | I90: Ariph | L90: Sprint 8
A91: 84 | B91: AYO Principal | D91: Validation Retailer Mapping | E91: If user principal updating a duplicated value for phone number, it will rejected by the system. | F91: if user uploading duplicated phone number, then it will be rejected for that specific row, and shown to the user. | G91: Ariph | I91: Ariph | L91: Sprint 8 | M91: Deprio | P91: Sprint 9
A92: 85 | B92: AYO Principal - TRS Back Office | E92: TRS System Variable - Add Multi Company Setting Limitation | F92: Adding fitur Configuraable TRS Operational limit Transaction | G92: Adnan | I92: BV1 Project & Compliance | L92: Sprint 8 | M92: 2 | O92: Sprint 7 (deployment 30 sept 2025) | X92: CDE-14276 B2B ID - AYO Principal TRS - Update BV1 Proccess and TRS Mechanism
A93: 86 | B93: AYO Principal - TRS Back Office | E93: TRS Setup Proposal - Add Split Multi Company Activity | F93: Split Proposal for Sampoerna & Partner Items. | G93: Adnan | I93: BV1 Project | L93: Sprint 8 | M93: 3 | O93: Sprint 7 (deployment 30 sept 2025) | X93: CDE-14276 B2B ID - AYO Principal TRS - Update BV1 Proccess and TRS Mechanism
A94: 87 | B94: AYO Principal - TRS Back Office | E94: TRS Reconcilliation Report | F94: Adding Fitur to View Sparate Transaction / Group by Sampoerna Or Partner | G94: Adnan | I94: BV1 Project | L94: Sprint 8 | M94: 4 | O94: Sprint 7 (deployment 30 sept 2025) | X94: CDE-14276 B2B ID - AYO Principal TRS - Update BV1 Proccess and TRS Mechanism
A95: 88 | B95: Ayo Qoncierge Coach | D95: Test Advisory Revamp | E95: Create website builder for Taste Advisory Page | F95: Business can set up for catalog matrix & page design for Taste Advisory | G95: Wildan & Michel | I95: Mustika Nagari | L95: Sprint 8 | M95: 1
A96: 89 | B96: Ayo Qoncierge Coach | C96: Tania | D96: Tania for SFP | E96: Interactive AI to support frontliner incentive | F96: Tanai will giving information & recommendation of the frontliner achievement status | G96: Wildan | L96: Sprint 8 | M96: 2
A97: 90 | B97: AYO Toko | D97: Home Page Revamp | E97: More engaging content in homepage will be led to more active user | F97: -Publish new configuration at anytime without deployment -Section menu can be arranged in principal -Tile menu can be arrange & hide from principal - [OK TO SWAP] | G97: M. Yusron / Gerry | K97: 45955 | L97: Sprint 8 | M97: 5 | Q97: [Low Prio] Ok to swap | W97: PRD | X97: CDE-19158
A98: 91 | B98: AYO Toko | D98: Belanja Page Revamp | E98: Tidier and attaractive Belanja poge will attract to more good experience in Belanja | F98: -Collect all history order in one page -Merged cart page and checkout page into 1 pasge only - [OK TO SWAP] | G98: M. Yusron / Gerry | K98: 45955 | L98: Sprint 8 | M98: 6 | Q98: [Low Prio] Ok to swap | W98: PRD | X98: CDE-19301
A99: 92 | B99: AYO Toko | D99: Non Login experience | E99: Dummy homepage with B2B & DTE menu end to end | F99: -Create real order that will be proceed when retailer log-in/registered -Answer real DTE mission with all type of question detail - [OK TO SWAP] | G99: M. Yusron / Gerry | K99: 45955 | L99: Sprint 8 | M99: 1 | Q99: [Low Prio] Ok to swap | W99: PRD | X99: CDE-19015
A100: 93 | B100: AYO Toko | D100: Pinang Raya performa - Bank Raya -Pojok Modal | E100: SRC Partnership X Bank Raya | F100: -connection to Pojok Modal AYO Toko with pinang performan bank raya -Configure panel in principal -user can apply for a loan at Bank Raya - [Higher prio. due to biz request] | G100: M. Yusron / Gerry | I100: Dhea Rizka | K100: 45955 | L100: Sprint 8 | M100: 4 | Q100: [High Prio] Business Req | W100: PRD | X100: CDE-24268
...

Sheet Kasir Qoncierge
A1: Sprint List | H1: AYO Toko | J1: -3 | K1: DTE | L1: 12
A2: Objective : File ini digunakan oleh CI dan Deployment untuk mentracking List Sprint sepanjang tahun 2025 | H2: MyHero | I2: 66 | J2: -1 | K2: AYO Kasir | L2: 97
A3: User yang memiliki akses untuk edit adalah : Tim Deployment & CI | J3: -2 | K3: CITA | L3: 50 | M3: 10 | N3: allocate to AYO Kasir
A4: Sprint 7, need tobe check by tim CI | K4: AYO Mitra
K5: AMO | L5: 107 | O5: SPRINT 8
C6: CI Team | G6: CI Team | L6: assume 1 sprint = 10 mandays | O6: 45904 | P6: 45916 | Q6: 45919 | R6: 45926 | S6: 45958
A7: No | B7: Platform (Aplikasi) | C7: Dependency | D7: Background | E7: Objective | F7: Description | G7: Product Manager | H7: Requestor | I7: Chanel | J7: Expected Deployed | K7: Sprint | L7: Rank Prio | M7: Sprint Carry Over | N7: Update 0 8/28 | O7: Update 1 | P7: Update 2 | Q7: Update 3 | R7: Update 4 | S7: Update 5 | T7: Update 6 | U7: Update 7 | V7: JIRA | W7: Mandays
A8: 1 | B8: AMO | D8: QR code phase 2 (adding button to top up canvassing during pengiriman CITA di AMO offline) | E8: QR code phase 2 (adding button to top up canvassing during pengiriman CITA di AMO offline) | F8: QR code phase 2 (adding button to top up canvassing during pengiriman CITA di AMO offline) | G8: Marcha | H8: Duta | J8: 45894 | K8: Sprint 6 | O8: Done
A9: 2 | B9: AMO | D9: Canvassing = Product assortment / carousel untuk focused product | E9: Canvassing = Product assortment / carousel untuk focused product | F9: Canvassing = Product assortment / carousel untuk focused product follow B2B | G9: Marcha | H9: Duta | J9: 45894 | K9: Sprint 6 | O9: Done
A10: 3 | B10: AMO | D10: SKU reminder untuk focused product sebelum dilakukan payment | E10: SKU reminder untuk focused product sebelum dilakukan payment | F10: SKU reminder untuk focused product sebelum dilakukan payment (Re-offering) | G10: Marcha | H10: Duta | J10: 45894 | K10: Sprint 6 | O10: Done
A11: 4 | B11: AMO | D11: Mendapatkan progress achievement PG (Unique Call, Volume canvass & CITA) dari PBI Reporting AMO | E11: Mendapatkan progress achievement PG (Unique Call, Volume canvass & CITA) dari PBI Reporting AMO | F11: Mendapatkan progress achievement PG (Unique Call, Volume canvass & CITA) dari PBI Reporting AMO | G11: Marcha | H11: Duta | J11: 45894 | K11: Sprint 6 | O11: Done
A12: 5 | B12: AMO | D12: Add tab "Laporan" untuk menunjukan progress achievement PG (Unique Call, Volume canvass & CITA) | E12: Add tab "Laporan" untuk menunjukan progress achievement PG (Unique Call, Volume canvass & CITA) | F12: Add tab "Laporan" untuk menunjukan progress achievement PG (Unique Call, Volume canvass & CITA) | G12: Marcha | H12: Duta | J12: 45894 | K12: Sprint 6 | O12: Done
A13: 6 | B13: AYO Principal | D13: Elevate Automation | E13: Elevate - Data Entry | F13: Capability untuk user bisa melakukan WO atau guideline submission | G13: Nessia | H13: Nika | J13: 45925 | K13: Sprint 7
A14: 7 | B14: AYO Principal | D14: Elevate Automation | E14: Elevate - Email generator | F14: Capability elevate untuk generate email ke zone sehubungan dengan WO/guideline yang diinputkan di Elevate | G14: Nessia | H14: Nika | J14: 45925 | K14: Sprint 7
A15: 8 | B15: AYO Principal | D15: Elevate Automation | E15: Elevate - Cycle calendar | F15: Capability untuk show dan filter WO atau guideline yang impact ke waktu week tertentu | G15: Nessia | H15: Nika | J15: 45925 | K15: Sprint 7
A16: 9 | B16: Control Tower | D16: Seamless data upload | E16: CT Update Schedulling and rework data entry template | F16: Flexybility update data in CT by add feature schedule | G16: Nessia | H16: Sri P | J16: 45925 | K16: Sprint 7 | M16: Sprint 8 | N16: carry over to the next sprint
A17: 10 | B17: AMO | D17: Canvassing | E17: Fitur Scan QR pada mode Canvassing | F17: Edit text Kunjungan Non Downline menjadi "Mulai Kunjungan", direct page to fitur Scan QR dan akan ter-mapping ke customer registered HMS as map to RE | G17: Marcha | H17: Duta | J17: 45925 | K17: Sprint 7 | N17: covered in sprint 7
A18: 11 | B18: AMO plus | D18: Filter type outlet di maps | E18: Filter type outlet di maps | F18: Selecting toko yang tampil di peta pada AMO | G18: Maulana | H18: Duta | J18: 45925 | K18: Sprint 7
A19: 12 | B19: AMO Plus | D19: Search downline PG | E19: Search downline PG | F19: Fitur search downline salesman/mitra di AMO+ (seperti di AMO Existing) | G19: Maulana | H19: Duta | J19: 45925 | K19: Sprint 7 | N19: covered in sprint 7
A20: 13 | B20: AMO Plus | D20: Remaining stock product PG | E20: Remaining stock product PG | F20: Info sisa stok yang dibawa PG di page transaksi | G20: Maulana | H20: Duta | J20: 45925 | K20: Sprint 7 | N20: covered in sprint 7
A21: 14 | B21: AMO Plus | D21: Price product di page transaksi | E21: Price product di page transaksi | F21: Info price product / SKU di halaman transaksi | G21: Maulana | H21: Duta | J21: 45925 | K21: Sprint 7 | N21: covered in sprint 7
A22: 15 | B22: AMO Plus | D22: Reconciliation report | E22: Reconciliation report | F22: Menggabungkan LPU dan BPPB pada AMO | G22: Maulana | H22: Duta | J22: 45925 | K22: Sprint 7 | N22: covered in sprint 7
A23: 16 | B23: AYO Mitra Plus | D23: Manual assign by PG khususnya jika ada PG yg tidak masuk | E23: Manual assign by PG khususnya jika ada PG yg tidak masuk | F23: Manual assign by PG khususnya jika ada PG yg tidak masuk | G23: Maulana | H23: Sri P | J23: 45925 | K23: Sprint 7 | N23: covered in sprint 7
A24: 17 | B24: AYO Mitra Plus | D24: Grouping order by PG di hari H-1 | E24: Grouping order by PG di hari H-1 | F24: Grouping order by PG di hari H | G24: Maulana | H24: Sri P | J24: 45925 | K24: Sprint 7 | N24: covered in sprint 7
A25: 18 | B25: AYO Mitra Plus | D25: Mitra tetap dapat melakukan cluster, meskipun masih ada pesanan dalam pengiriman | E25: Mitra tetap dapat melakukan cluster, meskipun masih ada pesanan dalam pengiriman | F25: Mitra tetap dapat melakukan proses pesanan, ketika ada pesanan baru | G25: Maulana | H25: Sri P | J25: 45925 | K25: Sprint 7 | N25: covered in sprint 7
A26: 19 | B26: AYO Mitra Plus | D26: Fixing miss cluster | E26: Fixing miss cluster | F26: Fixing miss cluster | G26: Maulana | H26: Sri P | J26: 45925 | K26: Sprint 7 | N26: covered in sprint 7
A27: 20 | B27: AYO Mitra Plus | D27: Simply Initial load reccomendation | E27: Simply Initial load reccomendation | F27: Simply Initial load reccomendation | G27: Maulana | H27: Sri P | J27: 45925 | K27: Sprint 7 | N27: covered in sprint 7
A28: 21 | B28: MyHero | D28: Hygiene document | E28: LPU | F28: Saat ini yang muncul ketika cetak LPU hanyalah tanggal cetak, bukan tanggal journeynya | G28: Hadi Pram | H28: Nika | J28: 45925 | K28: Sprint 7
F29: Add 1 field for tanggal journey
A30: 22 | B30: MyHero | D30: Multicategory document | E30: BPPB, Add load | F30: On top of kode barang, penambahan Prod name (masking) di BPPB untuk FMCG | G30: Hadi Pram | H30: Nika | J30: 45925 | K30: Sprint 7
A31: 23 | B31: MyHero | D31: Multicategory document | E31: BPPB, Add load | F31: Printed doc DN after jourgen dan input initial load by back end | G31: Hadi Pram | H31: Nika | J31: 45925 | K31: Sprint 7
A32: 24 | B32: CITA | D32: Detect distinct SKU and pack quantity inside paket produk | E32: Detect distinct SKU and pack quantity inside paket produk | F32: To be able to detect quantity of packs inside Paket Produk | G32: Nessia | H32: Sri/CI | J32: 45925 | K32: Sprint 7 | N32: covered in sprint 7
A33: 25 | B33: CITA | D33: Category Standardization | E33: Category Standardization | F33: To standardize category chip shown on CITA to refer to category on Product Principal instead of referring on "subfamily" column on produk supplier menu on Control Tower | G33: Nessia | H33: Sri/CI | J33: 45925 | K33: Sprint 7 | N33: covered in sprint 7
A34: 26 | B34: AYO Kasir | D34: Eliminate double transaction happened in AYO due unresponsive Payment gateway | E34: [CDE-25950] AYO Kasir - Limit transaction when FF spam selesaikan pesanan button more than 1x | G34: Marcha | H34: Ida/Adnan | J34: 45925 | K34: Sprint 7 | N34: deployed, 13 aug
A35: 27 | B35: AYO Kasir | D35: Integrate ORF request & process in AYO Kasir | E35: ORF | F35: ORF submission form & process in AYO Kasir to eliminate manual form & manual tracking | G35: Marcha | H35: Ida/Adnan | J35: 45925 | K35: Sprint 7 | N35: covered in sprint 7 ( tp butuh lintas sprint)
A36: 28 | B36: AYO Kasir | D36: Provide inventory data access to AYO Kasir Admin | E36: Stock Count & Stock Adjusment | F36: Laporan inventory harian per toko, per staff, per SKU untuk membantu daily stock take process | G36: Marcha | H36: Ida/Adnan | J36: 45925 | K36: Sprint 7 | N36: covered in sprint 7 ( tp butuh lintas sprint)
A37: 29 | B37: AYO Kasir | D37: Support perpindahan stock antar toko (pemerataan Limited stock & LOGD) | E37: Stock Transfer Store to Store | F37: Stock dapat dipindahkan antar toko (dan antar SLOC) melalui fitur stock movement (beserta history nya) yang dapat di tracking, termasuk dengan penyesuaian di SAP nya | G37: Marcha | H37: Ida/Adnan | J37: 45925 | K37: Sprint 7 | N37: covered in sprint 7 ( tp butuh lintas sprint)
A38: 30 | B38: AYO Kasir | D38: Support loyalty/miles program di IQOS Partne dan allow customization | E38: IP Miles, VAP, Delivery Partner Program | F38: IP memiliki beberapa loyalty toolbox option yang bisa dipilih oleh masing-masing mereka, menyesuaikan dengan kebutuhan bisnis | G38: Marcha | H38: Ida/Adnan | J38: 45925 | K38: Sprint 7 | N38: covered in sprint 7 ( tp butuh lintas sprint)
A39: 31 | B39: AYO Kasir | D39: Provide inventory management & tracking untuk AYO Kasir admin dalam memindahkan stock ke setiap staff | E39: Stock Transfer Admin to Staff | F39: AYO Kasir Admin memerlukan control terhadap inventory management & movement di setiap staff nya, termasuk visibility terkait stock on hand dan movement history yang bisa di track setiap saat untuk monitoring & stock audit | G39: Marcha | H39: Ida/Adnan | J39: 45925 | K39: Sprint 7 | N39: covered in sprint 7
A40: 32 | B40: AYO Kasir | D40: Provide codentify form box for each device purchased --> link device | E40: Device Codentify Input for every device purchased in same order id | F40: Setiap device yang terdapat di dalam suatu transaksi, memerlukan input informasi ke dalam system untuk codentify untuk setiap device. Saat ini, AYO Kasir hanya | G40: Marcha | H40: Ida/Adnan | J40: 45925 | K40: Sprint 7 | N40: covered in sprint 7
A41: 33 | B41: AYO Kasir | D41: Voucher enhancement | E41: Voucher enhancement | F41: Voucher Product Limitation Adjustment | G41: Marcha | H41: Ida/Adnan | J41: 45925 | K41: Sprint 7 | N41: covered in sprint 7
A42: 34 | B42: AYO Kasir | D42: Improve product demo experience for better trial & acceptance | E42: Taste Advisory | F42: Taste Advisory feature yang saat ini tersedia di Qoncierge untuk bisa di integrate ke AYO Kasir untuk seamless journey & data connection (konsumen & transaksi) | G42: Marcha | H42: Ida/Adnan | J42: 45925 | K42: Sprint 7 | N42: covered in sprint 7
A43: 35 | B43: AYO Kasir | D43: Enable AYO Kasir Web Version to be fully operated in IOS based device (All Pages) | E43: AYO Kasir responsive (phase 2) - Compatibility in mobile version (web) | F43: Enable AYO Kasir web to be accessed in mobile browser | G43: Feli/Sean | H43: Ida/Adnan | J43: 45955 | K43: Sprint 8 (prio1) | L43: 1 | P43: Sprint 8
A44: 36 | B44: AYO Kasir | D44: Enable AYO Kasir Web Version to be fully operated in IOS based device (Catalog Pages) | E44: AYO Kasir responsive (phase 3) - Compatibility in mobile version (catalog) | F44: Enable AYO Kasir web to be accessed in mobile browser | G44: Feli/Sean | H44: Ida/Adnan | J44: 45955 | K44: Sprint 8 (prio1) | L44: 2 | P44: Sprint 9
A45: 37 | B45: AYO Kasir | D45: Data Security - Global Requirement | E45: Pentest Finding: Show generic error message to omit info if phone number exists in database | F45: As a part of security finding, we need to create 1 login page for user to insert phone number and passcode, and show a generic error message to users. | G45: Feli/Sean | H45: Ida/CI | J45: 45955 | K45: Sprint 8 (prio1) | L45: 6 | P45: Sprint 8 Waiting mandays assessment
F46: The deadline to fix the finding is in October 2025.
A47: 38 | B47: AYO Kasir | D47: Improve ORF accuracy by each touchpoint to ensure sufficient inventory management & security | E47: AYO Kasir - ORF Warehouse Replenishment - Jira (Phase 3) - PKM ORF | F47: AYO Kasir to be automatically provide ORF Qty recommendation for each touchpoints/coach based on Sales historical & current stock | G47: Feli/Sean | H47: Ida/Adnan | J47: 45955 | K47: Sprint 8 (prio1) | L47: 7 | P47: Need more info for max threshold number of stock from pak Indra
A48: 39 | B48: AYO Kasir | D48: Provide proper replacement service with proper process in terms of inventory & finance management, similar to DCE configuration | E48: phase 1: input replacement transaction | F48: Feature to enable SFP device replacement in AYO Kasir by inputting replacement transaction and having DCE API to check device eligibility & record the replacement. | G48: Feli/Sean | H48: Ida/Adnan | J48: 45955 | K48: Sprint 8 (prio1) | L48: 4 | P48: Need clarity from business for: 1. WH: auto STO (final, tanpa perlu edit) 2. OTC: Sync transaksi ke SAP, SLOC replacement
E49: phase 2: QURE in AYO Kasir
A50: 40 | B50: AYO Kasir | D50: Offline mode AYO Kasir & data synchronization (to SAP & DCE) ability | E50: Allow AYO Kasir to go with offline mode during network limitation and allow data synchronization when back to online | F50: Feature to enable AYO Kasir to be used in offline mode. Usually applicable for events, where there's no signal | G50: Feli/Sean | H50: Ida/Adnan | J50: 45955 | K50: Sprint 8 (prio1) | L50: 8 | P50: Need BRD
A51: 41 | B51: AYO Kasir | D51: Access Management differentiation for each role | E51: a. SDR to assign TL to selected touchpoint | F51: Feature for Team Leader and runner to access several booth/kiosk accounts | G51: Feli/Sean | H51: Ida/Adnan | J51: 45955 | K51: Sprint 8 (prio1) | L51: 3 | P51: Sprint 8
E52: b. TL to login AYO Kasir for few touchpoint using 1 account
E53: c. TL to assign runner to selected touchpoint
E54: d. Runner to login AYO Kasir for few touchpoint using 1 account
A55: 42 | B55: AYO Kasir | D55: AYO Principal - Payment gateway configuration for each customer type in AYO Principal | E55: Feature in AYO Principle to set accurate TID, MID and customer type for payment gatewaty configuration | F55: Feature in AYO Principle to set accurate TID, MID and customer type for payment gatewaty configuration | G55: Feli/Sean | H55: Ida/Adnan | J55: 45955 | K55: Sprint 8 (prio1) | L55: 9 | P55: Sprint 8
A56: 43 | B56: AYO Kasir | D56: Add shopping bag as sellable item, with proper configuration in finance & transaction record | E56: a. Enable shopping bag transaction to be recognized by SAP | F56: Shopping Bag IQOS akan menjadi sellable item dan menjadi berbayar. | G56: Feli/Sean | H56: Ida/Adnan | J56: 45955 | K56: Sprint 8 (prio1) | L56: 5 | P56: Sprint 8
E57: b. Enable stock count of shopping bag in AYO Kasir
A58: 44 | B58: AYO Kasir | D58: Aligning coin reward from new leads/member registration with DSD purchase history | E58: Automatic coin rewards for leads/member registration - SRC IQOS Point | F58: Currently, there is matching process between the amount of leads/member registration with DSD purchase by SRC/SRC IQOS Point. | G58: Feli/Sean | H58: Jess/Ragib | J58: 45955 | K58: Sprint 8 (prio1) | L58: 12 | P58: Sprint 8
F60: This will result in discrepency and potential for fraud.
A61: 45 | B61: DTE | D61: Streamlining coin approval process to become more efficient | E61: Change Process Flow - Coins Approval | F61: Currently, when user conduct RFT or Transfer to Pojok Bayar the process is very lengthy. Through this initiative, we propose a way on how to ensure this process can be conducted in more efficient manner. | G61: Michael Stephen | H61: Hanif/Jess | J61: 45955 | K61: Sprint 8 (prio1) | L61: 1
F63: Approval from related Departments have already been secured.
A64: 46 | B64: PBI | D64: FMCG performance | E64: Add multiple SKU selection PNM in KSI panamas | F64: Add multiple SKU selection PNM in KSI panamas | G64: Junaidi | H64: Nika | J64: 45955 | K64: Sprint 8 (prio1) | L64: 1
A65: 47 | B65: AYO Kasir | D65: Delimit AYO Kasir Stock at SRC IQOS Point to enable higher stock input | E65: Delimit AYO Kasir Stock - SFP | F65: SRC IQOS Point have limitation in adding product due to stock number restriction. This limitation needs to be removed. | G65: Feli/Sean | H65: Jess/Ragib | J65: 45955 | K65: Sprint 8 (prio1) | L65: 13 | P65: Sprint 8 Waiting mandays assessment
A66: 48 | B66: AYO Kasir | D66: Provide "Order Cart" / "Order Draft" Feature before continue to payment | E66: Draft order and reload after doing other activities | F66: Memungkinkan Frontliners untuk menyimpan dulu draft order (seperti cart di e-commerce) sebelum melanjutkan ke payment/complete transaksi, sering digunakan pada saat traffic lagi ramai, >1 konsumen yang perlu dilayani dan diantara mereka masih mungkin untuk merubah item pembelanjaan | G66: Feli/Sean | H66: Ida/Adnan | J66: 45955 | K66: Sprint 8 (prio2) | L66: 10 | P66: Need BRD
A67: 49 | B67: AYO Kasir | D67: Separate product stock for each inventory type (similar to DCE) | E67: Stock categories - sellable & non-sellable | F67: Replicate DCE (CEGID & CeApp), dimana stock untuk product sellable dan non-sellable (product demo stock, display, broken device from replacement, trade in) tidak tercampur menjadi satu, memastikan proses disposal & return ke WH termasuk financial record nya bisa tepat & akurat | G67: Feli/Sean | H67: Ida/Adnan | J67: 45955 | K67: Sprint 8 (prio2) | L67: 11
E68: - Guided Trial
E69: - Replacement
E70: - Display Stock
E71: - Trade in
A72: 50 | B72: DTE | D72: Add Visual Overlay Guide | E72: Visual Overlay Guides for In-App Camera | F72: Currently, there are no guidelines for users taking photos, which may result in pictures being taken under various conditions, not follow to the specified guidance. | G72: Michael Stephen | H72: Hanif/Jess | J72: 45955 | K72: Sprint 8 (prio2) | L72: 5
F73: To improve the quality and reliability of photo submissions during DTE missions in the AYO Toko mobile app, we are introducing key enhancements that address both user experience and submission integrity.
F74: Visual Overlay Guides for In-App Camera
F75: Users often struggle to align their photos with brand-specific display requirements (e.g., Coca-Cola planogram, Aqua Danone layout, cigarette display standards). This leads to frequent submission errors, rework, and delays in mission validation. To address this, we will implement visual overlay guides directly on the in-app camera. These semi-transparent templates will help users align their camera shots with the expected visual standards, reducing human error and ensuring compliance with planogram expectations. This feature enhances clarity and guidance during submission, resulting in higher-quality, brand-compliant data capture.
A76: 51 | B76: DTE | D76: To understand user behaviour and provide analytics in DTE platform in AYO Toko | E76: GA AYO Toko Tracking | F76: Implement Google Analytics for DTE features in Ayo Toko to understand user behavior. | G76: Michael Stephen | H76: Hanif/Jess | J76: 45955 | K76: Sprint 8 (prio2) | L76: 3
A77: 52 | B77: DTE | D77: Send reminder to budget owner if it's below a pre-defined threshold to ensure the sustainability of the program | E77: Trade Program Budget Reminder | F77: Send reminder to budget owner if it's below a pre-defined threshold. Reminder will be sent regularly until certain actions are taken (program expired, additional budget, manual close/delete) | G77: Michael Stephen | H77: Hanif/Jess | J77: 45955 | K77: Sprint 8 (prio2) | L77: 6
A78: 53 | B78: DTE | C78: Principal, CITA | D78: DTE CITA Missions | E78: Reactivate inactive CITA users and increase the pool size of active CITA users | F78: Introduce Missions on CITA | G78: Michael | K78: Sprint 8 | L78: 4
A79: 54 | B79: DTE | D79: DTE Avatar Entry Point | E79: New entry point for Mission Performance and Mission Guidance video | F79: New entry point for Mission Performance and Mission Guidance video | G79: Michael Stephen | H79: Hanif/Jess | J79: 45955 | K79: Sprint 8 (prio2) | L79: 2
A80: 55 | B80: DTE | D80: Recaptured Image Detection using Moire Pattern | E80: Detect and flag Moiré patterns in submitted images to identify potential manipulation and prevent fraudulent execution verification. | F80: Detect and flag Moiré patterns in submitted images to identify potential manipulation and prevent fraudulent execution verification. | G80: Michael Stephen | H80: Ahmad/Jeffry | J80: 45955 | K80: Sprint 8 (prio2) | L80: Deprio | O80: Sprint 9
A81: 56 | B81: AMO Plus | D81: AYO Mitra Plus Hybrid Mode | E81: AYO Mitra Plus Hybrid Mode | F81: AMO Existing bisa digunakan dengan AYO Mitra yang baru | G81: Varhan | H81: Sri P | J81: 45955 | K81: Sprint 8 (prio2) | L81: 1
A82: 57 | B82: AYO Mitra | D82: Cluster mapping | E82: Capability AYO Mitra Plus untuk export dan import hasil clutering agar memudahkan proses revisi cluster. (akan dihandle dari principal dan internal HMS bisa suggest cluster via principal) | F82: Capability AYO Mitra Plus untuk export dan import hasil clutering agar memudahkan proses revisi cluster. | G82: Varhan | H82: Sri P | J82: 45955 | K82: Sprint 8 (prio2) | L82: 2
E83: Untuk new customer akan ikut ditarik datanya dan ada flagging "new" (tersedia di mid aug) | F83: Untuk new customer akan ikut ditarik datanya dan ada flagging "new".
E84: Jika PIC melakukan update
E85: Skenario : jika zone melakukan update panel di CT, maka data panel yang baru akan ikut ditarik | F85: Skenario : jika zone melakukan update panel di CT, maka data panel yang baru akan ikut ditarik
A86: 58 | B86: AYO Mitra | D86: Cluster mapping | E86: - Jika ada update panel di CT, maka panel baru tersebut akan secara otomatis terassign ke PG di AYO Mitra. | F86: - Jika ada update panel CITA di CT, maka panel baru tersebut akan secara otomatis terassign ke PG di AYO Mitra. | G86: Varhan | H86: Sri P | J86: 45955 | K86: Sprint 8 (prio2) | L86: 3 | V86: Deployment proposed
E87: '- Panel baru akan diassignkan ke PG terdekat. | F87: - panel baru akan diassignkan ke PG terdekat.
E88: Hasil clustering bisa dilihat CT (misal di Retailer Mapping ada PG ID nya), sehingga bisa dijadikan bahan review | F88: Hasil clustering bisa dilihat CT (misal di Retailer Mapping ada PG ID nya), sehingga bisa dijadikan bahan review
A89: 59 | B89: Ayo Qoncierge Coach | D89: Test Advisory Revamp | E89: Create website builder for Taste Advisory Page | F89: Business can set up for catalog matrix & page design for Taste Advisory | G89: Wildan & Michel | H89: Mustika Nagari | K89: Sprint 8 | L89: 1
A90: 60 | B90: AYO Principal | D90: Duplication Number in Retailer Mapping | E90: Currently there are duplicated phone number between CT and iSMS | F90: to avoid possible bugs happening we need to ensure that CT has a unique phone number between each retailer. Still on discussion to fix this | G90: Ariph | K90: Sprint 8 | L90: 7
A91: 61 | B91: AYO Principal | D91: Validation Retailer Mapping | E91: If user principal updating a duplicated value for phone number, it will rejected by the system. | F91: if user uploading duplicated phone number, then it will be rejected for that specific row, and shown to the user. | G91: Ariph | K91: Sprint 8 | L91: Deprio | O91: Sprint 9
A92: 62 | B92: CITA | C92: Principal, OSEM, TSM, My Hero, AMO | D92: [CITA Loyalty] dormant users keep increasing despite the rapid increase of DAU from dijamin1klik. | E92: retain users and increase regular purchasers through loyalty program, learning from AYO DTE | G92: Jere, Michael | H92: CI/Commstrat | K92: Sprint 8 | L92: 3 | N92: v
A93: 63 | B93: CITA | C93: Principal, OSEM, TSM | D93: [CITA Coachmark] no guidance exists on CITA to help users navigate important activities by themselves | E93: user can learn to operate the platform by themselves and reduce dependency to FF | F93: enable coachmark for every user, at the right time, tailored for each user type-- dormant, regular, etc. In the context of D1K, the coachmark is adaptive. By adaptivemeans the coachmark is tailored based on FF’s stock recommendations.​ | G93: Jere | H93: CI | K93: Sprint 8 | L93: 2 | N93: v
A94: 64 | B94: CITA | C94: Principal, DTE, MyHero | D94: [Instant CN Rewards] Currently, CN Rewards are only applied to Direct Selling activities, and the reward distribution is not immediate—it can only be redeemed during the next visit by the salesman, which typically occurs every two weeks. | E94: Enabling instant reward distribution to digital platform | F94: Instant CN Rewards, | G94: Jere | H94: Trade Team | K94: Sprint 8 | L94: 1 | N94: v
F95: we would like to allocate a portion of the coins to CITA, allowing users to redeem digital vouchers or use them to offset the total order value when purchasing through CITA
A96: 65 | B96: CITA | C96: Principal, OSEM, TSM | D96: [CITA PN Integration to OSEM&TSM] Currently, CITA relies on manual audience selection for sending push notifications, which results in significant administrative effort and static targeting. | E96: To improve efficiency and relevance when sending push notification to users | F96: Push Notification Integration with TSM and OSEM | G96: Jere | H96: CI/Deployment | K96: Sprint 8 | L96: 4
F98: This integration will enable trigger- and condition-based notifications, as well as dynamic audience segmentation. As a result, notifications will reach the right users at the right time, while also reducing manual workload for our admins.
A99: 66 | B99: MyAyo Web | C99: AYO Toko | D99: Metahuman for PD Support at SRC | E99: SRC Customer have an access for product knowledge, especially for IQOS BONDS | F99: Metahuman support by Global Vendor Synthesia. Consumer can access through QR scanning after registration at SRC as Leads | G99: Wildan | K99: Sprint 8 | L99: 1
A100: 67 | B100: SSR | D100: LAS/LANU Registration for KA (IDM) | E100: Facilitate LAS LANU for self registration & Device Link | F100: Website that LAS/LANU can access for registration process & device link | G100: Wildan | H100: Ivan Orlando | K100: Sprint 8 | L100: 1
A101: 68 | B101: Principal SFP | C101: AYO Toko, My Hero, iSMS, SAP | D101: Customer registration for IQOS Partner (Phase I) | E101: Create seamless system integration for IQOS Partner Registration | F101: Create seamless system integration for IQOS Partner Registration, & initial support invoice automatitation | G101: Wildan | H101: Mustika Nagari | K101: Sprint 8 | L101: 1
A102: 69 | B102: TANIA | C102: Tania | D102: Tania for SFP | E102: Interactive AI to support frontliner incentive | F102: Tanai will giving information & recommendation of the frontliner achievement status | G102: Wildan | K102: Sprint 8 | L102: 2
A103: 70 | B103: AYO Principal | D103: CMS For Tania | E103: To create CMS for Tania in AYO Principal | F103: for this phase it will be simple editor and add edit delete content in AYO Principal. | G103: Ariph | H103: Arum | K103: Sprint 8 | L103: 13 | M103: Sprint7 | N103: v
...

Sheet Sprint 8 with Prio (unlocked) 2
A1: Sprint List | H1: AYO Toko | J1: (3) | K1: DTE | L1: 12
A2: Objective : File ini digunakan oleh CI dan Deployment untuk mentracking List Sprint sepanjang tahun 2025 | H2: MyHero | I2: =66 -> 66 | J2: (1) | K2: AYO Kasir | L2: 97
A3: User yang memiliki akses untuk edit adalah : Tim Deployment & CI | J3: (2) | K3: CITA | L3: 50 | M3: 10 | N3: allocate to AYO Kasir
A4: Sprint 7, need tobe check by tim CI | K4: AYO Mitra
K5: AMO | L5: 107 | O5: SPRINT 8
C6: CI Team | G6: CI Team | L6: assume 1 sprint = 10 mandays | O6: 45904 | P6: 45920 | Q6: 45927 | R6: 45929 | S6: 45958
A7: No | B7: Platform (Aplikasi) | C7: Dependency | D7: Background | E7: Objective | F7: Description | G7: Product Manager | H7: Requestor | I7: Chanel | J7: Expected Deployed | K7: Sprint | L7: Rank Prio | M7: Sprint Carry Over | N7: Update 0 8/28 | O7: Update 1 | P7: Update 2 | Q7: Update 3 | R7: Update 4 | S7: Update 5 | T7: Update 6 | U7: Update 7 | V7: JIRA | W7: Mandays
A8: 1 | B8: AMO | D8: QR code phase 2 (adding button to top up canvassing during pengiriman CITA di AMO offline) | E8: QR code phase 2 (adding button to top up canvassing during pengiriman CITA di AMO offline) | F8: QR code phase 2 (adding button to top up canvassing during pengiriman CITA di AMO offline) | G8: Marcha | H8: Duta | J8: 45870 | K8: Sprint 6 | O8: Done
A9: 2 | B9: AMO | D9: Canvassing = Product assortment / carousel untuk focused product | E9: Canvassing = Product assortment / carousel untuk focused product | F9: Canvassing = Product assortment / carousel untuk focused product follow B2B | G9: Marcha | H9: Duta | J9: 45870 | K9: Sprint 6 | O9: Done
A10: 3 | B10: AMO | D10: SKU reminder untuk focused product sebelum dilakukan payment | E10: SKU reminder untuk focused product sebelum dilakukan payment | F10: SKU reminder untuk focused product sebelum dilakukan payment (Re-offering) | G10: Marcha | H10: Duta | J10: 45870 | K10: Sprint 6 | O10: Done
A11: 4 | B11: AMO | D11: Mendapatkan progress achievement PG (Unique Call, Volume canvass & CITA) dari PBI Reporting AMO | E11: Mendapatkan progress achievement PG (Unique Call, Volume canvass & CITA) dari PBI Reporting AMO | F11: Mendapatkan progress achievement PG (Unique Call, Volume canvass & CITA) dari PBI Reporting AMO | G11: Marcha | H11: Duta | J11: 45870 | K11: Sprint 6 | O11: Done
A12: 5 | B12: AMO | D12: Add tab "Laporan" untuk menunjukan progress achievement PG (Unique Call, Volume canvass & CITA) | E12: Add tab "Laporan" untuk menunjukan progress achievement PG (Unique Call, Volume canvass & CITA) | F12: Add tab "Laporan" untuk menunjukan progress achievement PG (Unique Call, Volume canvass & CITA) | G12: Marcha | H12: Duta | J12: 45870 | K12: Sprint 6 | O12: Done
A13: 6 | B13: AYO Principal | D13: Elevate Automation | E13: Elevate - Data Entry | F13: Capability untuk user bisa melakukan WO atau guideline submission | G13: Nessia | H13: Nika | J13: 45930 | K13: Sprint 7
A14: 7 | B14: AYO Principal | D14: Elevate Automation | E14: Elevate - Email generator | F14: Capability elevate untuk generate email ke zone sehubungan dengan WO/guideline yang diinputkan di Elevate | G14: Nessia | H14: Nika | J14: 45930 | K14: Sprint 7
A15: 8 | B15: AYO Principal | D15: Elevate Automation | E15: Elevate - Cycle calendar | F15: Capability untuk show dan filter WO atau guideline yang impact ke waktu week tertentu | G15: Nessia | H15: Nika | J15: 45930 | K15: Sprint 7
A16: 9 | B16: Control Tower | D16: Seamless data upload | E16: CT Update Schedulling and rework data entry template | F16: Flexybility update data in CT by add feature schedule | G16: Nessia | H16: Sri P | J16: 45930 | K16: Sprint 7 | M16: Sprint 8 | N16: carry over to the next sprint
A17: 10 | B17: AMO | D17: Canvassing | E17: Fitur Scan QR pada mode Canvassing | F17: Edit text Kunjungan Non Downline menjadi "Mulai Kunjungan", direct page to fitur Scan QR dan akan ter-mapping ke customer registered HMS as map to RE | G17: Marcha | H17: Duta | J17: 45930 | K17: Sprint 7 | N17: covered in sprint 7
A18: 11 | B18: AMO plus | D18: Filter type outlet di maps | E18: Filter type outlet di maps | F18: Selecting toko yang tampil di peta pada AMO | G18: Maulana | H18: Duta | J18: 45930 | K18: Sprint 7
A19: 12 | B19: AMO Plus | D19: Search downline PG | E19: Search downline PG | F19: Fitur search downline salesman/mitra di AMO+ (seperti di AMO Existing) | G19: Maulana | H19: Duta | J19: 45930 | K19: Sprint 7 | N19: covered in sprint 7
A20: 13 | B20: AMO Plus | D20: Remaining stock product PG | E20: Remaining stock product PG | F20: Info sisa stok yang dibawa PG di page transaksi | G20: Maulana | H20: Duta | J20: 45930 | K20: Sprint 7 | N20: covered in sprint 7
A21: 14 | B21: AMO Plus | D21: Price product di page transaksi | E21: Price product di page transaksi | F21: Info price product / SKU di halaman transaksi | G21: Maulana | H21: Duta | J21: 45930 | K21: Sprint 7 | N21: covered in sprint 7
A22: 15 | B22: AMO Plus | D22: Reconciliation report | E22: Reconciliation report | F22: Menggabungkan LPU dan BPPB pada AMO | G22: Maulana | H22: Duta | J22: 45930 | K22: Sprint 7 | N22: covered in sprint 7
A23: 16 | B23: AYO Mitra Plus | D23: Manual assign by PG khususnya jika ada PG yg tidak masuk | E23: Manual assign by PG khususnya jika ada PG yg tidak masuk | F23: Manual assign by PG khususnya jika ada PG yg tidak masuk | G23: Maulana | H23: Sri P | J23: 45930 | K23: Sprint 7 | N23: covered in sprint 7
A24: 17 | B24: AYO Mitra Plus | D24: Grouping order by PG di hari H-1 | E24: Grouping order by PG di hari H-1 | F24: Grouping order by PG di hari H | G24: Maulana | H24: Sri P | J24: 45930 | K24: Sprint 7 | N24: covered in sprint 7
A25: 18 | B25: AYO Mitra Plus | D25: Mitra tetap dapat melakukan cluster, meskipun masih ada pesanan dalam pengiriman | E25: Mitra tetap dapat melakukan cluster, meskipun masih ada pesanan dalam pengiriman | F25: Mitra tetap dapat melakukan proses pesanan, ketika ada pesanan baru | G25: Maulana | H25: Sri P | J25: 45930 | K25: Sprint 7 | N25: covered in sprint 7
A26: 19 | B26: AYO Mitra Plus | D26: Fixing miss cluster | E26: Fixing miss cluster | F26: Fixing miss cluster | G26: Maulana | H26: Sri P | J26: 45930 | K26: Sprint 7 | N26: covered in sprint 7
A27: 20 | B27: AYO Mitra Plus | D27: Simply Initial load reccomendation | E27: Simply Initial load reccomendation | F27: Simply Initial load reccomendation | G27: Maulana | H27: Sri P | J27: 45930 | K27: Sprint 7 | N27: covered in sprint 7
A28: 21 | B28: MyHero | D28: Hygiene document | E28: LPU | F28: Saat ini yang muncul ketika cetak LPU hanyalah tanggal cetak, bukan tanggal journeynya Add 1 field for tanggal journey | G28: Hadi Pram | H28: Nika | J28: 45930 | K28: Sprint 7
A29: 22 | B29: MyHero | D29: Multicategory document | E29: BPPB, Add load | F29: On top of kode barang, penambahan Prod name (masking) di BPPB untuk FMCG | G29: Hadi Pram | H29: Nika | J29: 45930 | K29: Sprint 7
A30: 23 | B30: MyHero | D30: Multicategory document | E30: BPPB, Add load | F30: Printed doc DN after jourgen dan input initial load by back end | G30: Hadi Pram | H30: Nika | J30: 45930 | K30: Sprint 7
A31: 24 | B31: CITA | D31: Detect distinct SKU and pack quantity inside paket produk | E31: Detect distinct SKU and pack quantity inside paket produk | F31: To be able to detect quantity of packs inside Paket Produk | G31: Nessia | H31: Sri/CI | J31: 45930 | K31: Sprint 7 | N31: covered in sprint 7
A32: 25 | B32: CITA | D32: Category Standardization | E32: Category Standardization | F32: To standardize category chip shown on CITA to refer to category on Product Principal instead of referring on "subfamily" column on produk supplier menu on Control Tower | G32: Nessia | H32: Sri/CI | J32: 45930 | K32: Sprint 7 | N32: covered in sprint 7
A33: 26 | B33: AYO Kasir | D33: Eliminate double transaction happened in AYO due unresponsive Payment gateway | E33: [CDE-25950] AYO Kasir - Limit transaction when FF spam selesaikan pesanan button more than 1x | G33: Marcha | H33: Ida/Adnan | J33: 45930 | K33: Sprint 7 | N33: deployed, 13 aug
A34: 27 | B34: AYO Kasir | D34: Integrate ORF request & process in AYO Kasir | E34: ORF | F34: ORF submission form & process in AYO Kasir to eliminate manual form & manual tracking | G34: Marcha | H34: Ida/Adnan | J34: 45930 | K34: Sprint 7 | N34: covered in sprint 7 ( tp butuh lintas sprint)
A35: 28 | B35: AYO Kasir | D35: Provide inventory data access to AYO Kasir Admin | E35: Stock Count & Stock Adjusment | F35: Laporan inventory harian per toko, per staff, per SKU untuk membantu daily stock take process | G35: Marcha | H35: Ida/Adnan | J35: 45930 | K35: Sprint 7 | N35: covered in sprint 7 ( tp butuh lintas sprint)
A36: 29 | B36: AYO Kasir | D36: Support perpindahan stock antar toko (pemerataan Limited stock & LOGD) | E36: Stock Transfer Store to Store | F36: Stock dapat dipindahkan antar toko (dan antar SLOC) melalui fitur stock movement (beserta history nya) yang dapat di tracking, termasuk dengan penyesuaian di SAP nya | G36: Marcha | H36: Ida/Adnan | J36: 45930 | K36: Sprint 7 | N36: covered in sprint 7 ( tp butuh lintas sprint)
A37: 30 | B37: AYO Kasir | D37: Support loyalty/miles program di IQOS Partne dan allow customization | E37: IP Miles, VAP, Delivery Partner Program | F37: IP memiliki beberapa loyalty toolbox option yang bisa dipilih oleh masing-masing mereka, menyesuaikan dengan kebutuhan bisnis | G37: Marcha | H37: Ida/Adnan | J37: 45930 | K37: Sprint 7 | N37: covered in sprint 7 ( tp butuh lintas sprint)
A38: 31 | B38: AYO Kasir | D38: Provide inventory management & tracking untuk AYO Kasir admin dalam memindahkan stock ke setiap staff | E38: Stock Transfer Admin to Staff | F38: AYO Kasir Admin memerlukan control terhadap inventory management & movement di setiap staff nya, termasuk visibility terkait stock on hand dan movement history yang bisa di track setiap saat untuk monitoring & stock audit | G38: Marcha | H38: Ida/Adnan | J38: 45930 | K38: Sprint 7 | N38: covered in sprint 7
A39: 32 | B39: AYO Kasir | D39: Provide codentify form box for each device purchased --> link device | E39: Device Codentify Input for every device purchased in same order id | F39: Setiap device yang terdapat di dalam suatu transaksi, memerlukan input informasi ke dalam system untuk codentify untuk setiap device. Saat ini, AYO Kasir hanya | G39: Marcha | H39: Ida/Adnan | J39: 45930 | K39: Sprint 7 | N39: covered in sprint 7
A40: 33 | B40: AYO Kasir | D40: Voucher enhancement | E40: Voucher enhancement | F40: Voucher Product Limitation Adjustment | G40: Marcha | H40: Ida/Adnan | J40: 45930 | K40: Sprint 7 | N40: covered in sprint 7
A41: 34 | B41: AYO Kasir | D41: Improve product demo experience for better trial & acceptance | E41: Taste Advisory | F41: Taste Advisory feature yang saat ini tersedia di Qoncierge untuk bisa di integrate ke AYO Kasir untuk seamless journey & data connection (konsumen & transaksi) | G41: Marcha | H41: Ida/Adnan | J41: 45930 | K41: Sprint 7 | N41: covered in sprint 7
A42: 35 | B42: AYO Kasir | D42: Enable AYO Kasir Web Version to be fully operated in IOS based device (All Pages) | E42: AYO Kasir responsive (phase 2) - Compatibility in mobile version (web) | F42: Enable AYO Kasir web to be accessed in mobile browser | H42: Ida/Adnan | J42: 45955 | K42: Sprint 8 (prio1)
A43: 36 | B43: AYO Kasir | D43: Enable AYO Kasir Web Version to be fully operated in IOS based device (Catalog Pages) | E43: AYO Kasir responsive (phase 3) - Compatibility in mobile version (catalog) | F43: Enable AYO Kasir web to be accessed in mobile browser | H43: Ida/Adnan | J43: 45955 | K43: Sprint 8 (prio1)
A44: 37 | B44: AYO Kasir | D44: Data Security - Global Requirement | E44: Pentest Finding: Show generic error message to omit info if phone number exists in database | F44: As a part of security finding, we need to create 1 login page for user to insert phone number and passcode, and show a generic error message to users. The deadline to fix the finding is in October 2025. | H44: Ida/CI | J44: 45955 | K44: Sprint 8 (prio1)
A45: 38 | B45: AYO Kasir | D45: Improve ORF accuracy by each touchpoint to ensure sufficient inventory management & security | E45: AYO Kasir - ORF Warehouse Replenishment - Jira (Phase 3) - PKM ORF | F45: AYO Kasir to be automatically provide ORF Qty recommendation for each touchpoints/coach based on Sales historical & current stock | H45: Ida/Adnan | J45: 45955 | K45: Sprint 8 (prio1)
A46: 39 | B46: AYO Kasir | D46: Provide proper replacement service with proper process in terms of inventory & finance management, similar to DCE configuration | E46: phase 1: input replacement transaction phase 2: QURE in AYO Kasir | F46: Feature to enable SFP device replacement in AYO Kasir by inputting replacement transaction and having DCE API to check device eligibility & record the replacement. | H46: Ida/Adnan | J46: 45955 | K46: Sprint 8 (prio1)
A47: 40 | B47: AYO Kasir | D47: Offline mode AYO Kasir & data synchronization (to SAP & DCE) ability | E47: Allow AYO Kasir to go with offline mode during network limitation and allow data synchronization when back to online | F47: Feature to enable AYO Kasir to be used in offline mode. Usually applicable for events, where there's no signal | H47: Ida/Adnan | J47: 45955 | K47: Sprint 8 (prio1)
A48: 41 | B48: AYO Kasir | D48: Access Management differentiation for each role | E48: a. SDR to assign TL to selected touchpoint b. TL to login AYO Kasir for few touchpoint using 1 account c. TL to assign runner to selected touchpoint d. Runner to login AYO Kasir for few touchpoint using 1 account | F48: Feature for Team Leader and runner to access several booth/kiosk accounts | H48: Ida/Adnan | J48: 45955 | K48: Sprint 8 (prio1)
A49: 42 | B49: AYO Kasir | D49: AYO Principal - Payment gateway configuration for each customer type in AYO Principal | E49: Feature in AYO Principle to set accurate TID, MID and customer type for payment gatewaty configuration | F49: Feature in AYO Principle to set accurate TID, MID and customer type for payment gatewaty configuration | H49: Ida/Adnan | J49: 45955 | K49: Sprint 8 (prio1)
A50: 43 | B50: AYO Kasir | D50: Add shopping bag as sellable item, with proper configuration in finance & transaction record | E50: a. Enable shopping bag transaction to be recognized by SAP b. Enable stock count of shopping bag in AYO Kasir | F50: Shopping Bag IQOS akan menjadi sellable item dan menjadi berbayar. | H50: Ida/Adnan | J50: 45955 | K50: Sprint 8 (prio1)
A51: 44 | B51: AYO Kasir | D51: Aligning coin reward from new leads/member registration with DSD purchase history | E51: Automatic coin rewards for leads/member registration - SRC IQOS Point | F51: Currently, there is matching process between the amount of leads/member registration with DSD purchase by SRC/SRC IQOS Point. This will result in discrepency and potential for fraud. | H51: Jess/Ragib | J51: 45955 | K51: Sprint 8 (prio1)
A52: 45 | B52: DTE | D52: Streamlining coin approval process to become more efficient | E52: Change Process Flow - Coins Approval | F52: Currently, when user conduct RFT or Transfer to Pojok Bayar the process is very lengthy. Through this initiative, we propose a way on how to ensure this process can be conducted in more efficient manner. Approval from related Departments have already been secured. | H52: Hanif/Jess | J52: 45955 | K52: Sprint 8 (prio1) | L52: 1
A53: 46 | B53: PBI | D53: FMCG performance | E53: Add multiple SKU selection PNM in KSI panamas | F53: Add multiple SKU selection PNM in KSI panamas | H53: Nika | J53: 45955 | K53: Sprint 8 (prio1) | L53: 1
A54: 47 | B54: AYO Kasir | D54: Delimit AYO Kasir Stock at SRC IQOS Point to enable higher stock input | E54: Delimit AYO Kasir Stock - SFP | F54: SRC IQOS Point have limitation in adding product due to stock number restriction. This limitation needs to be removed. | H54: Jess/Ragib | J54: 45955 | K54: Sprint 8 (prio1)
A55: 48 | B55: AYO Kasir | D55: Provide "Order Cart" / "Order Draft" Feature before continue to payment | E55: Draft order and reload after doing other activities | F55: Memungkinkan Frontliners untuk menyimpan dulu draft order (seperti cart di e-commerce) sebelum melanjutkan ke payment/complete transaksi, sering digunakan pada saat traffic lagi ramai, >1 konsumen yang perlu dilayani dan diantara mereka masih mungkin untuk merubah item pembelanjaan | H55: Ida/Adnan | J55: 45955 | K55: Sprint 8 (prio2)
A56: 49 | B56: AYO Kasir | D56: Separate product stock for each inventory type (similar to DCE) | E56: Stock categories - sellable & non-sellable - Guided Trial - Replacement - Display Stock - Trade in | F56: Replicate DCE (CEGID & CeApp), dimana stock untuk product sellable dan non-sellable (product demo stock, display, broken device from replacement, trade in) tidak tercampur menjadi satu, memastikan proses disposal & return ke WH termasuk financial record nya bisa tepat & akurat | H56: Ida/Adnan | J56: 45955 | K56: Sprint 8 (prio2)
A57: 50 | B57: DTE | D57: Add Visual Overlay Guide | E57: Visual Overlay Guides for In-App Camera | F57: Currently, there are no guidelines for users taking photos, which may result in pictures being taken under various conditions, not follow to the specified guidance. To improve the quality and reliability of photo submissions during DTE missions in the AYO Toko mobile app, we are introducing key enhancements that address both user experience and submission integrity. Visual Overlay Guides for In-App Camera Users often struggle to align their photos with brand-specific display requirements (e.g., Coca-Cola planogram, Aqua Danone layout, cigarette display standards). This leads to frequent submission errors, rework, and delays in mission validation. To address this, we will implement visual overlay guides directly on the in-app camera. These semi-transparent templates will help users align their camera shots with the expected visual standards, reducing human error and ensuring compliance with planogram expectations. This feature enhances clarity and guidance during submission, resulting in higher-quality, brand-compliant data capture. | H57: Hanif/Jess | J57: 45955 | K57: Sprint 8 (prio2) | L57: 5
A58: 51 | B58: DTE | D58: To understand user behaviour and provide analytics in DTE platform in AYO Toko | E58: GA AYO Toko Tracking | F58: Implement Google Analytics for DTE features in Ayo Toko to understand user behavior. | H58: Hanif/Jess | J58: 45955 | K58: Sprint 8 (prio2) | L58: 3
A59: 52 | B59: DTE | D59: Send reminder to budget owner if it's below a pre-defined threshold to ensure the sustainability of the program | E59: Trade Program Budget Reminder | F59: Send reminder to budget owner if it's below a pre-defined threshold. Reminder will be sent regularly until certain actions are taken (program expired, additional budget, manual close/delete) | H59: Hanif/Jess | J59: 45955 | K59: Sprint 8 (prio2) | L59: 6
A60: 53 | B60: DTE | C60: Principal, CITA | D60: DTE CITA Missions | E60: Reactivate inactive CITA users and increase the pool size of active CITA users | F60: Introduce Missions on CITA | G60: Michael | K60: Sprint 9 | L60: 4
A61: 54 | B61: DTE | D61: DTE Avatar Entry Point | E61: New entry point for Mission Performance and Mission Guidance video | F61: New entry point for Mission Performance and Mission Guidance video | H61: Hanif/Jess | J61: 45955 | K61: Sprint 8 (prio2) | L61: 2
A62: 55 | B62: DTE | D62: Recaptured Image Detection using Moire Pattern | E62: Detect and flag Moiré patterns in submitted images to identify potential manipulation and prevent fraudulent execution verification. | F62: Detect and flag Moiré patterns in submitted images to identify potential manipulation and prevent fraudulent execution verification. | H62: Ahmad/Jeffry | J62: 45955 | K62: Sprint 8 (prio2) | L62: Deprio | O62: Sprint 9
A63: 56 | B63: AMO Plus | D63: AYO Mitra Plus Hybrid Mode | E63: AYO Mitra Plus Hybrid Mode | F63: AMO Existing bisa digunakan dengan AYO Mitra yang baru | H63: Sri P | J63: 45955 | K63: Sprint 8 (prio2) | L63: 1
A64: 57 | B64: AYO Mitra --> from AYO Principle | D64: Cluster mapping | E64: Capability AYO Mitra Plus untuk export dan import hasil clutering agar memudahkan proses revisi cluster. (akan dihandle dari principal dan internal HMS bisa suggest cluster via principal) Untuk new customer akan ikut ditarik datanya dan ada flagging "new" (tersedia di mid aug) Jika PIC melakukan update Skenario : jika zone melakukan update panel di CT, maka data panel yang baru akan ikut ditarik | F64: Capability AYO Mitra Plus untuk export dan import hasil clutering agar memudahkan proses revisi cluster. Untuk new customer akan ikut ditarik datanya dan ada flagging "new". Skenario : jika zone melakukan update panel di CT, maka data panel yang baru akan ikut ditarik | H64: Sri P | J64: 45955 | K64: Sprint 8 (prio2) | L64: 2
A65: 58 | B65: AYO Mitra --> from AYO Principle | D65: Cluster mapping | E65: - Jika ada update panel di CT, maka panel baru tersebut akan secara otomatis terassign ke PG di AYO Mitra. '- Panel baru akan diassignkan ke PG terdekat. Hasil clustering bisa dilihat CT (misal di Retailer Mapping ada PG ID nya), sehingga bisa dijadikan bahan review | F65: - Jika ada update panel CITA di CT, maka panel baru tersebut akan secara otomatis terassign ke PG di AYO Mitra. - panel baru akan diassignkan ke PG terdekat. Hasil clustering bisa dilihat CT (misal di Retailer Mapping ada PG ID nya), sehingga bisa dijadikan bahan review | H65: Sri P | J65: 45955 | K65: Sprint 8 (prio2) | L65: 3
A66: 59 | B66: Ayo Qoncierge Coach | D66: Test Advisory Revamp | E66: Create website builder for Taste Advisory Page | F66: Business can set up for catalog matrix & page design for Taste Advisory | G66: Wildan & Michel | H66: Mustika Nagari | K66: Sprint 8 | L66: 1
A67: 60 | B67: AYO Principal | D67: Duplication Number in Retailer Mapping | E67: Currently there are duplicated phone number between CT and iSMS | F67: to avoid possible bugs happening we need to ensure that CT has a unique phone number between each retailer. Still on discussion to fix this | G67: Ariph | H67: Ariph | K67: Sprint 9 | L67: Deprio
A68: 61 | B68: AYO Principal | D68: Validation Retailer Mapping | E68: If user principal updating a duplicated value for phone number, it will rejected by the system. | F68: if user uploading duplicated phone number, then it will be rejected for that specific row, and shown to the user. | G68: Ariph | H68: Ariph | K68: Sprint 9 | L68: Deprio | O68: Sprint 9
A69: 62 | B69: CITA | C69: Principal, OSEM, TSM, My Hero, AMO | D69: [CITA Loyalty] dormant users keep increasing despite the rapid increase of DAU from dijamin1klik. | E69: retain users and increase regular purchasers through loyalty program, learning from AYO DTE | G69: Jere, Michael | H69: CI/Commstrat | K69: Sprint 8 | L69: 3 | N69: v
A70: 63 | B70: CITA | C70: Principal, OSEM, TSM | D70: [CITA Coachmark] no guidance exists on CITA to help users navigate important activities by themselves | E70: user can learn to operate the platform by themselves and reduce dependency to FF | F70: enable coachmark for every user, at the right time, tailored for each user type-- dormant, regular, etc. In the context of D1K, the coachmark is adaptive. By adaptivemeans the coachmark is tailored based on FF’s stock recommendations.​ | G70: Jere | H70: CI | K70: Sprint 8 | L70: 2 | N70: v
A71: 64 | B71: CITA | C71: Principal, DTE, MyHero | D71: [Instant CN Rewards] Currently, CN Rewards are only applied to Direct Selling activities, and the reward distribution is not immediate—it can only be redeemed during the next visit by the salesman, which typically occurs every two weeks. | E71: Enabling instant reward distribution to digital platform | F71: Instant CN Rewards, we would like to allocate a portion of the coins to CITA, allowing users to redeem digital vouchers or use them to offset the total order value when purchasing through CITA | G71: Jere | H71: Trade Team | K71: Sprint 8 | L71: 1 | N71: v
A72: 65 | B72: CITA | C72: Principal, OSEM, TSM | D72: [CITA PN Integration to OSEM&TSM] Currently, CITA relies on manual audience selection for sending push notifications, which results in significant administrative effort and static targeting. | E72: To improve efficiency and relevance when sending push notification to users | F72: Push Notification Integration with TSM and OSEM This integration will enable trigger- and condition-based notifications, as well as dynamic audience segmentation. As a result, notifications will reach the right users at the right time, while also reducing manual workload for our admins. | G72: Jere | H72: CI/Deployment | K72: Sprint 8 | L72: 4
A73: 66 | B73: MyAyo Web | C73: AYO Toko | D73: Metahuman for PD Support at SRC | E73: SRC Customer have an access for product knowledge, especially for IQOS BONDS | F73: Metahuman support by Global Vendor Synthesia. Consumer can access through QR scanning after registration at SRC as Leads | G73: Wildan | K73: Sprint 8 | L73: 1
A74: 67 | B74: SSR | D74: LAS/LANU Registration for KA (IDM) | E74: Facilitate LAS LANU for self registration & Device Link | F74: Website that LAS/LANU can access for registration process & device link | G74: Wildan | H74: Ivan Orlando | K74: Sprint 8 | L74: 1
A75: 68 | B75: Principal SFP | C75: AYO Toko, My Hero, iSMS, SAP | D75: Customer registration for IQOS Partner (Phase I) | E75: Create seamless system integration for IQOS Partner Registration | F75: Create seamless system integration for IQOS Partner Registration, & initial support invoice automatitation | G75: Wildan | H75: Mustika Nagari | K75: Sprint 8 | L75: 1
A76: 69 | B76: Ayo Qoncierge Coach | C76: Tania | D76: Tania for SFP | E76: Interactive AI to support frontliner incentive | F76: Tanai will giving information & recommendation of the frontliner achievement status | G76: Wildan | K76: Sprint 8 | L76: 2
A77: 70 | B77: AYO Principal | D77: CMS For Tania | E77: To create CMS for Tania in AYO Principal | F77: for this phase it will be simple editor and add edit delete content in AYO Principal. | G77: Ariph | H77: Arum | K77: Sprint 8 | L77: 13 | M77: Sprint7 | N77: v
A78: 71 | B78: AYO PRINCIPAL | D78: Database Push Notification | E78: Improve logging database for push notification CITA on ayo_master | F78: Enhancement include: 1) Adding pnrl_id column 2) Remove execution_count 3) Make every PN execution recorded as 1 row (not updated). https://wiki.app.pconnect.biz/x/t4BzTg https://jira.app.pconnect.biz/browse/CDE-27312 | G78: Livi / Jere | H78: Livi | J78: 45955 | K78: Sprint 8 | L78: 10
A79: 72 | B79: AYO PRINCIPAL | D79: Create New Service for SMS Request to Infobip | E79: Prevent SMS request queueing system in the future to be challenging | F79: Create new service dedicated for SMS request to Infobip https://jira.app.pconnect.biz/browse/CDE-27686 | G79: Livi | H79: Diana/Zhafran/Livi | J79: 45955 | K79: Sprint 8 | L79: 8
A80: 73 | B80: AYO PRINCIPAL | D80: MITA x OSEM, New Audience Paneling for MITA | E80: Improve current way to generate panel MITA to be more seamless and flexible. Currently relying heavily on pipeline & logic from IT DATA. | F80: Enhancement include: 1) Adding new golden records related to MITA 2) Create new S3 AYO for Wiz to consume the panel 3) Create new MITA Config menu on AYO PRINCIPAL (select audience osem, retrieve phone number, export to S3 AYO, split by panel category, config logic for salesman last visit, etc) https://wiki.app.pconnect.biz/x/0AK0Sg | G80: Livi / Zhafran | H80: Shinta/Livi | J80: 45955 | K80: Sprint 9 | L80: 9
A81: 74 | B81: My Hero Backend - CDM Payment Gateway | D81: Cater Business Plan to Go with TA for PANAMAS PRE-ORDER Cash Collection | E81: Exclude Receipt PANAMAS PRE-ORDER Data Ingestion to Payment Gateway Flow | F81: Exclude booking_code "TARE...." from receipt data ingestion payment gateway (my hero ipad setoran page, my hero backend CDM menu, including receipt report, settlement report, disbursement report, etc) | G81: Livi / Melissa Tio | H81: Rangga | J81: 45955 | K81: Sprint 8 | L81: 2 | N81: Sprint 9
A82: 75 | B82: My Hero Backend - TA Cash Collection | D82: Create New Menu for TA Cash Collection | E82: Facilitate CPO / HO to identify how much amount of delivered order is collected by cash vs QRIS | F82: There will be a new menu on MHBE dedicated for TA Cash Collection, contain table with columns: Area, Salespoint, TA Code, TA Name, Total SO, Delivery Date, Total Delivered Amount, Uang Tunai, E-Payment [CDE-27276] TA Delivery Report | G82: Livi / Melissa Tio | H82: Bu Vivi (Commercial) / Mas Pram | J82: 45955 | K82: Sprint 8 | L82: 3 | N82: Sprint 9
A83: 76 | B83: My Hero Backend - TA Cash Collection | D83: Create New Menu for TA Delivery Status Report | E83: Facilitate CPO / HO to identify how many orders has been delivered or cancelled from TA (TMS app) | F83: There will be a new menu on MHBE dedicated for TA Cash Collection, contain table with columns: TA Journey Code, TA Name, SO Order Date, Delivery Date, Status, Invoice Amount, Invoice Code, Invoice Legal Number, Territory Code, Customer Code, Customer Name, FF Name, Entity [CDE-27347] Delivery Status (Report) | G83: Livi / Melissa Tio | H83: Bu Vivi (Commercial) / Mas Pram | J83: 45955 | K83: Sprint 8 | L83: 19
A84: 77 | B84: AMO Plus | D84: Sometimes PG completing delivery more than 6 p.m. when admin has gone home so they cannot help PG to carry over incomplete order to next day | E84: To avoid incomplete order to auto-cancelled when admin has finished their shift | F84: Carry over pengiriman CITA yang belum bisa diantarkan ke besok hari dari AMO PG | G84: Jimmy H./ M. Yusron | K84: Sprint 8 | L84: 4
A85: 78 | B85: AMO Existing & Plus | D85: Needed to help prepare the product D-1 prior to delivery | E85: To effectively categorized packaged product by the PG name | F85: Invoice pada transaksi selain memunculkan nama PG, juga no HP PG | G85: Jimmy H./ M. Yusron | K85: Sprint 8 | L85: 10
A86: 79 | B86: AMO Plus | D86: To avoid calculation error when the visit is retrieved via PBI (or any other reporting mechanism) | E86: To avoid calculation error when the visit is retrieved via PBI (or any other reporting mechanism) | F86: Update visit status when Selesaikan Pesanan (currently in DWH visit status is 0, even the delivery has been completed) | G86: Jimmy H./ M. Yusron | K86: Sprint 8 | L86: 11
A87: 80 | B87: AMO Plus | D87: Adanya kemungkinan duplikasi atau double counting pada Data PG Performance Tracker | E87: Fixing the calculation of Data PG Performance Tracker | F87: Calculation PG Performance Tracker yang dikirimkan melalui reverse ETL diharapkan bisa disummary tiap periode performance sehingga perlu enhancement juga dari sisi AMO | G87: Jimmy H./ M. Yusron | H87: Jimmy H. | K87: Sprint 8 | L87: 9
A88: 81 | B88: AMO Existing & AMO Plus | D88: The logic can cause processing inefficiency and high server load in a long run | E88: More effective process (if still needed) | F88: Change the logic from actively query-ing the data from data order table and whitelisting table in database upon completion of delivery order to using flagging on file download. | G88: Jimmy H./ M. Yusron | K88: Sprint 8 | L88: 7
A89: 82 | B89: AMO Plus | D89: To monitor PG activity and calculate a more accurate SLA | E89: To monitor PG activity and calculate a more accurate SLA | F89: Upon completion of CITA Delivery Order it is required to record the Longitude and Latitude | G89: Jimmy H./ M. Yusron | K89: Sprint 8 | L89: 6
A90: 83 | B90: AYO Toko | D90: Home Page Revamp | E90: More engaging content in homepage will be led to more active user | F90: -Publish new configuration at anytime without deployment -Section menu can be arranged in principal -Tile menu can be arrange & hide from principal - [OK TO SWAP] | G90: M. Yusron / Gerry | J90: 45955 | K90: Sprint 8 | L90: 5
A91: 84 | B91: AYO Toko | D91: Belanja Page Revamp | E91: Tidier and attaractive Belanja poge will attract to more good experience in Belanja | F91: -Collect all history order in one page -Merged cart page and checkout page into 1 pasge only - [OK TO SWAP] | G91: M. Yusron / Gerry | J91: 45955 | K91: Sprint 8 | L91: 6
A92: 85 | B92: AYO Toko | D92: Non Login experience | E92: Dummy homepage with B2B & DTE menu end to end | F92: -Create real order that will be proceed when retailer log-in/registered -Answer real DTE mission with all type of question detail - [OK TO SWAP] | G92: M. Yusron / Gerry | J92: 45955 | K92: Sprint 8 | L92: 1
A93: 86 | B93: AYO Toko | D93: Pinang Raya performa - Bank Raya -Pojok Modal | E93: SRC Partnership X Bank Raya | F93: -connection to Pojok Modal AYO Toko with pinang performan bank raya -Configure panel in principal -user can apply for a loan at Bank Raya - [Higher prio. due to biz request] | G93: M. Yusron / Gerry | H93: Dhea Rizka | J93: 45955 | K93: Sprint 8 | L93: 4
A94: 87 | B94: AYO Toko | D94: Shopping Bag - AYO Toko SFP | E94: The sale of SFP shopping bags provides PMI with additional income categorized as other revenue | F94: -Create a new 'Others' category in AYO Toko -Partners can purchase SFP shopping bags directly through the platform | G94: M. Yusron / Gerry | H94: Reza Aryo | J94: 45955 | K94: Sprint 8 | L94: 3 | P94: Business requirement TBD
A95: 88 | B95: AYO Toko | D95: Use Metahuman in AYO Toko for lead generation and to enhance user engagement | E95: Display a QR code in AYO Toko to support lead generation and strengthen SRC’s business operations by enabling seamless and accurate knowledge transfer | F95: -Display a QR code and link on Ayo Toko to show the Metahuman video experience -Enable video metahuman from both retailer and consumer devices to ensure broader engagement - [Higher prio. due to biz request] | G95: M. Yusron / Gerry | H95: Wildan | J95: 45955 | K95: Sprint 8 | L95: 2
B96: AYO Toko | D96: PN re-architecturing to improve send time and reduce delay | E96: To support DTE team in notifying users for ongoing and upcoming missions | F96: - Implement new PN structure for DTE and pop up PN sending | G96: M. Yusron / Gerry | H96: Mike | J96: 45955 | K96: Sprint 8
B97: AYO Toko | D97: SFP to update SKU price on cart | E97: Bug recently found where during price update, items added to cart will not reflect the new price post update | F97: - Ensure when SKU price is updated, SKU in cart to reflect new price - [High prio due to price-related issue] | G97: M. Yusron / Gerry | J97: 45955 | K97: Sprint 8
B98: AYO Toko | D98: Available Credit Limit syncing | E98: Currently ACL has 2 different syncing source at 2 different time schedule, which confuses partner and at the same time resulted in CL over limit and into the negative | F98: - To stop receiving CL calculations from SAP - AYO Toko to calculate CL independently based on partner payment | G98: M. Yusron / Gerry | J98: 45955 | K98: Sprint 8
B99: AYO Toko | D99: Bug: CDE-27425 Payment is overdue but can still order with cash | E99: When partner has an outstanding invoice, partner is still able to place order via cash | F99: - To prevent partner from placing order with any payment method when there is ongoing outstanding invoice - [High prio as it is an order-related loophole] | G99: M. Yusron / Gerry | J99: Adhoc | K99: Sprint 8 | L99: 7
B100: AYO Toko | D100: Bug: CDE-27426 Max order review - Reviewer can't open detail order if CL not available | E100: If whitelisted partner place an order when CL is not available, reviewer is blocked from access order details entirely | F100: - Allow reviewer to open order details (despite not being able to approve order) - Allow reviewer to edit and adjust order quantity based on available partner CL | G100: M. Yusron / Gerry | J100: 45955 | K100: Sprint 8 | L100: 7
...

Sheet MASTER SPRINT9
A1: Sprint List
A2: Objective : File ini digunakan oleh CI dan Deployment untuk mentracking List Sprint sepanjang tahun 2025
A3: User yang memiliki akses untuk edit adalah : Tim Deployment & CI
A4: Di isi yang warna biru
B5: New Sprint 9 | D5: Deprio Sprint 8 | F5: Lintas sprint from previous sprint (8) | H5: CI Sprint Proposed | I5: 0 | J5: lintas sprint dan harus masuk | Q5: SPRINT 9
C6: CI Team | G6: CI Team | L6: assume 1 sprint = 10 mandays | Q6: 45919 | R6: 45930 | S6: 45939 | T6: 45944 | U6: 45953 | V6: 45957 | W6: 45958
A7: No | B7: Platform (Aplikasi) | C7: Dependency | D7: Background | E7: Objective | F7: Description | G7: Product Manager | H7: Requestor | I7: Chanel | J7: Expected Deployed | K7: Sprint | L7: Rank Prio | M7: Re-Prio CI & Depl | N7: Sprint Carry Over | O7: Status | P7: Update 0 9/20 | Q7: Update 1 | R7: Update 2 | S7: Update 3 | T7: Update 4 | U7: Update 5 | V7: Update 6 | W7: Update 7 | X7: PRD | Y7: JIRA | Z7: Mandays | AA7: Remark
A8: 1 | B8: AMO Existing | D8: At this moment, there is no reference document available to confirm that the delivery of the CITA order via PG has indeed occurred, nor that it was delivered to the correct store. | E8: To provide a reliable mechanism for confirming and documenting the successful delivery of orders, ensuring accuracy, traceability, and accountability in the delivery process | F8: Proof of Delivery Feature: Unique code/ Taking photo | H8: Nastasya | J8: 45962 | K8: Sprint 9 | L8: 2 | M8: 7
A9: =A8+1 -> 2 | B9: AMO Existing | D9: Currently, the barcode scanning process does not yield any tangible benefits in terms of productivity for PG. Despite completing the scan, PGs still manually enter the relevant store visit information. | E9: Enhance operational efficiency by reducing manual input tasks for PG. Improve data accuracy by minimizing human error in store information entry. Accelerate visit preparation and allow PG to focus more on execution rather than administrative tasks. Ensure consistency in store data across all visits and reporting systems. | F9: This feature enables PGs to instantly retrieve store information upon scanning a barcode, eliminating the need for manual data entry. Once the barcode is scanned, relevant store details are automatically populated in the system interface. | H9: Nastasya | J9: 45962 | K9: Sprint 9 | L9: 1 | M9: 3
A10: =A9+1 -> 3 | B10: AYO KASIR | D10: Frontliners have inconsistent understanding of the complete product knowledge, talking points, and current programs or promotions. There are also limitations in accessing all supporting materials." | E10: Provide access for all frontliners to read and learn every working outlines, cue card and important initiatives | F10: Dedicated menu in AYO Kasir for WO/Program/Product Info/etc. library. Updateable through AYO Principle. | H10: IDA/Adnan | I10: SFP | J10: 45962 | K10: Sprint 10 | L10: 2 | M10: deprio
A11: =A10+1 -> 4 | B11: AYO KASIR | D11: Saat ini QRIS Dinamis BRI masih belum terintegrasi dengan AYO Kasir, sehingga transaksi melalui EDC BRI masih dilakukan terpisah dengan penginputan SO di AYO Kasir. Hal ini menyebabkan diperlukannya manual input approval code di AYO Kasir oleh frontliner dimana potensi human error sangat mungkin terjadi. Selain itu, missing input order juga dapat terjadi dikarenakan tidak adanya integrasi. | E11: 1. Mempermudah frontliner untuk melakukan transaksi dimana tidak perlu lagi penginputan approval code secara manual 2. Proses back-end reconciliation yang lebih efisien di tim OTC dikarenakan order tidak akan ter-create tanpa adanya payment 3. Meningkatkan jumlah transaksi menggunakan QRIS Dinamis BRI, dimana BRI menawarkan cashback rate yang tinggi untuk transaksi QRIS | F11: QRIS Dinamis BRI terintegrasi dengan AYO Kasir, sehingga order tidak akan ter-create tanpa adanya payment | H11: Linggajaya, Melissa/Ida | K11: Sprint 9 | M11: 6 | S11: In progress finalization
A12: =A11+1 -> 5 | B12: AYO Toko | D12: 1. Beberapa foto Toko (store outlook) di AYO Profile yang kurang menggambarkan situasi sebenarnya 2. Belum ada guide / standar yang tepat untuk memandu pemiliki Toko dalam pengisian Foto Toko di AYO Profile | E12: Untuk memvalidasi SRC Quality dan menggambarkan store outlook | F12: 1. Fitur image recognition 2. Fitur Video 3. Guide | H12: Dody | J12: Q1 2026 | K12: Sprint 9 | L12: 2 | M12: 2 | O12: Prio New Feature
A13: =A12+1 -> 6 | B13: AYO Toko | D13: 1. Belum ada pembeda antara SRC Quality dan SRC Regular didalam aplikasi AYO | E13: 1. Toko mengetahui statusnya sebagai SRC Quality 2. Toko mengetahui progress untuk menjadi SRC Quality | F13: SRC Quality Badge di AYO Toko | H13: Dody | J13: Q1 2026 | K13: Sprint 10 | M13: 4 | O13: Prio New Feature
A14: =A13+1 -> 7 | B14: AYO Toko | D14: 1. Belum ada menu untuk edukasi SFP di aplikasi AYO TOKO | E14: 1. Edukasi Toko SRC mengenai produk dan program SFP | F14: Edukasi SFP pada menu bebas Asap | H14: Kemal | J14: 46023 | K14: Sprint 9 | L14: 1 | M14: 1 | O14: Prio New Feature | AA14: injecting video/tutorial edukasi SFP di menu bebas asap
A15: =A14+1 -> 8 | B15: AYO Toko | D15: Support Perfect Territory for AYO User, so AYO user can also benefit from D1K | E15: enable D1K for AYO User | F15: D1K in AYO | H15: Hans | I15: CC | J15: Q1 2026 | K15: Sprint 1-2026 | M15: 3 | O15: Prio New Feature
A16: =A15+1 -> 9 | B16: BOT - AYO KASIR | D16: 1. Warranty rule set for P1 devices are based on purchase date and device type of customer : - ILUMA 4.0 : 12 Months after purchase date - ILUMA 4.1 : 12 Month + 12 Months if it is linked within 30 days from purchase date If the purchase date (based on proof of purchase) is not available the warranty eligibility will be refering to production date, the eligibility is : 12 months from production date + 3 months 2. BOT is currently recording new member device link date only, NOT recording the purchase date. 3. The impact is customer will not receive the eligible warranty period and might potentially generate complaints as the warranty periode have been expired during the day of the purchase. | E16: 1. Provide the correct warranty eligibility period for customer based on purchase date. 2. Minimize potential complaint due to the warranty eligibility period <12 months after purchase date. | F16: Enhanching current BOT capabilities for not only to link the device but to also capture the purchase date to DCE 2 / DCX | H16: IDA/Ade, Artha - CSC ID | I16: SFP | J16: September 2025 (as customer care has received complaints for warranty period eligibility) | K16: Sprint 9 | L16: 1 | M16: 8
A17: =A16+1 -> 10 | B17: CITA | D17: No validation once outlet login or made transaction | E17: OTP only applies once retailer receives coin/ redeem coin | F17: OTP for Coin Redemption | H17: Nastasya | K17: Sprint 9 | L17: 1 | M17: 5 | O17: Prio New Feature
A18: =A17+1 -> 11 | B18: CITA | D18: No avenue for retailer complain the order | E18: Complain button only appear at 3-5 days after order status done | F18: Complain button | H18: Nastasya | K18: Sprint 9 | L18: 2 | M18: 6 | O18: Prio New Feature
A19: =A18+1 -> 12 | B19: CITA | D19: Saat ini pemberian reward kepada outlet bersifat non-instant sehingga mengurangi attractiveness dari reward tersebut. Di sisi lain, untuk saat ini reward hanya applicable pada transaksi DSD, belum mengakomodir pembelian melalui RTM Digital. | E19: Memberikan rewards kepada outlet secara instant dan memberikan fleksibilitas penggunaan rewards, baik melalui DSD maupun RTM Digital | F19: Receive instant reward (Scan + Push notif) ability | H19: Nastasya | K19: Sprint 9 | L19: 4 | M19: 7 | O19: Prio New Feature
A20: =A19+1 -> 13 | B20: CITA | D20: some customer retailers shown unusual sales that exceed normal transaction value | F20: set the limit at IDR 30 mio per day for CITA | H20: Nastasya | K20: Sprint 9 | L20: 3 | M20: 1 | O20: Others
A21: =A20+1 -> 14 | B21: DTE | D21: Streamlining coin approval process to become more efficient | E21: Change Process Flow - Coins Approval | F21: Currently, when user conduct RFT or Transfer to Pojok Bayar the process is very lengthy. Through this initiative, we propose a way on how to ensure this process can be conducted in more efficient manner. Approval from related Departments have already been secured. | H21: Kemal | K21: Sprint 9 | L21: 1 | M21: pls double check with no.44 | O21: Prio New Feature | AA21: lanjutan sprint 8
A22: =A21+1 -> 15 | B22: DTE | D22: With CITA enable of loyalty coin, we need to consolidate both coin in AYO & CITA | E22: Consolidate Coin in AYO & CITA | F22: One currency of coin AYO & CITA | H22: Indah & Dody | K22: Sprint 10 | M22: 4 | O22: Prio New Feature | AA22: similar with sprint 8 proposed & deprio to sprint 9
A23: =A22+1 -> 16 | B23: DTE | D23: Saat ini pemberian reward kepada outlet bersifat non-instant sehingga mengurangi attractiveness dari reward tersebut. Di sisi lain, untuk saat ini reward hanya applicable pada transaksi DSD, belum mengakomodir pembelian melalui RTM Digital. | E23: Memberikan rewards kepada outlet secara instant dan memberikan fleksibilitas penggunaan rewards, baik melalui DSD maupun RTM Digital | F23: Receive instant reward (Scan + Push notif) ability | H23: Indah & Dody | K23: Sprint 10 | M23: 3 | O23: Prio New Feature
A24: =A23+1 -> 17 | B24: MyHero FF | D24: 1. SLA time untuk melakukan taking Order saat ff visit 2. Banyak nya page order dalam MyHero (pre order, DSD, D1K) 3. Informasi dalam page order terlalu scattered | E24: 1. Menyatukan 1 page order untuk semua product 2. mengurangi jumlah step yg dibutuhkan dalam taking order 3. menampilkan informasi yg relevant saat taking order 4. Mengurangi waktu yg dibutuhkan FF untuk taking order | F24: Create order page untuk seluruh product: Phase 1: Change UI with more compact UI Phase 2: 1. Unify DSD for all category 2. Select Order Method in 1 page (DSD, D1K, Preorder) | H24: Hans | I24: Multicategory | J24: Phase 1: Nov 25 Phase 2: Q1 26 | K24: Sprint 9 | L24: 3 | M24: 3 | O24: Others
A25: =A24+1 -> 18 | B25: MyHero FF | D25: 1. Multiple invoice untuk pembelian DSD 2. Setiap invoice perlu di tanda tangan | E25: 1. Mempermudah retailer dan FF dalam proses transaksi | F25: Create digital sign untuk semua invoice di MyHero | H25: Hans | I25: Multicategory | J25: Q1 2026 | K25: Sprint 10 | O25: Prio New Feature
A26: =A25+1 -> 19 | B26: MyHero FF | D26: 1. Jumlah SKU saat stock count sudah mencapai ratusan 2. Perbedaan list brand focus setiap area | E26: 1. Mempermudah proses stock count 2. Mempercepat proses stock count | F26: Set up stock count via AYO Principal untuk kebutuhan brand focus dan frequency daari Stock Count | H26: Hans | I26: CC | J26: 45962 | K26: Sprint 9 | L26: 2 | M26: 2 | O26: Others
A27: =A26+1 -> 20 | B27: MyHero FF | D27: 1. SLA dari field force saat melakukan proses pembayaran di mesin CDM 2. Banyak Retail yg sudah menggunakan pembayaran QRIS | E27: 1. Mempercepat proses pembayaran di mesin CDM 2. Mempercepat proses pembayaran dari retail ke field force | F27: Payment Gateway pada My Hero Phase 1: mesin CDM Phase 2: QRIS Retail | H27: Hans | I27: Multicategory | J27: Phase 1: Q1 2026 Phase 2: Q2 2026 | K27: Sprint 10 | O27: Prio New Feature
A28: =A27+1 -> 21 | B28: MyHero FF | D28: 1. Banyak callcard yg obsolete 2. Callcard yg kebutuhan one time | E28: 1. Mengurangi jumlah agreement yg muncul pada MyHero | F28: Simplifikasi dari Agreement | H28: Hans | I28: CC | J28: 45962 | K28: Sprint 9 | L28: 5 | M28: 5 | O28: Prio New Feature
A29: =A28+1 -> 22 | B29: MyHero FF | D29: Saat ini pemberian reward kepada outlet bersifat non-instant sehingga mengurangi attractiveness dari reward tersebut. Di sisi lain, untuk saat ini reward hanya applicable pada transaksi DSD, belum mengakomodir pembelian melalui RTM Digital. | E29: Memberikan rewards kepada outlet secara instant dan memberikan fleksibilitas penggunaan rewards, baik melalui DSD maupun RTM Digital | F29: Phase 1 - Rewards dapat diinject melalui CITA sehingga existing CITA user dapat menggunakan CITA dan menikmati eligible rewards berdasarkan Trade Program yang telah diikuti. Phase 2 - CITA dan AYO Toko dapat membaca QR Code generated dari MY Hero sehingga memudahkan adopsi penerimaan reward (tanpa perlu inject). Sebagai tambahan, jika outlet merupakan user keduanya, rewards (coin) bersifat interchangeable (dapat digunakan dikeduanya) | H29: Indah | K29: Sprint 9 | L29: 1 | M29: 1 | O29: Prio New Feature | AA29: makesure gak double dengan CITA put in sprint 8
A30: =A29+1 -> 23 | B30: MyHero FF | D30: Belum ada akumulasi penjualan between CC, FMCG dan Cricket: - LPU HMS,Panamas, SCL dan SRCIS tetap ada - Ada LPU gabungan yang dibutuhkan FF untuk setoran keseluruhan V1,BV1, FMCG dan Cricket - Ada kebutuhan list preview gabungan V1,BV1,FMCG dan Cricket | E30: Belum ada akumulasi penjualan between CC, FMCG dan Cricket: - LPU HMS,Panamas, SCL dan SRCIS tetap ada - Ada LPU gabungan yang dibutuhkan FF untuk setoran keseluruhan V1,BV1, FMCG dan Cricket - Ada kebutuhan list preview gabungan V1,BV1,FMCG dan Cricket | F30: - terdapat fitur pilihan print total LPU Gabungan - terdapat fitur print total barang gabungan per toko | H30: Hans | J30: 45992 | K30: Sprint 9 | L30: 4 | M30: 4 | O30: Prio New Feature
A31: =A30+1 -> 24 | B31: MyHero Backend | D31: CPO masih harus upload 2 file untuk initial load: 1. MyHero Back end: FMCG & Cricket 2. ISMS: CC & SFP | E31: Menyatukan file upload dalam 1 system | F31: Create menu baru dalam MyHero Backend untuk capability upload 1 file dalam MyHero Backend | H31: Hans | K31: Sprint 9 | L31: 6 | M31: 7 | O31: Prio New Feature
A32: =A31+1 -> 25 | B32: AYO Mitra | D32: Saat ini tidak ada page tersedia di AYO Mitra untuk bisa lihat potongan belanja yang dipotong (Instant reward) | E32: View WS for redemption instant reward | F32: Page di AYO Mitra untuk bisa lihat list toko dan value yang sudah redemption instant reward | H32: Nastasya | K32: Sprint 9 | L32: 1 | M32: 1 | O32: Prio New Feature
A33: =A32+1 -> 26 | B33: AMO Existing | D33: Untuk kebutuhan instant reward melalui CITA, dibutuhkan keterangan jumlah potongan belanja dalam invoice yang diterima oleh TOKO | F33: Improvement invoice CITA melalui AMO untuk potongan belanja (Instant reward) | H33: Nastasya | J33: 45962 | K33: Sprint 9 | L33: 3 | M33: 8 | O33: Prio New Feature
A34: =A33+1 -> 27 | B34: AMO Existing | D34: Saat ini jika ada error, belum ada informasi trouble shooting dan pembeda root cause of issue. | E34: Memberikan informasi yang cukup ke user (PG) agar lebih mudah follow up berikutnya | F34: Dibuatkan error message/wording yang unik dan spesifik include trouble shooting. | H34: Dila | J34: 45962 | K34: Sprint 9 | L34: 6 | M34: 6 | O34: Prio New Feature
A35: =A34+1 -> 28 | B35: AYO Mitra | D35: Belum ada T&C di AYO Mitra | F35: rewrite T&C for PG employment purpose | H35: Nastasya | K35: Sprint 9 | O35: Compliance Issue | AA35: New insert
A36: =A35+1 -> 29 | B36: AMO | D36: Belum ada T&C di AMO | F36: rewrite T&C for PG employment purpose | H36: Nastasya | K36: Sprint 9 | L36: 7 | O36: Compliance Issue | AA36: New insert
A37: =A36+1 -> 30 | B37: My Hero Back End dan My Hero | D37: Variasi produk semakin banyak dan range harga yang sangat beragam. Membutuhkan banyak waktu menjelaskan dan menawarkan masing-masing product | E37: Mempermudah proses menawarkan ke toko dan proses penjualan dengan pilihan product bundling | F37: - My Hero Back End - bisa mendaftarkan product bundling per area per type, berupa paket berisi beberapa product dengan qty tertentu. User dapat mengatur jadwal aktif bundling - My Hero - FF dapat melihat product bunlding beserta detailnya, dan dapat melakukan penjualan dengan memilih product bundling tersebut otomatis ter breakdown ke product-product komponennya | H37: Adityo Gunawan | K37: Sprint 9 | AA37: New insert
A38: =A37+1 -> 31 | B38: AYO Kasir | D38: Currently, every time inbound / outbound document is edited or canceled in SAP by warehouse team, AYO Kasir users don't have the ability to delete the document. The document needs to be deleted from backend by IT (i.e. raise CHT). | E38: Enable AYO Kasir admin to perform rejection/deletion to any wrong stock movement request | F38: Ability to reject inbound & outbound docs from WH in AYO Kasir | H38: Ida/Adnan | J38: Sprint 8 | K38: Sprint 9 | L38: 11 | M38: 9 | S38: Sprint 8 Make sure doesn't carry over to Sprint 9 | AA38: New insert by 6 Oct 2025
A39: =A38+1 -> 32 | B39: AYO Kasir | D39: Staff memiliki visibility jumlah stock/inventory di setiap store (termasuk store nya sendiri) untuk semua product. Case: Bila ada SKU tertentu yang OOS di store tersebut, dan konsumen bisa diarahkan untuk mencari SKU tersebut di store lain yang sudah pasti memiliki stock (dengan dibantu pengecekan oleh staff), termasuk bila HMS team memerlukan pengecekan availability SKU tertentu tersedia di store mana saja (secara real time) untuk kemudian bila diperlukan pemerataan/pemindahan stock antar toko | E39: Coach/Staff Visbility on Every Store Inventory Status | F39: Check stock in other stores feature Enable feature for inventory visibility in every store | H39: Ida/Adnan | K39: Sprint 9 | L39: 10 | M39: 10 | S39: Need BRD | AA39: New insert by 6 Oct 2025
A40: =A39+1 -> 33 | B40: AYO Kasir | D40: Enable field forces / internal employees to have single sign on to AYO Kasir using work email | E40: Single Sign On for Field Forces | F40: Enable field forces / internal employees to have single sign on to AYO Kasir using work email | H40: Ida/Adnan | K40: Sprint 9 | L40: 14 | M40: 11 | S40: Need BRD | AA40: New insert by 6 Oct 2025
A41: =A40+1 -> 34 | B41: AYO Toko | D41: Background : Selama periode price increase, jika partner telah menambahkan SKU ke "Cart" di AYO Toko sebelum harga terupdate, maka price tidak akan otomatis terupdate saat order diklik. Akibatnya, harga lama tetap digunakan. Hal ini menyebabkan order stuck di AYO dan tidak dapat diteruskan ke iLogic untuk proses Logistik. Order tersebut harus dicancel secara manual melalui back-end, dan partner perlu melakukan order ulang. Proposal : Melakukan force update terhadap price pada SKU yang sudah masuk ke "Cart". | E41: Minimize Invalid Price (order stuck in iLogic for Partner during price increase period) | F41: Force updated pricing in order cart in period of price update | H41: Ida/Adnan | K41: Sprint 9 | L41: 10 | M41: 13 | AA41: New insert by 6 Oct 2025
A42: =A41+1 -> 35 | B42: AYO Qoncierge Coach | D42: In alignment with management team decision to ensure effectiveness and to follow PMI regulation regarding leads data management | E42: Hide feature leads database & registration, consumer 360, handholding & mission | F42: In alignment with management team decision to ensure effectiveness and to follow PMI regulation regarding leads data management | H42: Ida/Adnan | K42: Sprint 9 | L42: 12 | M42: 1 | AA42: New insert by 6 Oct 2025
A43: =A42+1 -> 36 | B43: AYO Kasir | D43: Provide proper replacement service with proper process in terms of inventory & finance management, similar to DCE configuration | E43: phase 1: input replacement transaction phase 2: QURE in AYO Kasir | F43: Feature to enable SFP device replacement in AYO Kasir by inputting replacement transaction and having DCE API to check device eligibility & record the replacement. | H43: Ida/Adnan | K43: Sprint 9 | L43: 1 | M43: 5 | S43: In progress technical requirement
A44: =A43+1 -> 37 | B44: AYO Kasir | D44: AYO Principal - Payment gateway configuration for each customer type in AYO Principal | E44: Feature in AYO Principle to set accurate TID, MID and customer type for payment gatewaty configuration | F44: Feature in AYO Principle to set accurate TID, MID and customer type for payment gatewaty configuration | H44: Ida/Adnan | K44: Sprint 10 | M44: deprio
A45: =A44+1 -> 38 | B45: AYO Kasir | D45: Aligning coin reward from new leads/member registration with DSD purchase history | E45: Automatic coin rewards for leads/member registration - SRC IQOS Point | F45: Currently, there is matching process between the amount of leads/member registration with DSD purchase by SRC/SRC IQOS Point. This will result in discrepency and potential for fraud. | H45: Jess/Ragib | K45: Sprint 9 | S45: Include in no. 61 | AA45: Please rank between Ida,Jess & Mas Tyo
A46: =A45+1 -> 39 | B46: AYO Kasir | D46: Provide "Order Cart" / "Order Draft" Feature before continue to payment | E46: Draft order and reload after doing other activities | F46: Memungkinkan Frontliners untuk menyimpan dulu draft order (seperti cart di e-commerce) sebelum melanjutkan ke payment/complete transaksi, sering digunakan pada saat traffic lagi ramai, >1 konsumen yang perlu dilayani dan diantara mereka masih mungkin untuk merubah item pembelanjaan | H46: Ida/Adnan | K46: Sprint 10 | M46: deprio
A47: =A46+1 -> 40 | B47: DTE | C47: Principal, CITA | D47: DTE CITA Loyalty | E47: Reactivate inactive CITA users and increase the pool size of active CITA users | F47: Introduce and prepare Instant reward and loyalty in CITA | H47: CI | K47: Sprint 9 | L47: hold | M47: 2
A48: =A47+1 -> 41 | B48: DTE | D48: Recaptured Image Detection using Moire Pattern | E48: Detect and flag Moiré patterns in submitted images to identify potential manipulation and prevent fraudulent execution verification. | F48: Detect and flag Moiré patterns in submitted images to identify potential manipulation and prevent fraudulent execution verification. | H48: Ahmad/Jeffry | K48: Sprint 9 | L48: 2 | M48: 5
A49: =A48+1 -> 42 | B49: AMO Existing | D49: AMO existing belum memiliki feature yang sama dengan AMO Plus | E49: AMO existing dengan feature yang sama dengan AMO Plus, sehingga tidak harus online ketika digunakan | F49: AMO Existing bisa digunakan dengan AYO Mitra yang baru. Fitur yang ada di AMO Plus dapat digunakan pada AMO Existing | H49: Sri P | K49: Lintas Sprint 8 | L49: 0 | M49: 0
A50: =A49+1 -> 43 | B50: AYO Kasir | D50: Enable AYO Kasir Web Version to be fully operated in IOS based device (All Pages) | E50: AYO Kasir responsive (phase 2) - Compatibility in mobile version (web) | F50: Enable AYO Kasir web to be accessed in mobile browser | H50: Ida/Adnan | K50: Lintas Sprint 8 | L50: 0 | M50: 1 | S50: In progress sharing requirement
A51: =A50+1 -> 44 | B51: AYO Kasir | D51: Improve ORF accuracy by each touchpoint to ensure sufficient inventory management & security | E51: AYO Kasir - ORF Warehouse Replenishment - Jira (Phase 3) - PKM ORF | F51: AYO Kasir to be automatically provide ORF Qty recommendation for each touchpoints/coach based on Sales historical & current stock | H51: Ida/Adnan | K51: Lintas Sprint 8 | L51: 0 | M51: 2 | S51: In progress finalization
A52: =A51+1 -> 45 | B52: AYO Kasir | D52: Offline mode AYO Kasir & data synchronization (to SAP & DCE) ability | E52: Allow AYO Kasir to go with offline mode during network limitation and allow data synchronization when back to online | F52: Feature to enable AYO Kasir to be used in offline mode. Usually applicable for events, where there's no signal | H52: Ida/Adnan | K52: Lintas Sprint 8 | L52: 0 | M52: 3 | S52: Done sharing requirement
A53: =A52+1 -> 46 | B53: AYO Kasir | D53: Separate product stock for each inventory type (similar to DCE) | E53: Stock categories - sellable & non-sellable - Guided Trial - Replacement - Display Stock - Trade in | F53: Replicate DCE (CEGID & CeApp), dimana stock untuk product sellable dan non-sellable (product demo stock, display, broken device from replacement, trade in) tidak tercampur menjadi satu, memastikan proses disposal & return ke WH termasuk financial record nya bisa tepat & akurat | H53: Ida/Adnan | K53: Lintas Sprint 8 | L53: 0 | M53: 4 | S53: In progress finalization
A54: =A53+1 -> 47 | B54: AYO Mitra | D54: Cluster mapping | E54: Capability AYO Mitra Plus untuk export dan import hasil clutering agar memudahkan proses revisi cluster. (akan dihandle dari principal dan internal HMS bisa suggest cluster via principal) Untuk new customer akan ikut ditarik datanya dan ada flagging "new" (tersedia di mid aug) Jika PIC melakukan update Skenario : jika zone melakukan update panel di CT, maka data panel yang baru akan ikut ditarik | F54: Capability AYO Mitra Plus untuk export dan import hasil clutering agar memudahkan proses revisi cluster. Untuk new customer akan ikut ditarik datanya dan ada flagging "new". Skenario : jika zone melakukan update panel di CT, maka data panel yang baru akan ikut ditarik | H54: Sri P | K54: Lintas Sprint 8 | L54: 0 | M54: 0
A55: =A54+1 -> 48 | B55: AYO Mitra | D55: Cluster mapping | E55: - Jika ada update panel di CT, maka panel baru tersebut akan secara otomatis terassign ke PG di AYO Mitra. '- Panel baru akan diassignkan ke PG terdekat. Hasil clustering bisa dilihat CT (misal di Retailer Mapping ada PG ID nya), sehingga bisa dijadikan bahan review | F55: - Jika ada update panel CITA di CT, maka panel baru tersebut akan secara otomatis terassign ke PG di AYO Mitra. - panel baru akan diassignkan ke PG terdekat. Hasil clustering bisa dilihat CT (misal di Retailer Mapping ada PG ID nya), sehingga bisa dijadikan bahan review | H55: Sri P | K55: Lintas Sprint 8 | L55: 0 | M55: 0
A56: =A55+1 -> 49 | B56: AYO Qoncierge Coach | D56: 1. Reduce expenses up to ~30mio/month (to pay igooana) 2. Ensure daily operational task in TP running well (from attendance, overtime, training, etc.) 3. Manage and own the data for seamless integration and analysis related to the manpower | E56: 1. user management for direct retail 2. touchpoint database 3. shift management, assignment & attendance survey/quiz 4. OPEX assessment 5. notifikasi/reminder 6. training module | F56: Build features for coach to ensure operational excellence in touchpoint direct retail, and for DR Ops to process and analyze the data related to manpower | H56: Ida/Adnan | K56: Lintas Sprint 8 | L56: 0 | M56: 0
A57: =A56+1 -> 50 | B57: DTE | D57: Streamlining coin approval process to become more efficient | E57: Change Process Flow - Coins Approval | F57: Currently, when user conduct RFT or Transfer to Pojok Bayar the process is very lengthy. Through this initiative, we propose a way on how to ensure this process can be conducted in more efficient manner. Approval from related Departments have already been secured. | H57: Hanif/Jess | K57: Lintas Sprint 8 | M57: 0
A58: =A57+1 -> 51 | B58: DTE | D58: DTE Avatar Entry Point | E58: New entry point for Mission Performance and Mission Guidance video | F58: New entry point for Mission Performance and Mission Guidance video | H58: Hanif/Jess | K58: Lintas Sprint 8 | M58: 0
A59: CI | B59: CI | C59: CI | D59: CI | E59: CI | F59: CI | G59: CI | H59: CI | I59: CI | J59: CI | K59: CI | L59: CI | M59: CI | N59: CI | O59: CI | P59: CI | Q59: CI | R59: CI | S59: CI | T59: CI | U59: CI | V59: CI | W59: CI | X59: CI | Y59: CI | Z59: CI | AA59: CI
